Workbook

Sheet Base de datos
A1: ID | B1: Proveedor | C1: Nombre ingrediente | D1: Formato compra | E1: Unidad de compra | F1: Precio formato compra | G1: Unidad Producto | H1: Precio Unidad Producto | I1: NOTAS
A2: 1 | B2: ADL | C2: Aceite Adl Alto Oleico 60% | D2: 25 | E2: Litro | F2: 45.8 | G2: Litro | H2: =F2/D2 -> 1.832
A3: =A2+1 -> 2 | B3: ADL | C3: Aceite de girasol Adl | D3: 25 | E3: Litro | F3: 37.95 | G3: Litro | H3: =F3/D3 -> 1.518
A4: =A3+1 -> 3 | B4: ADL | C4: ATUN EN ACEITE VEGETAL | D4: 1 | E4: Kg | F4: 5.75 | G4: Kg | H4: =F4/D4 -> 5.75
A5: =A4+1 -> 4 | B5: R2R | C5: BACON LONCHEADO 25 | D5: 1 | E5: Kg | F5: =5.07-(5.07*5%) -> 4.8165 | G5: Kg | H5: =F5/D5 -> 4.8165 | I5: %rappel aplicado
A6: =A5+1 -> 5 | B6: Neron | C6: bolsa lata delivery | D6: 250 | E6: Unidad | F6: 25 | G6: Unidad | H6: =F6/D6 -> 0.1
A7: =A6+1 -> 6 | B7: LUXBOX | C7: Bolsa personalizada | D7: 1 | E7: Unidad | F7: 0.243 | G7: Unidad | H7: =F7/D7 -> 0.243
A8: =A7+1 -> 7 | B8: Neron | C8: Bolsas AMERICANA GRANDE 25x15x43,5 | D8: 250 | E8: Unidad | F8: 31.15 | G8: Unidad | H8: =F8/D8 -> 0.1246
A9: =A8+1 -> 8 | B9: Neron | C9: Bolsas AMERICANA UNITARIA 18x34x11 | D9: 500 | E9: Unidad | F9: 37.97 | G9: Unidad | H9: =F9/D9 -> 0.07594
A10: =A9+1 -> 9 | B10: Neron | C10: CAJA BOX 780 | D10: 500 | E10: Kg | F10: 89.49 | H10: =F10/D10 -> 0.17898 | I10: la caja contiene 10 tiras de 50 unidades
A11: =A10+1 -> 10 | B11: Neron | C11: CAJA Burger blanca 234.18 | D11: 500 | E11: Kg | F11: 40.14 | H11: =F11/D11 -> 0.08028
A12: =A11+1 -> 11 | B12: LUXBOX | C12: Caja personalizada | D12: 1 | E12: Kg | F12: 0.261 | H12: =F12/D12 -> 0.261
A13: =A12+1 -> 12 | B13: BIENVENIDO CARNICAS | C13: CARNE B. | D13: 1 | E13: Kg | F13: =9/1.1 -> 8.1818182 | H13: =F13/D13 -> 8.1818182
A14: =A13+1 -> 13 | B14: MAKRO | C14: CEBOLLA CARAMELIZADA | D14: 0.9 | E14: Kg | F14: 5.62 | H14: =F14/D14 -> 6.2444444
A15: =A14+1 -> 14 | B15: BAREA | C15: CEBOLLA CRUJIENTE | D15: 0.5 | E15: Kg | F15: 3.47 | H15: =F15/D15 -> 6.94
A16: =A15+1 -> 15 | B16: F.CUEVAS | C16: CEBOLLA DULCE BLANCA | E16: Kg | H16: =F16/D16 -> #DIV/0!
A17: =A16+1 -> 16 | B17: MERCA | C17: CEBOLLA DULCE BLANCA | E17: Kg | H17: =F17/D17 -> #DIV/0!
A18: =A17+1 -> 17 | B18: F.CUEVAS | C18: CEBOLLA MORADA | E18: Kg | H18: =F18/D18 -> #DIV/0!
A19: =A18+1 -> 18 | B19: MERCA | C19: CEBOLLA MORADA | E19: Kg | H19: =F19/D19 -> #DIV/0!
A20: =A19+1 -> 19 | B20: R2R | C20: Chedar LONCHA R2R | D20: 8 | E20: Kg | F20: 80 | H20: =F20/D20 -> 10 | I20: no usado
A21: =A20+1 -> 20 | B21: SOLLERO | C21: CHEDDAR LIQUIDO SOLLERO | D21: 3 | E21: Kg | F21: 18.05 | H21: =F21/D21 -> 6.0166667
A22: =A21+1 -> 21 | B22: LA FUENTE | C22: CHEDDAR LONCHA LA FUENTE | D22: 1 | E22: Kg | F22: 8.56 | H22: =F22/D22 -> 8.56
A23: =A22+1 -> 22 | B23: LA FUENTE | C23: GOUDA LONCHA LA FUENTE | D23: 1 | F23: 7.11 | H23: =F23/D23 -> 7.11
A24: =A23+1 -> 23 | B24: LA FUENTE | C24: CHEDDAR SALSA LA FUENTE | D24: 3 | E24: Kg | F24: 13.17 | H24: =F24/D24 -> 4.39
A25: =A24+1 -> 24 | B25: SOLLERO | C25: CHEDDAR SOLLERO 25 | D25: 1 | E25: Kg | F25: 8.56 | H25: =F25/D25 -> 8.56
A26: =A25+1 -> 25 | B26: LAFUENTE | C26: RULO DE CABRA ORIGINAL LA FUENTE | D26: 1 | F26: 11.9 | H26: =F26/D26 -> 11.9
A27: =A26+1 -> 26 | B27: LAFUENTE | C27: RULO MEZCLA MADURADO LAFUENTE | D27: 1 | F27: 7.99 | H27: =F27/D27 -> 7.99
A28: =A27+1 -> 27 | B28: LAFUENTE | C28: CHEDDAR LONCHA ROJO LAFUENTE | D28: 1 | F28: 7.55 | H28: =F28/D28 -> 7.55
A29: =A28+1 -> 28 | B29: RAULFONT | C29: ENVASE BURG. SOFI | D29: 20000 | E29: Unidad | F29: =1746*2 -> 3492 | G29: Unidad | H29: =F29/D29 -> 0.1746
A30: =A29+1 -> 29 | B30: Neron | C30: ENVASE SERRANO IP10 .25 | D30: 50 | E30: Unidad | F30: 9.73 | G30: Unidad | H30: =F30/D30 -> 0.1946
A31: =A30+1 -> 30 | B31: ESPECIAS GRANADO | C31: ESPECIAS GRANADO POLLO ASADO | D31: 1 | E31: Kg | F31: 7 | H31: =F31/D31 -> 7
A32: =A31+1 -> 31 | B32: R2R | C32: FRANKFURT | D32: 15 | E32: Unidad | F32: =11.25-(11.25*5%) -> 10.6875 | H32: =F32/D32 -> 0.7125 | I32: % rappel aplicado
A33: =A32+1 -> 32 | B33: GRANJA S.A. | C33: CLARA LIQUIDA GRANJA | D33: 1 | F33: 2.5 | H33: =F33/D33 -> 2.5
A34: =A33+1 -> 33 | B34: Neron | C34: CAJA BOX 780 NEGRA OFERTA | D34: 500 | E34: Kg | F34: 70 | H34: =F34/D34 -> 0.14 | I34: la caja contiene 10 tiras de 50 unidades, OFERTA LIMITADA
A35: =A34+1 -> 34 | B35: GRANJA S.A. | C35: HUEVO LÍQUIDO GRANJA | D35: 1 | E35: Litro | F35: 3.75 | G35: Litro | H35: =F35/D35 -> 3.75
A36: =A35+1 -> 35 | B36: GRANJA S.A. | C36: HUEVO CASCARA | D36: 20 | E36: Unidad | F36: 2.9 | H36: =F36/D36 -> 0.145
A37: =A36+1 -> 36 | B37: R2R | C37: JALAPEÑOS | D37: 1 | E37: Kg | F37: 1.1 | H37: =F37/D37 -> 1.1
A38: =A37+1 -> 37 | B38: BAREA | C38: JAMON LONCHEADO CUMBRE IB. | D38: 1 | E38: Kg | F38: 7 | G38: Kg | H38: =F38/D38 -> 7
A39: =A38+1 -> 38 | B39: AVINATUR | C39: LAGRIMITAS | D39: 1 | E39: Kg | F39: 6 | H39: =F39/D39 -> 6
A40: =A39+1 -> 39 | B40: F.CUEVAS | C40: LECHUGA LOLLO CUEVAS | D40: 1 | E40: Kg | F40: 1.04 | H40: =F40/D40 -> 1.04
A41: =A40+1 -> 40 | B41: NERON | C41: Bolsa Serrano ROAST
A42: =A41+1 -> 41 | B42: MAKRO | C42: MERMELADA DE PIMIENTO | D42: 0.8 | E42: Kg | F42: 6.02 | G42: Kg | H42: =F42/D42 -> 7.525
A43: =A42+1 -> 42 | B43: TAPIA | C43: NUGGETS POLLO PRIELA | D43: 1 | E43: Kg | F43: 7.2 | H43: =F43/D43 -> 7.2
A44: =A43+1 -> 43 | B44: BIENVENIDO CARNICAS | C44: Paleta | D44: 1 | E44: Kg | F44: 5.8 | H44: =F44/D44 -> 5.8
A45: =A44+1 -> 44 | B45: RICKY | C45: Pan baguette | D45: 55 | E45: Unidad | F45: 14.51 | G45: Unidad | H45: =F45/D45 -> 0.26381818
A46: =A45+1 -> 45
A47: =A46+1 -> 46 | B47: R2R | C47: PAN BRIOCHE 25 | D47: 24 | E47: Kg | F47: =8.99-(8.99*5%) -> 8.5405 | H47: =F47/D47 -> 0.35585417 | I47: % rappel aplicado
A48: =A47+1 -> 47 | B48: R2R | C48: PAN BRIOCHE PERRITO | D48: 30 | E48: Kg | F48: =17.7-(17.7*5%) -> 16.815 | H48: =F48/D48 -> 0.5605 | I48: % rappel aplicado
A49: =A48+1 -> 48
A50: =A49+1 -> 49
A51: =A50+1 -> 50 | B51: LUZBOX | C51: papel personalizado | D51: 0.03 | E51: Kg | H51: 0.03
A52: =A51+1 -> 51 | B52: TAPIA | C52: Patata surecrisp 10/10 MAX | D52: 1 | E52: Kg | F52: 2.35 | H52: =F52/D52 -> 2.35
A53: =A52+1 -> 52
A54: =A53+1 -> 53
A55: =A54+1 -> 54
A56: =A55+1 -> 55 | B56: TAPIA | C56: PATATAS FRY & DIP | D56: 2.5 | E56: Kg | F56: 5.875 | H56: =F56/D56 -> 2.35
A57: =A56+1 -> 56
A58: =A57+1 -> 57
A59: =A58+1 -> 58 | B59: LLINARES | C59: PATATAS FRY & DIP 25 | D59: 1 | E59: Kg | F59: 2.15 | G59: Kg | H59: =F59/D59 -> 2.15
A60: =A59+1 -> 59
A61: =A60+1 -> 60
A62: =A61+1 -> 61
A63: =A62+1 -> 62 | B63: TAPIA | C63: PECHUGA EMPANADA 25 | D63: 1 | E63: Kg | F63: 5.6 | H63: =F63/D63 -> 5.6
A64: =A63+1 -> 63 | B64: SADA | C64: PECHUGA POLLO FILETEADA 25 SADA | D64: 1 | E64: Kg | F64: 6.15 | H64: =F64/D64 -> 6.15
A65: =A64+1 -> 64
A66: =A65+1 -> 65
A67: =A66+1 -> 66
A68: =A67+1 -> 67 | B68: MAKRO | C68: PEPINILLOS | D68: 1.9 | E68: Kg | F68: 11.49 | H68: =F68/D68 -> 6.0473684
A69: =A68+1 -> 68
A70: =A69+1 -> 69 | B70: Neron | C70: Petaca patatas | D70: 1200 | E70: Unidad | F70: 84.65 | G70: Unidad | H70: =F70/D70 -> 0.070541667
A71: =A70+1 -> 70
A72: =A71+1 -> 71
A73: =A72+1 -> 72 | B73: CUEVA | C73: PIMIENTO | D73: 1 | E73: Kg | F73: 2 | H73: =F73/D73 -> 2
A74: =A73+1 -> 73
A75: =A74+1 -> 74 | B75: SOFI | C75: POLLO ASADO | D75: 1.3 | E75: Kg | F75: 8 | H75: =F75/D75 -> 6.1538462
A76: =A75+1 -> 75 | B76: AVINATUR | C76: POLLO ASADO CRUDO AVINATUR | D76: 1.3 | E76: Kg | F76: 2.9 | H76: =F76/D76 -> 2.2307692
A77: =A76+1 -> 76 | B77: SADA | C77: POLLO ASADO CRUDO SADA | D77: 1.3 | E77: Kg | F77: 2.9 | H77: =F77/D77 -> 2.2307692
A78: =A77+1 -> 77 | B78: TAPIA | C78: POLLO CRISPY SIMON(CRUJIPOLLO) | D78: 1 | E78: Kg | F78: 6 | H78: =F78/D78 -> 6
A79: =A78+1 -> 78 | B79: R2R | C79: PULLED PORK | D79: 6 | E79: Kg | F79: =52.61-(53.61*5%) -> 49.9295 | G79: Kg | H79: =F79/D79 -> 8.3215833 | I79: % rappel aplicado
A80: =A79+1 -> 79
A81: =A80+1 -> 80 | B81: SOLLERO | C81: Queso GOUDA SOLLERO | D81: 6.66 | E81: Kg | H81: =F81/D81 -> 0
A82: =A81+1 -> 81 | B82: Elaboracion | C82: Salsa agria | E82: Kg | H82: =F82/D82 -> #DIV/0!
A83: =A82+1 -> 82
A84: =A83+1 -> 83 | B84: BAREA | C84: SALSA BBQ BAREA | D84: 1.85 | E84: Kg | F84: 3.03 | H84: =F84/D84 -> 1.6378378
A85: =A84+1 -> 84 | B85: R2R | C85: SALSA BBQ WHISKY | D85: 2 | E85: Kg | F85: 10.9 | H85: =F85/D85 -> 5.45 | I85: NO USADO
A86: =A85+1 -> 85 | B86: Elaboracion | C86: salsa emily | E86: Kg | H86: =F86/D86 -> #DIV/0!
A87: =A86+1 -> 86 | B87: Elaboracion | C87: salsa mayobacon | D87: 5 | E87: Kg | H87: =F87/D87 -> 0
A88: =A87+1 -> 87 | B88: Elaboracion | C88: Salsa mayonesa | D88: 1.7 | E88: Kg | H88: =F88/D88 -> 0
A89: =A88+1 -> 88 | B89: MAKRO | C89: SALSA MOSTAZA MIEL | D89: 1.71 | E89: Kg | F89: 7.95 | H89: =F89/D89 -> 4.6491228
A90: =A89+1 -> 89 | B90: Elaboracion | C90: Salsa oculto | E90: Kg | H90: =F90/D90 -> #DIV/0!
A91: =A90+1 -> 90 | B91: Elaboracion | C91: Salsa tomate | E91: Kg | H91: =F91/D91 -> #DIV/0!
A92: =A91+1 -> 91 | B92: Elaboracion | C92: Salsa trufada | E92: Kg | H92: =F92/D92 -> #DIV/0!
A93: =A92+1 -> 92 | B93: Elaboracion | C93: TARTA LOTUS | D93: 1 | F93: 1.43 | H93: =F93/D93 -> 1.43
A94: =A93+1 -> 93 | B94: BAREA | C94: SERVILLETA 40X40 100UD | D94: 100 | E94: Unidad | F94: 2.77 | G94: Unidad | H94: =F94/D94 -> 0.0277
A95: =A94+1 -> 94 | B95: F.CUEVAS | C95: SETAS | E95: Kg | H95: =F95/D95 -> #DIV/0!
A96: =A95+1 -> 95 | B96: ARCOS IBERICOS | C96: TARTAS QUESO | D96: 1 | E96: Unidad | F96: 4.3 | G96: Unidad | H96: =F96/D96 -> 4.3
A97: =A96+1 -> 96 | B97: F.CUEVAS | C97: TOMATE DANIELA | D97: 1 | E97: Kg | F97: 1.8 | G97: Kg | H97: =F97/D97 -> 1.8
A98: =A97+1 -> 97 | B98: ARCOS IBERICOS | C98: TARTAS DUBAI | D98: 1 | E98: Unidad | F98: 4.3 | G98: Unidad | H98: =F98/D98 -> 4.3
A99: =A98+1 -> 98 | B99: mercadona | C99: TRUFA | D99: 0.08 | E99: Kg | F99: 4 | H99: =F99/D99 -> 50
A100: =A99+1 -> 99 | B100: MAKRO | C100: Salsa TRUFADA Makro | D100: 0.5 | E100: Kg | F100: 5.39 | H100: =F100/D100 -> 10.78
...

Sheet RESUMEN DE COSTES
I1: =SUM(I3:I59) -> 7524
A2: Familia | B2: Producto | C2: Coste € | D2: PVP sin IVA | E2: PVP Actual | F2: MARGEN € | G2: MARGEN % | H2: Coste % | I2: Unidades Vendidas | J2: Peso venta %
A3: Bocadillos | B3: =BOCATAS!D2 -> SIMPLE DE POLLO | C3: =BOCATAS!L6 -> 1.4018182 | D3: =BOCATAS!L8 -> 3.6363636 | E3: =D3*1.1 -> 4 | F3: =D3-C3 -> 2.2345455 | G3: =BOCATAS!L11 -> 61.45 | H3: =BOCATAS!L10 -> 38.55 | I3: 163 | J3: =I3/SUM($I$3:I201)*100 -> 2.1664009
A4: Bocadillos | B4: SIMPLE ASADO | C4: =BOCATAS!L34 -> 1.3407028 | D4: =BOCATAS!L36 -> 5 | E4: =D4*1.1 -> 5.5 | F4: =D4-C4 -> 3.6592972 | G4: =100-H4 -> 73.185944 | H4: =C4/D4*100 -> 26.814056 | I4: 33 | J4: =I4/SUM($I$3:I202)*100 -> 0.43859649
A5: Bocadillos | B5: SIMPLE EMPANADO | C5: =BOCATAS!L20 -> 1.3413182 | D5: =BOCATAS!L22 -> 4.5454545 | E5: =D5*1.1 -> 5 | F5: =D5-C5 -> 3.2041364 | G5: =100-H5 -> 70.491 | H5: =C5/D5*100 -> 29.509 | I5: 31 | J5: =I5/SUM($I$3:I203)*100 -> 0.41201489
A6: Bocadillos | B6: SIMPLE SOLOMILO | C6: =BOCATAS!L48 -> 1.2743182 | D6: =BOCATAS!L50 -> 4.5454545 | E6: =D6*1.1 -> 5 | F6: =D6-C6 -> 3.2711364 | G6: =100-H6 -> 71.965 | H6: =C6/D6*100 -> 28.035 | I6: 19 | J6: =I6/SUM($I$3:I204)*100 -> 0.25252525
A7: Bocadillos | B7: VEGETAL POLLO | C7: =BOCATAS!L63 -> 1.3687182 | D7: =BOCATAS!L65 -> 4.5454545 | E7: =D7*1.1 -> 5 | F7: =D7-C7 -> 3.1767364 | G7: =100-H7 -> 69.8882 | H7: =C7/D7*100 -> 30.1118 | I7: 218 | J7: =I7/SUM($I$3:I205)*100 -> 2.897395
A8: Bocadillos | B8: VEGETAL POLLO ASADO | C8: =BOCATAS!L95 -> 1.3691028 | D8: =BOCATAS!L97 -> 5.9090909 | E8: =D8*1.1 -> 6.5 | F8: =D8-C8 -> 4.5399881 | G8: =100-H8 -> 76.830568 | H8: =C8/D8*100 -> 23.169432 | I8: 173 | J8: =I8/SUM($I$3:I206)*100 -> 2.2993089
A9: Bocadillos | B9: VEGETAL EMPANADO | C9: =BOCATAS!L113 -> 1.3137182 | D9: =BOCATAS!L115 -> 4.5454545 | E9: =D9*1.1 -> 5 | F9: =D9-C9 -> 3.2317364 | G9: =100-H9 -> 71.0982 | H9: =C9/D9*100 -> 28.9018 | I9: 25 | J9: =I9/SUM($I$3:I207)*100 -> 0.33227007
A10: Bocadillos | B10: VEGETAL ATUN | C10: =BOCATAS!L79 -> 1.3287182 | D10: =BOCATAS!L81 -> 4.5454545 | E10: =D10*1.1 -> 5 | F10: =D10-C10 -> 3.2167364 | G10: =100-H10 -> 70.7682 | H10: =C10/D10*100 -> 29.2318 | I10: 35 | J10: =I10/SUM($I$3:I208)*100 -> 0.4651781
A11: Bocadillos | B11: BARBARA | C11: =BOCATAS!L131 -> 1.7153182 | D11: =BOCATAS!L133 -> 4.5454545 | E11: =D11*1.1 -> 5 | F11: =D11-C11 -> 2.8301364 | G11: =100-H11 -> 62.263 | H11: =C11/D11*100 -> 37.737 | I11: 249 | J11: =I11/SUM($I$3:I209)*100 -> 3.3094099
A12: Bocadillos | B12: CRISTIAN | C12: =BOCATAS!L147 -> 1.5238482 | D12: =BOCATAS!L149 -> 6.3636364 | E12: =D12*1.1 -> 7 | F12: =D12-C12 -> 4.8397882 | G12: =100-H12 -> 76.053814 | H12: =C12/D12*100 -> 23.946186 | I12: 188 | J12: =I12/SUM($I$3:I210)*100 -> 2.4986709
A13: Bocadillos | B13: JAKINIÑO | C13: =BOCATAS!L185 -> 1.8190482 | D13: =BOCATAS!L187 -> 7.2727273 | E13: =D13*1.1 -> 8 | F13: =D13-C13 -> 5.4536791 | G13: =100-H13 -> 74.988088 | H13: =C13/D13*100 -> 25.011913 | I13: 374 | J13: =I13/SUM($I$3:I211)*100 -> 4.9707602
A14: Bocadillos | B14: GUARRITO | C14: =BOCATAS!L166 -> 1.5106482 | D14: =BOCATAS!L168 -> 6.3636364 | E14: =D14*1.1 -> 7 | F14: =D14-C14 -> 4.8529882 | G14: =100-H14 -> 76.261243 | H14: =C14/D14*100 -> 23.738757 | I14: 197 | J14: =I14/SUM($I$3:I212)*100 -> 2.6182881
A16: SERRANITOS | B16: SERRANO EMPANADO | C16: =SERRANOS!L34 -> 1.5666182 | D16: =SERRANOS!L36 -> 5.9090909 | E16: =D16*1.1 -> 6.5 | F16: =D16-C16 -> 4.3424727 | G16: =100-H16 -> 73.488 | H16: =C16/D16*100 -> 26.512 | I16: 183 | J16: =I16/SUM($I$3:I214)*100 -> 2.4322169
A17: SERRANITOS | B17: SERRANO POLLO | C17: =SERRANOS!L6 -> 1.6271182 | D17: =SERRANOS!L8 -> 5.4545455 | E17: =D17*1.1 -> 6 | F17: =D17-C17 -> 3.8274273 | G17: =100-H17 -> 70.1695 | H17: =C17/D17*100 -> 29.8305 | I17: 1105 | J17: =I17/SUM($I$3:I215)*100 -> 14.686337
A18: SERRANITOS | B18: SERRANO POLLO ASADO | C18: =SERRANOS!L63 -> 1.5660028 | D18: =SERRANOS!L65 -> 5.9090909 | E18: =D18*1.1 -> 6.5 | F18: =D18-C18 -> 4.3430881 | G18: =100-H18 -> 73.498414 | H18: =C18/D18*100 -> 26.501586 | I18: 357 | J18: =I18/SUM($I$3:I216)*100 -> 4.7448166
A19: SERRANITOS | B19: SERRANO SOLOMILLO | C19: =SERRANOS!L92 -> 1.4996182 | D19: =SERRANOS!L94 -> 6.3636364 | E19: =D19*1.1 -> 7 | F19: =D19-C19 -> 4.8640182 | G19: =100-H19 -> 76.434571 | H19: =C19/D19*100 -> 23.565429 | I19: 270 | J19: =I19/SUM($I$3:I217)*100 -> 3.5885167
A20: SERRANITOS | B20: SERRANO PULLED PORK | C20: =SERRANOS!L121 -> 1.7827765 | D20: =SERRANOS!L123 -> 7.2727273 | E20: =D20*1.1 -> 8 | F20: =D20-C20 -> 5.4899508 | G20: =100-H20 -> 75.486823 | H20: =C20/D20*100 -> 24.513177 | J20: =I20/SUM($I$3:I218)*100 -> 0
A22: BRIOCHES | B22: XMAS CHIKEN | C22: ='BRIOCH-SUBS'!L177 -> 2.0977582 | D22: ='BRIOCH-SUBS'!L179 -> 9 | E22: =D22*1.1 -> 9.9 | F22: =D22-C22 -> 6.9022418 | G22: =100-H22 -> 76.691575 | H22: =C22/D22*100 -> 23.308425
A23: BRIOCHES | B23: CESAR BRIOCHE | C23: ='BRIOCH-SUBS'!L149 -> 1.98895 | D23: ='BRIOCH-SUBS'!L151 -> 7.7272727 | E23: =D23*1.1 -> 8.5 | F23: =D23-C23 -> 5.7383227 | G23: =100-H23 -> 74.260647 | H23: =C23/D23*100 -> 25.739353 | I23: 15 | J23: =I23/SUM($I$3:I221)*100 -> 0.19936204
A24: BRIOCHES | B24: GYPSY | C24: ='BRIOCH-SUBS'!L64 -> 1.9596667 | D24: ='BRIOCH-SUBS'!L66 -> 7.2727273 | E24: =D24*1.1 -> 8 | F24: =D24-C24 -> 5.3130606 | G24: =100-H24 -> 73.054583 | H24: =C24/D24*100 -> 26.945417 | I24: 71 | J24: =I24/SUM($I$3:I222)*100 -> 0.943647
A25: BRIOCHES | B25: CHICKEN FRIED | C25: ='BRIOCH-SUBS'!L6 -> 1.9732002 | D25: ='BRIOCH-SUBS'!L8 -> 7.2727273 | E25: =D25*1.1 -> 8 | F25: =D25-C25 -> 5.2995271 | G25: =100-H25 -> 72.868498 | H25: =C25/D25*100 -> 27.131502 | I25: 210 | J25: =I25/SUM($I$3:I223)*100 -> 2.7910686
A26: BRIOCHES | B26: CHEESE STEAK | C26: ='BRIOCH-SUBS'!L35 -> 2.3676979 | D26: ='BRIOCH-SUBS'!L37 -> 7.2727273 | E26: =D26*1.1 -> 8 | F26: =D26-C26 -> 4.9050294 | G26: =100-H26 -> 67.444154 | H26: =C26/D26*100 -> 32.555846 | J26: =I26/SUM($I$3:I224)*100 -> 0
A27: BRIOCHES | B27: SMASH SERRANO | C27: ='BRIOCH-SUBS'!L93 -> 1.9800455 | D27: ='BRIOCH-SUBS'!L95 -> 7.2727273 | E27: =D27*1.1 -> 8 | F27: =D27-C27 -> 5.2926818 | G27: =100-H27 -> 72.774375 | H27: =C27/D27*100 -> 27.225625 | I27: 144 | J27: =I27/SUM($I$3:I225)*100 -> 1.9138756
A30: BURGER | B30: CRUJIPOLLO BBQ | C30: =BURGERS!L239 -> 1.8604959 | D30: =BURGERS!L241 -> 7.2727273 | E30: =D30*1.1 -> 8 | F30: =D30-C30 -> 5.4122314 | G30: =100-H30 -> 74.418182 | H30: =C30/D30*100 -> 25.581818 | I30: 131 | J30: =I30/SUM($I$3:I228)*100 -> 1.7410952
A31: BURGER | B31: CRUJIPOLLO ORIGINAL | C31: =BURGERS!L269 -> 1.5300542 | D31: =BURGERS!L271 -> 6.3636364 | E31: =D31*1.1 -> 7 | F31: =D31-C31 -> 4.8335822 | G31: =100-H31 -> 75.956292 | H31: =C31/D31*100 -> 24.043708 | I31: 98 | J31: =I31/SUM($I$3:I229)*100 -> 1.3024987
A32: BURGER | B32: MAKA | C32: =BURGERS!L151 -> 2.2052973 | D32: =BURGERS!L153 -> 9 | E32: =D32*1.1 -> 9.9 | F32: =D32-C32 -> 6.7947027 | G32: =100-H32 -> 75.496696 | H32: =C32/D32*100 -> 24.503304 | I32: 210 | J32: =I32/SUM($I$3:I230)*100 -> 2.7910686
A33: BURGER | B33: BICHOTA | C33: =BURGERS!L180 -> 2.1501303 | D33: =BURGERS!L182 -> 9.0909091 | E33: =D33*1.1 -> 10 | F33: =D33-C33 -> 6.9407788 | G33: =100-H33 -> 76.348567 | H33: =C33/D33*100 -> 23.651433 | I33: 532 | J33: =I33/SUM($I$3:I231)*100 -> 7.0707071
A34: BURGER | B34: DADDY | C34: =BURGERS!L209 -> 2.5895738 | D34: =BURGERS!L211 -> 10 | E34: =D34*1.1 -> 11 | F34: =D34-C34 -> 7.4104262 | G34: =100-H34 -> 74.104262 | H34: =C34/D34*100 -> 25.895738 | J34: =I34/SUM($I$3:I232)*100 -> 0
A35: BURGER | B35: DOBLE QUESOS | C35: =BURGERS!L6 -> 2.1871023 | D35: =BURGERS!L8 -> 7.2727273 | E35: =D35*1.1 -> 8 | F35: =D35-C35 -> 5.0856249 | G35: =100-H35 -> 69.927343 | H35: =C35/D35*100 -> 30.072657 | I35: 781 | J35: =I35/SUM($I$3:I233)*100 -> 10.380117
A36: BURGER | B36: CERO15 | C36: =BURGERS!L35 -> 2.3754736 | D36: =BURGERS!L37 -> 7.2727273 | E36: =D36*1.1 -> 8 | F36: =D36-C36 -> 4.8972537 | G36: =100-H36 -> 67.337238 | H36: =C36/D36*100 -> 32.662762 | I36: 525 | J36: =I36/SUM($I$3:I234)*100 -> 6.9776715
A37: BURGER | B37: KAROL | C37: =BURGERS!L122 -> 2.5701467 | D37: =BURGERS!L124 -> 7.2727273 | E37: =D37*1.1 -> 8 | F37: =D37-C37 -> 4.7025805 | G37: =100-H37 -> 64.660482 | H37: =C37/D37*100 -> 35.339518 | J37: =I37/SUM($I$3:I235)*100 -> 0
A38: BURGER | B38: BARRIERA | C38: =BURGERS!L93 -> 2.6506748 | D38: =BURGERS!L95 -> 6.3636364 | E38: =D38*1.1 -> 7 | F38: =D38-C38 -> 3.7129615 | G38: =100-H38 -> 58.346539 | H38: =C38/D38*100 -> 41.653461 | I38: 383 | J38: =I38/SUM($I$3:I236)*100 -> 5.0903775
A39: BURGER | B39: CALLEJERA | C39: =BURGERS!L64 -> 2.4731124 | D39: =BURGERS!L66 -> 9 | E39: =D39*1.1 -> 9.9 | F39: =D39-C39 -> 6.5268876 | G39: =100-H39 -> 72.520973 | H39: =C39/D39*100 -> 27.479027 | I39: 0 | J39: =I39/SUM($I$3:I237)*100 -> 0
A41: ENTRANTES | B41: BOX ALITAS | C41: =ENTRANTES!L34 -> 2.4242067 | D41: =ENTRANTES!L36 -> 5.4545455 | E41: =D41*1.1 -> 6 | F41: =D41-C41 -> 3.0303387 | G41: =100-H41 -> 55.55621 | H41: =C41/D41*100 -> 44.44379 | I41: 85 | J41: =I41/SUM($I$3:I239)*100 -> 1.1297182
A42: ENTRANTES | B42: BOX LAGRIMITAS | C42: =ENTRANTES!L90 -> 1.5589067 | D42: =ENTRANTES!L92 -> 5.4545455 | E42: =D42*1.1 -> 6 | F42: =D42-C42 -> 3.8956387 | G42: =100-H42 -> 71.420044 | H42: =C42/D42*100 -> 28.579956 | I42: 113 | J42: =I42/SUM($I$3:I240)*100 -> 1.5018607
A43: ENTRANTES | B43: BOX NUGGETS | C43: =ENTRANTES!L6 -> 1.8325067 | D43: =ENTRANTES!L8 -> 5.4545455 | E43: =D43*1.1 -> 6 | F43: =D43-C43 -> 3.6220387 | G43: =100-H43 -> 66.404044 | H43: =C43/D43*100 -> 33.595956 | I43: 98 | J43: =I43/SUM($I$3:I241)*100 -> 1.3024987
A44: ENTRANTES | B44: BOX PATATAS | C44: =ENTRANTES!L118 -> 0.91663342 | D44: =ENTRANTES!L120 -> 4.5454545 | E44: =D44*1.1 -> 5 | F44: =D44-C44 -> 3.6288211 | G44: =100-H44 -> 79.834065 | H44: =C44/D44*100 -> 20.165935 | I44: 164 | J44: =I44/SUM($I$3:I242)*100 -> 2.1796917
A45: ENTRANTES | B45: BOX PAPAS PULLED PORK | C45: =ENTRANTES!L174 -> 1.3761221 | D45: =ENTRANTES!L176 -> 6.3636364 | E45: =D45*1.1 -> 7 | F45: =D45-C45 -> 4.9875142 | G45: =100-H45 -> 78.375224 | H45: =C45/D45*100 -> 21.624776 | I45: 91 | J45: =I45/SUM($I$3:I243)*100 -> 1.2094631
A46: ENTRANTES | B46: PETACA PATATA | C46: =ENTRANTES!L146 -> 0.26404167 | D46: =ENTRANTES!L148 -> 1.8181818 | E46: =D46*1.1 -> 2 | F46: =D46-C46 -> 1.5541402 | G46: =100-H46 -> 85.477708 | H46: =C46/D46*100 -> 14.522292 | I46: 60 | J46: =I46/SUM($I$3:I244)*100 -> 0.79744817
A47: ENTRANTES | B47: NEW PATATAS CHEESE BACON
A50: POSTRES | B50: TARTA LOTUS | C50: =POSTRES!L50 -> 1.43 | D50: =POSTRES!L52 -> 5.4545455 | E50: =D50*1.1 -> 6 | F50: =D50-C50 -> 4.0245455 | G50: =100-H50 -> 73.783333 | H50: =C50/D50*100 -> 26.216667 | I50: 44 | J50: =I50/SUM($I$3:I248)*100 -> 0.58479532
A51: POSTRES | B51: TARTA QUESO | C51: =POSTRES!L6 -> 4.3 | D51: =POSTRES!L8 -> 5.4545455 | E51: =D51*1.1 -> 6 | F51: =D51-C51 -> 1.1545455 | G51: =100-H51 -> 21.166667 | H51: =C51/D51*100 -> 78.833333 | I51: 13 | J51: =I51/SUM($I$3:I249)*100 -> 0.17278044
A52: POSTRES | B52: TARTA DUBAI | C52: =POSTRES!L28 -> 4.3 | D52: =POSTRES!L30 -> 5.9090909 | E52: =D52*1.1 -> 6.5 | F52: =D52-C52 -> 1.6090909 | G52: =100-H52 -> 27.230769 | H52: =C52/D52*100 -> 72.769231
A55: HOTDOG | B55: HOTDOG/ PERRITOS SIMPLE | C55: ='BRIOCH-SUBS'!L205 -> 1.7600676 | D55: ='BRIOCH-SUBS'!L207 -> 3.5454545 | E55: ='BRIOCH-SUBS'!L206 -> 3.9 | F55: =D55-C55 -> 1.785387 | G55: =100-H55 -> 50.357069 | H55: =C55/D55*100 -> 49.642931 | I55: 136 | J55: =I55/SUM($I$3:I253)*100 -> 1.8075492
A56: HOTDOG | B56: HOTDOG BACONQUESO | C56: ='BRIOCH-SUBS'!L223 -> 2.0661296 | D56: ='BRIOCH-SUBS'!L225 -> 5.3636364 | E56: ='BRIOCH-SUBS'!L224 -> 5.9 | F56: =D56-C56 -> 3.2975068 | G56: =100-H56 -> 61.47894 | H56: =C56/D56*100 -> 38.52106
A57: HOTDOG | B57: HOTDOG CHILL BBQ | C57: ='BRIOCH-SUBS'!L241 -> 1.8283224 | D57: ='BRIOCH-SUBS'!L243 -> 6.3636364 | E57: ='BRIOCH-SUBS'!L242 -> 7 | F57: =D57-C57 -> 4.535314 | G57: =100-H57 -> 71.269219 | H57: =C57/D57*100 -> 28.730781
A59: BEBIDA | B59: LATA AQUARIOUS LIMON | C59: 0.72791667 | D59: =E59/1.1 -> 1.4545455 | E59: 1.6 | F59: =D59-C59 -> 0.72662879 | G59: =100-H59 -> 49.955729 | H59: =C59/D59*100 -> 50.044271
A60: BEBIDA | B60: LATA AQUARIOUS NARANJA | C60: 0.72791667 | D60: =E60/1.1 -> 1.4545455 | E60: 1.6 | F60: =D60-C60 -> 0.72662879 | G60: =100-H60 -> 49.955729 | H60: =C60/D60*100 -> 50.044271
A61: BEBIDA | B61: LATA COCACOLA | C61: 0.61375 | D61: =E61/1.1 -> 1.3636364 | E61: 1.5 | F61: =D61-C61 -> 0.74988636 | G61: =100-H61 -> 54.991667 | H61: =C61/D61*100 -> 45.008333
A62: BEBIDA | B62: LATA COCACOLA ZERO | C62: 0.61375 | D62: =E62/1.1 -> 1.3636364 | E62: 1.5 | F62: =D62-C62 -> 0.74988636 | G62: =100-H62 -> 54.991667 | H62: =C62/D62*100 -> 45.008333
A63: BEBIDA | B63: LATA COLACOLA ZERO ZERO | C63: 0.61375 | D63: =E63/1.1 -> 1.3636364 | E63: 1.5 | F63: =D63-C63 -> 0.74988636 | G63: =100-H63 -> 54.991667 | H63: =C63/D63*100 -> 45.008333
A64: BEBIDA | B64: LATA FANTA LIMON | C64: 0.52666667 | D64: =E64/1.1 -> 1.3636364 | E64: 1.5 | F64: =D64-C64 -> 0.8369697 | G64: =100-H64 -> 61.377778 | H64: =C64/D64*100 -> 38.622222
A65: BEBIDA | B65: LATA FANTA NARANJA | C65: 0.52666667 | D65: =E65/1.1 -> 1.3636364 | E65: 1.5 | F65: =D65-C65 -> 0.8369697 | G65: =100-H65 -> 61.377778 | H65: =C65/D65*100 -> 38.622222
A66: BEBIDA | B66: LATA FUZEE TEA LIMON | C66: 0.635 | D66: =E66/1.1 -> 1.4545455 | E66: 1.6 | F66: =D66-C66 -> 0.81954545 | G66: =100-H66 -> 56.34375 | H66: =C66/D66*100 -> 43.65625
A67: BEBIDA | B67: LATA FUZEE TEA MARACUYA | C67: 0.635 | D67: =E67/1.1 -> 1.4545455 | E67: 1.6 | F67: =D67-C67 -> 0.81954545 | G67: =100-H67 -> 56.34375 | H67: =C67/D67*100 -> 43.65625
A70: TARROS | B70: TARRITO ALIOLI | C70: ='TARROS SALSA'!L6 -> 0.19187671 | D70: ='TARROS SALSA'!L8 -> 0.45454545 | E70: ='TARROS SALSA'!L7 -> 0.5 | F70: =D70-C70 -> 0.26266874 | G70: =100-H70 -> 57.787124 | H70: =C70/D70*100 -> 42.212876
A71: TARROS | B71: TARRITO MAYONESA | C71: ='TARROS SALSA'!L17 -> 0.13715 | D71: ='TARROS SALSA'!L19 -> 0.45454545 | E71: ='TARROS SALSA'!L18 -> 0.5 | F71: =D71-C71 -> 0.31739545 | G71: =100-H71 -> 69.827 | H71: =C71/D71*100 -> 30.173
A72: TARROS | B72: TARRITO SALSA WISKY | C72: ='TARROS SALSA'!L37 -> 0.10440526 | D72: ='TARROS SALSA'!L39 -> 0.45454545 | E72: =D72*1.1 -> 0.5 | F72: =D72-C72 -> 0.3501402 | G72: =100-H72 -> 77.030843 | H72: =C72/D72*100 -> 22.969157
A73: TARROS | B73: TARRO KETCHUP | C73: ='TARROS SALSA'!L95 -> 0.15006892 | D73: ='TARROS SALSA'!L97 -> 0.45454545 | E73: =D73*1.1 -> 0.5 | F73: =D73-C73 -> 0.30447654 | G73: =100-H73 -> 66.984838 | H73: =C73/D73*100 -> 33.015162
A74: TARROS | B74: TARRITO SALSA BBQ | C74: ='TARROS SALSA'!L56 -> 0.18493378 | D74: ='TARROS SALSA'!L58 -> 0.45454545 | E74: =D74*1.1 -> 0.5 | F74: =D74-C74 -> 0.26961167 | G74: =100-H74 -> 59.314568 | H74: =C74/D74*100 -> 40.685432
A75: TARROS | B75: TARRITO SALSA MOJO PICON | C75: ='TARROS SALSA'!L27 -> 0.18170085 | D75: ='TARROS SALSA'!L29 -> 0.45454545 | E75: =D75*1.1 -> 0.5 | F75: =D75-C75 -> 0.2728446 | G75: =100-H75 -> 60.025813 | H75: =C75/D75*100 -> 39.974187
A76: TARROS | B76: TARRITO SALSA AMERICAN BURGER | C76: ='TARROS SALSA'!L66 -> 0.251575 | D76: ='TARROS SALSA'!L68 -> 0.90909091 | E76: =D76*1.1 -> 1 | F76: =D76-C76 -> 0.65751591 | G76: =100-H76 -> 72.32675 | H76: =C76/D76*100 -> 27.67325
A77: TARROS | B77: TARRITO SALSA TRUFADA | C77: ='TARROS SALSA'!L85 -> 0.16111675 | D77: ='TARROS SALSA'!L87 -> 1.0909091 | E77: =D77*1.1 -> 1.2 | F77: =D77-C77 -> 0.92979234 | G77: =100-H77 -> 85.230964 | H77: =C77/D77*100 -> 14.769036
A78: TARROS | B78: TARRO SALSA BICHOTA | C78: ='TARROS SALSA'!L75 -> 0.12662868 | D78: ='TARROS SALSA'!L77 -> 1.0909091 | E78: =D78*1.1 -> 1.2 | F78: =D78-C78 -> 0.96428041 | G78: =100-H78 -> 88.392371 | H78: =C78/D78*100 -> 11.607629
A79: TARROS | B79: TARRO RANCHERA | C79: ='TARROS SALSA'!L106 -> 0.27821818 | D79: ='TARROS SALSA'!L108 -> 1.0909091 | E79: =D79*1.1 -> 1.2 | F79: =D79-C79 -> 0.81269091 | G79: =100-H79 -> 74.496667 | H79: =C79/D79*100 -> 25.503333
A80: TARROS | B80: TARRO MAYO SRIRACHA | C80: ='TARROS SALSA'!L46 -> 0.57745137 | D80: ='TARROS SALSA'!L48 -> 1.8181818 | E80: =D80*1.1 -> 2 | F80: =D80-C80 -> 1.2407304 | G80: =100-H80 -> 68.240175 | H80: =C80/D80*100 -> 31.759825

Sheet UPSMENUS
L1: 1.5
A2: Familia | B2: Producto | C2: Coste € | D2: PVP sin IVA | E2: PVP Actual | F2: MARGEN € | G2: MARGEN % | H2: Coste % | I2: TARROS | J2: BEBIDAS | K2: COSTE T. | L2: PVP MENU X | M2: PVP sin Iva. | N2: PVP + MENU X | O2: MARGEN € | P2: MARGEN % | Q2: Coste % | R2: DIF. MARGEN | S2: DIF. PVP
A3: Bocadillos | B3: =BOCATAS!D2 -> SIMPLE DE POLLO | C3: =BOCATAS!L6 -> 1.4018182 | D3: =BOCATAS!L8 -> 3.6363636 | E3: =D3*1.1 -> 4 | F3: =D3-C3 -> 2.2345455 | G3: =100-H3 -> 61.45 | H3: =C3/D3*100 -> 38.55 | I3: 0.19187671 | J3: 0.61375 | K3: =I3+J3+C3 -> 2.2074449 | L3: =$L$1/1.1 -> 1.3636364 | M3: =D3+L3 -> 5 | N3: =E3+(L3*1.1) -> 5.5 | O3: =M3-K3 -> 2.7925551 | P3: =100-Q3 -> 55.851102 | Q3: =K3/M3*100 -> 44.148898 | R3: =P3-G3 -> -5.5988978 | S3: =O3-F3 -> 0.55800965 | U3: UBER | V3: SERRANITOS & BAGUETTES by SOFI | W3: 622 | X3: 5543.3
A4: Bocadillos | B4: SIMPLE ASADO | C4: =BOCATAS!L34 -> 1.3407028 | D4: =BOCATAS!L36 -> 5 | E4: =D4*1.1 -> 5.5 | F4: =D4-C4 -> 3.6592972 | G4: =100-H4 -> 73.185944 | H4: =C4/D4*100 -> 26.814056 | I4: 0.19187671 | J4: 0.61375 | K4: =I4+J4+C4 -> 2.1463295 | L4: =$L$1/1.1 -> 1.3636364 | M4: =D4+1.36 -> 6.36 | N4: =E4+(L4*1.1) -> 7 | O4: =M4-K4 -> 4.2136705 | P4: =100-Q4 -> 66.252681 | Q4: =K4/M4*100 -> 33.747319 | R4: =P4-G4 -> -6.9332634 | S4: =O4-F4 -> 0.55437329 | U4: UBER | V4: BURGERS | W4: 426 | X4: 5106.7
A5: Bocadillos | B5: SIMPLE EMPANADO | C5: =BOCATAS!L20 -> 1.3413182 | D5: =BOCATAS!L22 -> 4.5454545 | E5: =D5*1.1 -> 5 | F5: =D5-C5 -> 3.2041364 | G5: =100-H5 -> 70.491 | H5: =C5/D5*100 -> 29.509 | I5: 0.19187671 | J5: 0.61375 | K5: =I5+J5+C5 -> 2.1469449 | L5: =$L$1/1.1 -> 1.3636364 | M5: =D5+1.36 -> 5.9054545 | N5: =E5+(L5*1.1) -> 6.5 | O5: =M5-K5 -> 3.7585097 | P5: =100-Q5 -> 63.644714 | Q5: =K5/M5*100 -> 36.355286 | R5: =P5-G5 -> -6.846286 | S5: =O5-F5 -> 0.55437329 | U5: UBER | V5: NUEVOS SUB´s (BRIOCHES) | W5: 315 | X5: 3454.2
A6: Bocadillos | B6: SIMPLE SOLOMILO | C6: =BOCATAS!L48 -> 1.2743182 | D6: =BOCATAS!L50 -> 4.5454545 | E6: =D6*1.1 -> 5 | F6: =D6-C6 -> 3.2711364 | G6: =100-H6 -> 71.965 | H6: =C6/D6*100 -> 28.035 | I6: 0.19187671 | J6: 0.61375 | K6: =I6+J6+C6 -> 2.0799449 | L6: =$L$1/1.1 -> 1.3636364 | M6: =D6+1.36 -> 5.9054545 | N6: =E6+(L6*1.1) -> 6.5 | O6: =M6-K6 -> 3.8255097 | P6: =100-Q6 -> 64.779258 | Q6: =K6/M6*100 -> 35.220742 | R6: =P6-G6 -> -7.1857417 | S6: =O6-F6 -> 0.55437329 | U6: UBER | V6: CAMPEONATO DE BOCATAS DE ESPAÑA | W6: 98 | X6: 1322.6
A7: Bocadillos | B7: VEGETAL POLLO | C7: =BOCATAS!L63 -> 1.3687182 | D7: =BOCATAS!L65 -> 4.5454545 | E7: =D7*1.1 -> 5 | F7: =D7-C7 -> 3.1767364 | G7: =100-H7 -> 69.8882 | H7: =C7/D7*100 -> 30.1118 | I7: 0.19187671 | J7: 0.61375 | K7: =I7+J7+C7 -> 2.1743449 | L7: =$L$1/1.1 -> 1.3636364 | M7: =D7+1.36 -> 5.9054545 | N7: =E7+(L7*1.1) -> 6.5 | O7: =M7-K7 -> 3.7311097 | P7: =100-Q7 -> 63.180736 | Q7: =K7/M7*100 -> 36.819264 | R7: =P7-G7 -> -6.7074639 | S7: =O7-F7 -> 0.55437329 | X7: SIN MENU | Y7: CON MENU | Z7: DIFERENCIA | AA7: MARGEN | AB7: DIF. MARGEN
A8: Bocadillos | B8: VEGETAL POLLO ASADO | C8: =BOCATAS!L95 -> 1.3691028 | D8: =BOCATAS!L97 -> 5.9090909 | E8: =D8*1.1 -> 6.5 | F8: =D8-C8 -> 4.5399881 | G8: =100-H8 -> 76.830568 | H8: =C8/D8*100 -> 23.169432 | I8: 0.19187671 | J8: 0.61375 | K8: =I8+J8+C8 -> 2.1747295 | L8: =$L$1/1.1 -> 1.3636364 | M8: =D8+1.36 -> 7.2690909 | N8: =E8+(L8*1.1) -> 8 | O8: =M8-K8 -> 5.0943614 | P8: =100-Q8 -> 70.082511 | Q8: =K8/M8*100 -> 29.917489 | R8: =P8-G8 -> -6.7480575 | S8: =O8-F8 -> 0.55437329 | U8: LOCAL | V8: Burgers | W8: 1361 | X8: 11905.2 | Y8: =X8+(W8*1.5) -> 13946.7 | Z8: =Y8-X8 -> 2041.5 | AA8: =X8+(W8*0.55) -> 12653.75 | AB8: =AA8-X8 -> 748.55
A9: Bocadillos | B9: VEGETAL EMPANADO | C9: =BOCATAS!L113 -> 1.3137182 | D9: =BOCATAS!L115 -> 4.5454545 | E9: =D9*1.1 -> 5 | F9: =D9-C9 -> 3.2317364 | G9: =100-H9 -> 71.0982 | H9: =C9/D9*100 -> 28.9018 | I9: 0.19187671 | J9: 0.61375 | K9: =I9+J9+C9 -> 2.1193449 | L9: =$L$1/1.1 -> 1.3636364 | M9: =D9+1.36 -> 5.9054545 | N9: =E9+(L9*1.1) -> 6.5 | O9: =M9-K9 -> 3.7861097 | P9: =100-Q9 -> 64.112078 | Q9: =K9/M9*100 -> 35.887922 | R9: =P9-G9 -> -6.9861215 | S9: =O9-F9 -> 0.55437329 | U9: LOCAL | V9: Serranitos | W9: 787 | X9: 5055.5 | Y9: =X9+(W9*1.5) -> 6236 | Z9: =Y9-X9 -> 1180.5 | AA9: =X9+(W9*0.55) -> 5488.35 | AB9: =AA9-X9 -> 432.85
A10: Bocadillos | B10: VEGETAL ATUN | C10: =BOCATAS!L79 -> 1.3287182 | D10: =BOCATAS!L81 -> 4.5454545 | E10: =D10*1.1 -> 5 | F10: =D10-C10 -> 3.2167364 | G10: =100-H10 -> 70.7682 | H10: =C10/D10*100 -> 29.2318 | I10: 0.19187671 | J10: 0.61375 | K10: =I10+J10+C10 -> 2.1343449 | L10: =$L$1/1.1 -> 1.3636364 | M10: =D10+1.36 -> 5.9054545 | N10: =E10+(L10*1.1) -> 6.5 | O10: =M10-K10 -> 3.7711097 | P10: =100-Q10 -> 63.858076 | Q10: =K10/M10*100 -> 36.141924 | R10: =P10-G10 -> -6.910124 | S10: =O10-F10 -> 0.55437329 | U10: LOCAL | V10: Brioches | W10: 610 | X10: 4788.4 | Y10: =X10+(W10*1.5) -> 5703.4 | Z10: =Y10-X10 -> 915 | AA10: =X10+(W10*0.55) -> 5123.9 | AB10: =AA10-X10 -> 335.5
A11: Bocadillos | B11: BARBARA | C11: =BOCATAS!L131 -> 1.7153182 | D11: =BOCATAS!L133 -> 4.5454545 | E11: =D11*1.1 -> 5 | F11: =D11-C11 -> 2.8301364 | G11: =100-H11 -> 62.263 | H11: =C11/D11*100 -> 37.737 | I11: 0.19187671 | J11: 0.61375 | K11: =I11+J11+C11 -> 2.5209449 | L11: =$L$1/1.1 -> 1.3636364 | M11: =D11+1.36 -> 5.9054545 | N11: =E11+(L11*1.1) -> 6.5 | O11: =M11-K11 -> 3.3845097 | P11: =100-Q11 -> 57.311586 | Q11: =K11/M11*100 -> 42.688414 | R11: =P11-G11 -> -4.9514141 | S11: =O11-F11 -> 0.55437329 | U11: LOCAL | V11: Bocatas | W11: 484 | X11: 3326.8 | Y11: =X11+(W11*1.5) -> 4052.8 | Z11: =Y11-X11 -> 726 | AA11: =X11+(W11*0.55) -> 3593 | AB11: =AA11-X11 -> 266.2
A12: Bocadillos | B12: CRISTIAN | C12: =BOCATAS!L147 -> 1.5238482 | D12: =BOCATAS!L149 -> 6.3636364 | E12: =D12*1.1 -> 7 | F12: =D12-C12 -> 4.8397882 | G12: =100-H12 -> 76.053814 | H12: =C12/D12*100 -> 23.946186 | I12: 0.19187671 | J12: 0.61375 | K12: =I12+J12+C12 -> 2.3294749 | L12: =$L$1/1.1 -> 1.3636364 | M12: =D12+1.36 -> 7.7236364 | N12: =E12+(L12*1.1) -> 8.5 | O12: =M12-K12 -> 5.3941615 | P12: =100-Q12 -> 69.839661 | Q12: =K12/M12*100 -> 30.160339 | R12: =P12-G12 -> -6.2141531 | S12: =O12-F12 -> 0.55437329 | U12: LOCAL | V12: Bocatas Vegetales | W12: 174 | X12: 939 | Y12: =X12+(W12*1.5) -> 1200 | Z12: =Y12-X12 -> 261 | AA12: =X12+(W12*0.55) -> 1034.7 | AB12: =AA12-X12 -> 95.7
A13: Bocadillos | B13: JAKINIÑO | C13: =BOCATAS!L185 -> 1.8190482 | D13: =BOCATAS!L187 -> 7.2727273 | E13: =D13*1.1 -> 8 | F13: =D13-C13 -> 5.4536791 | G13: =100-H13 -> 74.988088 | H13: =C13/D13*100 -> 25.011913 | I13: 0.19187671 | J13: 0.61375 | K13: =I13+J13+C13 -> 2.6246749 | L13: =$L$1/1.1 -> 1.3636364 | M13: =D13+1.36 -> 8.6327273 | N13: =E13+(L13*1.1) -> 9.5 | O13: =M13-K13 -> 6.0080524 | P13: =100-Q13 -> 69.596226 | Q13: =K13/M13*100 -> 30.403774 | R13: =P13-G13 -> -5.3918615 | S13: =O13-F13 -> 0.55437329 | U13: LOCAL | V13: BOCATAS SIMPLES | W13: 163 | X13: 791.5 | Y13: =X13+(W13*1.5) -> 1036 | Z13: =Y13-X13 -> 244.5 | AA13: =X13+(W13*0.55) -> 881.15 | AB13: =AA13-X13 -> 89.65
A14: Bocadillos | B14: GUARRITO | C14: =BOCATAS!L166 -> 1.5106482 | D14: =BOCATAS!L168 -> 6.3636364 | E14: =D14*1.1 -> 7 | F14: =D14-C14 -> 4.8529882 | G14: =100-H14 -> 76.261243 | H14: =C14/D14*100 -> 23.738757 | I14: 0.19187671 | J14: 0.61375 | K14: =I14+J14+C14 -> 2.3162749 | L14: =$L$1/1.1 -> 1.3636364 | M14: =D14+1.36 -> 7.7236364 | N14: =E14+(L14*1.1) -> 8.5 | O14: =M14-K14 -> 5.4073615 | P14: =100-Q14 -> 70.010565 | Q14: =K14/M14*100 -> 29.989435 | R14: =P14-G14 -> -6.2506777 | S14: =O14-F14 -> 0.55437329
A16: SERRANITOS | B16: SERRANO EMPANADO | C16: =SERRANOS!L34 -> 1.5666182 | D16: =SERRANOS!L36 -> 5.9090909 | E16: =D16*1.1 -> 6.5 | F16: =D16-C16 -> 4.3424727 | G16: =100-H16 -> 73.488 | H16: =C16/D16*100 -> 26.512 | I16: 0.19187671 | J16: 0.61375 | K16: =I16+J16+C16 -> 2.3722449 | L16: =$L$1/1.1 -> 1.3636364 | M16: =D16+1.36 -> 7.2690909 | N16: =E16+(L16*1.1) -> 8 | O16: =M16-K16 -> 4.896846 | P16: =100-Q16 -> 67.365315 | Q16: =K16/M16*100 -> 32.634685 | R16: =P16-G16 -> -6.1226846 | S16: =O16-F16 -> 0.55437329 | V16: TOTAL FACTURACION LOCAL | W16: =SUM(X8:X13) -> 26806.4
A17: SERRANITOS | B17: SERRANO POLLO | C17: =SERRANOS!L6 -> 1.6271182 | D17: =SERRANOS!L8 -> 5.4545455 | E17: =D17*1.1 -> 6 | F17: =D17-C17 -> 3.8274273 | G17: =100-H17 -> 70.1695 | H17: =C17/D17*100 -> 29.8305 | I17: 0.19187671 | J17: 0.61375 | K17: =I17+J17+C17 -> 2.4327449 | L17: =$L$1/1.1 -> 1.3636364 | M17: =D17+1.36 -> 6.8145455 | N17: =E17+(L17*1.1) -> 7.5 | O17: =M17-K17 -> 4.3818006 | P17: =100-Q17 -> 64.300702 | Q17: =K17/M17*100 -> 35.699298 | R17: =P17-G17 -> -5.868798 | S17: =O17-F17 -> 0.55437329 | V17: TOTAL FACT. MENU | W17: =SUM(Y8:Y13) -> 32174.9
A18: SERRANITOS | B18: SERRANO POLLO ASADO | C18: =SERRANOS!L63 -> 1.5660028 | D18: =SERRANOS!L65 -> 5.9090909 | E18: =D18*1.1 -> 6.5 | F18: =D18-C18 -> 4.3430881 | G18: =100-H18 -> 73.498414 | H18: =C18/D18*100 -> 26.501586 | I18: 0.19187671 | J18: 0.61375 | K18: =I18+J18+C18 -> 2.3716295 | L18: =$L$1/1.1 -> 1.3636364 | M18: =D18+1.36 -> 7.2690909 | N18: =E18+(L18*1.1) -> 8 | O18: =M18-K18 -> 4.8974614 | P18: =100-Q18 -> 67.373781 | Q18: =K18/M18*100 -> 32.626219 | R18: =P18-G18 -> -6.124633 | S18: =O18-F18 -> 0.55437329 | V18: DIFERENCIA | W18: =W17-W16 -> 5368.5
A19: SERRANITOS | B19: SERRANO SOLOMILLO | C19: =SERRANOS!L92 -> 1.4996182 | D19: =SERRANOS!L94 -> 6.3636364 | E19: =D19*1.1 -> 7 | F19: =D19-C19 -> 4.8640182 | G19: =100-H19 -> 76.434571 | H19: =C19/D19*100 -> 23.565429 | I19: 0.19187671 | J19: 0.61375 | K19: =I19+J19+C19 -> 2.3052449 | L19: =$L$1/1.1 -> 1.3636364 | M19: =D19+1.36 -> 7.7236364 | N19: =E19+(L19*1.1) -> 8.5 | O19: =M19-K19 -> 5.4183915 | P19: =100-Q19 -> 70.153374 | Q19: =K19/M19*100 -> 29.846626 | R19: =P19-G19 -> -6.2811979 | S19: =O19-F19 -> 0.55437329 | V19: DIFERENCIA MARGEN | W19: =SUM(AB8:AB13) -> 1968.45
A20: SERRANITOS | B20: SERRANO PULLED PORK | C20: =SERRANOS!L121 -> 1.7827765 | D20: =SERRANOS!L123 -> 7.2727273 | E20: =D20*1.1 -> 8 | F20: =D20-C20 -> 5.4899508 | G20: =100-H20 -> 75.486823 | H20: =C20/D20*100 -> 24.513177 | I20: 0.19187671 | J20: 0.61375 | K20: =I20+J20+C20 -> 2.5884032 | L20: =$L$1/1.1 -> 1.3636364 | M20: =D20+1.36 -> 8.6327273 | N20: =E20+(L20*1.1) -> 9.5 | O20: =M20-K20 -> 6.044324 | P20: =100-Q20 -> 70.016391 | Q20: =K20/M20*100 -> 29.983609 | R20: =P20-G20 -> -5.4704323 | S20: =O20-F20 -> 0.55437329
A22: BRIOCHES | B22: XMAS CHIKEN | C22: ='BRIOCH-SUBS'!L177 -> 2.0977582 | D22: ='BRIOCH-SUBS'!L179 -> 9 | E22: =D22*1.1 -> 9.9 | F22: =D22-C22 -> 6.9022418 | G22: =100-H22 -> 76.691575 | H22: =C22/D22*100 -> 23.308425 | I22: 0.19187671 | J22: 0.61375 | K22: =I22+J22+C22 -> 2.9033849 | L22: =$L$1/1.1 -> 1.3636364 | M22: =D22+1.36 -> 10.36 | N22: =E22+1.5 -> 11.4 | O22: =M22-K22 -> 7.4566151 | P22: =100-Q22 -> 71.975049 | Q22: =K22/M22*100 -> 28.024951 | R22: =P22-G22 -> -4.7165264 | S22: =O22-F22 -> 0.55437329
A23: BRIOCHES | B23: CESAR BRIOCHE | C23: ='BRIOCH-SUBS'!L149 -> 1.98895 | D23: ='BRIOCH-SUBS'!L151 -> 7.7272727 | E23: =D23*1.1 -> 8.5 | F23: =D23-C23 -> 5.7383227 | G23: =100-H23 -> 74.260647 | H23: =C23/D23*100 -> 25.739353 | I23: 0.19187671 | J23: 0.61375 | K23: =I23+J23+C23 -> 2.7945767 | L23: =$L$1/1.1 -> 1.3636364 | M23: =D23+1.36 -> 9.0872727 | N23: =E23+1.5 -> 10 | O23: =M23-K23 -> 6.292696 | P23: =100-Q23 -> 69.247355 | Q23: =K23/M23*100 -> 30.752645 | R23: =P23-G23 -> -5.0132919 | S23: =O23-F23 -> 0.55437329
A24: BRIOCHES | B24: GYPSY | C24: ='BRIOCH-SUBS'!L64 -> 1.9596667 | D24: ='BRIOCH-SUBS'!L66 -> 7.2727273 | E24: =D24*1.1 -> 8 | F24: =D24-C24 -> 5.3130606 | G24: =100-H24 -> 73.054583 | H24: =C24/D24*100 -> 26.945417 | I24: 0.19187671 | J24: 0.61375 | K24: =I24+J24+C24 -> 2.7652934 | L24: =$L$1/1.1 -> 1.3636364 | M24: =D24+1.36 -> 8.6327273 | N24: =E24+1.5 -> 9.5 | O24: =M24-K24 -> 5.8674339 | P24: =100-Q24 -> 67.967326 | Q24: =K24/M24*100 -> 32.032674 | R24: =P24-G24 -> -5.0872572 | S24: =O24-F24 -> 0.55437329
A25: BRIOCHES | B25: CHICKEN FRIED | C25: ='BRIOCH-SUBS'!L6 -> 1.9732002 | D25: ='BRIOCH-SUBS'!L8 -> 7.2727273 | E25: =D25*1.1 -> 8 | F25: =D25-C25 -> 5.2995271 | G25: =100-H25 -> 72.868498 | H25: =C25/D25*100 -> 27.131502 | I25: 0.19187671 | J25: 0.61375 | K25: =I25+J25+C25 -> 2.7788269 | L25: =$L$1/1.1 -> 1.3636364 | M25: =D25+1.36 -> 8.6327273 | N25: =E25+1.5 -> 9.5 | O25: =M25-K25 -> 5.8539004 | P25: =100-Q25 -> 67.810556 | Q25: =K25/M25*100 -> 32.189444 | R25: =P25-G25 -> -5.0579413 | S25: =O25-F25 -> 0.55437329
A26: BRIOCHES | B26: CHEESE STEAK | C26: ='BRIOCH-SUBS'!L35 -> 2.3676979 | D26: ='BRIOCH-SUBS'!L37 -> 7.2727273 | E26: =D26*1.1 -> 8 | F26: =D26-C26 -> 4.9050294 | G26: =100-H26 -> 67.444154 | H26: =C26/D26*100 -> 32.555846 | I26: 0.19187671 | J26: 0.61375 | K26: =I26+J26+C26 -> 3.1733246 | L26: =$L$1/1.1 -> 1.3636364 | M26: =D26+1.36 -> 8.6327273 | N26: =E26+1.5 -> 9.5 | O26: =M26-K26 -> 5.4594026 | P26: =100-Q26 -> 63.240764 | Q26: =K26/M26*100 -> 36.759236 | R26: =P26-G26 -> -4.2033901 | S26: =O26-F26 -> 0.55437329
A27: BRIOCHES | B27: SMASH SERRANO | C27: ='BRIOCH-SUBS'!L93 -> 1.9800455 | D27: ='BRIOCH-SUBS'!L95 -> 7.2727273 | E27: =D27*1.1 -> 8 | F27: =D27-C27 -> 5.2926818 | G27: =100-H27 -> 72.774375 | H27: =C27/D27*100 -> 27.225625 | I27: 0.19187671 | J27: 0.61375 | K27: =I27+J27+C27 -> 2.7856722 | L27: =$L$1/1.1 -> 1.3636364 | M27: =D27+1.36 -> 8.6327273 | N27: =E27+1.5 -> 9.5 | O27: =M27-K27 -> 5.8470551 | P27: =100-Q27 -> 67.731262 | Q27: =K27/M27*100 -> 32.268738 | R27: =P27-G27 -> -5.0431132 | S27: =O27-F27 -> 0.55437329
A30: BURGER | B30: CRUJIPOLLO BBQ | C30: =BURGERS!L239 -> 1.8604959 | D30: =BURGERS!L241 -> 7.2727273 | E30: =D30*1.1 -> 8 | F30: =D30-C30 -> 5.4122314 | G30: =100-H30 -> 74.418182 | H30: =C30/D30*100 -> 25.581818 | I30: 0.19187671 | J30: 0.61375 | K30: =I30+J30+C30 -> 2.6661226 | L30: =$L$1/1.1 -> 1.3636364 | M30: =D30+1.36 -> 8.6327273 | N30: =E30+1.5 -> 9.5 | O30: =M30-K30 -> 5.9666047 | P30: =100-Q30 -> 69.116103 | Q30: =K30/M30*100 -> 30.883897 | R30: =P30-G30 -> -5.3020786 | S30: =O30-F30 -> 0.55437329
A31: BURGER | B31: CRUJIPOLLO ORIGINAL | C31: =BURGERS!L269 -> 1.5300542 | D31: =BURGERS!L271 -> 6.3636364 | E31: =D31*1.1 -> 7 | F31: =D31-C31 -> 4.8335822 | G31: =100-H31 -> 75.956292 | H31: =C31/D31*100 -> 24.043708 | I31: 0.19187671 | J31: 0.61375 | K31: =I31+J31+C31 -> 2.3356809 | L31: =$L$1/1.1 -> 1.3636364 | M31: =D31+1.36 -> 7.7236364 | N31: =E31+1.5 -> 8.5 | O31: =M31-K31 -> 5.3879555 | P31: =100-Q31 -> 69.759311 | Q31: =K31/M31*100 -> 30.240689 | R31: =P31-G31 -> -6.196981 | S31: =O31-F31 -> 0.55437329
A32: BURGER | B32: MAKA | C32: =BURGERS!L151 -> 2.2052973 | D32: =BURGERS!L153 -> 9 | E32: =D32*1.1 -> 9.9 | F32: =D32-C32 -> 6.7947027 | G32: =100-H32 -> 75.496696 | H32: =C32/D32*100 -> 24.503304 | I32: 0.19187671 | J32: 0.61375 | K32: =I32+J32+C32 -> 3.0109241 | L32: =$L$1/1.1 -> 1.3636364 | M32: =D32+1.36 -> 10.36 | N32: =E32+1.5 -> 11.4 | O32: =M32-K32 -> 7.3490759 | P32: =100-Q32 -> 70.937026 | Q32: =K32/M32*100 -> 29.062974 | R32: =P32-G32 -> -4.5596697 | S32: =O32-F32 -> 0.55437329
A33: BURGER | B33: BICHOTA | C33: =BURGERS!L180 -> 2.1501303 | D33: =BURGERS!L182 -> 9.0909091 | E33: =D33*1.1 -> 10 | F33: =D33-C33 -> 6.9407788 | G33: =100-H33 -> 76.348567 | H33: =C33/D33*100 -> 23.651433 | I33: 0.19187671 | J33: 0.61375 | K33: =I33+J33+C33 -> 2.955757 | L33: =$L$1/1.1 -> 1.3636364 | M33: =D33+1.36 -> 10.450909 | N33: =E33+1.5 -> 11.5 | O33: =M33-K33 -> 7.4951521 | P33: =100-Q33 -> 71.717704 | Q33: =K33/M33*100 -> 28.282296 | R33: =P33-G33 -> -4.6308624 | S33: =O33-F33 -> 0.55437329
A34: BURGER | B34: DADDY | C34: =BURGERS!L209 -> 2.5895738 | D34: =BURGERS!L211 -> 10 | E34: =D34*1.1 -> 11 | F34: =D34-C34 -> 7.4104262 | G34: =100-H34 -> 74.104262 | H34: =C34/D34*100 -> 25.895738 | I34: 0.19187671 | J34: 0.61375 | K34: =I34+J34+C34 -> 3.3952005 | L34: =$L$1/1.1 -> 1.3636364 | M34: =D34+1.36 -> 11.36 | N34: =E34+1.5 -> 12.5 | O34: =M34-K34 -> 7.9647995 | P34: =100-Q34 -> 70.112671 | Q34: =K34/M34*100 -> 29.887329 | R34: =P34-G34 -> -3.9915904 | S34: =O34-F34 -> 0.55437329
A35: BURGER | B35: DOBLE QUESOS | C35: =BURGERS!L6 -> 2.1871023 | D35: =BURGERS!L8 -> 7.2727273 | E35: =D35*1.1 -> 8 | F35: =D35-C35 -> 5.0856249 | G35: =100-H35 -> 69.927343 | H35: =C35/D35*100 -> 30.072657 | I35: 0.19187671 | J35: 0.61375 | K35: =I35+J35+C35 -> 2.9927291 | L35: =$L$1/1.1 -> 1.3636364 | M35: =D35+1.36 -> 8.6327273 | N35: =E35+1.5 -> 9.5 | O35: =M35-K35 -> 5.6399982 | P35: =100-Q35 -> 65.332751 | Q35: =K35/M35*100 -> 34.667249 | R35: =P35-G35 -> -4.5945917 | S35: =O35-F35 -> 0.55437329
A36: BURGER | B36: CERO15 | C36: =BURGERS!L35 -> 2.3754736 | D36: =BURGERS!L37 -> 7.2727273 | E36: =D36*1.1 -> 8 | F36: =D36-C36 -> 4.8972537 | G36: =100-H36 -> 67.337238 | H36: =C36/D36*100 -> 32.662762 | I36: 0.19187671 | J36: 0.61375 | K36: =I36+J36+C36 -> 3.1811003 | L36: =$L$1/1.1 -> 1.3636364 | M36: =D36+1.36 -> 8.6327273 | N36: =E36+1.5 -> 9.5 | O36: =M36-K36 -> 5.451627 | P36: =100-Q36 -> 63.150691 | Q36: =K36/M36*100 -> 36.849309 | R36: =P36-G36 -> -4.1865466 | S36: =O36-F36 -> 0.55437329
A37: BURGER | B37: KAROL | C37: =BURGERS!L122 -> 2.5701467 | D37: =BURGERS!L124 -> 7.2727273 | E37: =D37*1.1 -> 8 | F37: =D37-C37 -> 4.7025805 | G37: =100-H37 -> 64.660482 | H37: =C37/D37*100 -> 35.339518 | I37: 0.19187671 | J37: 0.61375 | K37: =I37+J37+C37 -> 3.3757735 | L37: =$L$1/1.1 -> 1.3636364 | M37: =D37+1.36 -> 8.6327273 | N37: =E37+1.5 -> 9.5 | O37: =M37-K37 -> 5.2569538 | P37: =100-Q37 -> 60.895632 | Q37: =K37/M37*100 -> 39.104368 | R37: =P37-G37 -> -3.7648504 | S37: =O37-F37 -> 0.55437329
A38: BURGER | B38: BARRIERA | C38: =BURGERS!L93 -> 2.6506748 | D38: =BURGERS!L95 -> 6.3636364 | E38: =D38*1.1 -> 7 | F38: =D38-C38 -> 3.7129615 | G38: =100-H38 -> 58.346539 | H38: =C38/D38*100 -> 41.653461 | I38: 0.19187671 | J38: 0.61375 | K38: =I38+J38+C38 -> 3.4563015 | L38: =$L$1/1.1 -> 1.3636364 | M38: =D38+1.36 -> 7.7236364 | N38: =E38+1.5 -> 8.5 | O38: =M38-K38 -> 4.2673348 | P38: =100-Q38 -> 55.250333 | Q38: =K38/M38*100 -> 44.749667 | R38: =P38-G38 -> -3.0962052 | S38: =O38-F38 -> 0.55437329
A39: BURGER | B39: CALLEJERA | C39: =BURGERS!L64 -> 2.4731124 | D39: =BURGERS!L66 -> 9 | E39: =D39*1.1 -> 9.9 | F39: =D39-C39 -> 6.5268876 | G39: =100-H39 -> 72.520973 | H39: =C39/D39*100 -> 27.479027 | I39: 0.19187671 | J39: 0.61375 | K39: =I39+J39+C39 -> 3.2787391 | L39: =$L$1/1.1 -> 1.3636364 | M39: =D39+1.36 -> 10.36 | N39: =E39+1.5 -> 11.4 | O39: =M39-K39 -> 7.0812609 | P39: =100-Q39 -> 68.351939 | Q39: =K39/M39*100 -> 31.648061 | R39: =P39-G39 -> -4.1690342 | S39: =O39-F39 -> 0.55437329
A41: HOTDOG | B41: HOTDOG/ PERRITOS SIMPLE | C41: ='BRIOCH-SUBS'!L205 -> 1.7600676 | D41: ='BRIOCH-SUBS'!L207 -> 3.5454545 | E41: ='BRIOCH-SUBS'!L206 -> 3.9 | F41: =D41-C41 -> 1.785387 | G41: =100-H41 -> 50.357069 | H41: =C41/D41*100 -> 49.642931 | I41: 0.19187671 | J41: 0.61375 | K41: =I41+J41+C41 -> 2.5656943 | L41: =$L$1/1.1 -> 1.3636364 | M41: =D41+1.36 -> 4.9054545 | N41: =E41+1.5 -> 5.4 | O41: =M41-K41 -> 2.3397603 | P41: =100-Q41 -> 47.697114 | Q41: =K41/M41*100 -> 52.302886 | R41: =P41-G41 -> -2.6599542 | S41: =O41-F41 -> 0.55437329
A42: HOTDOG | B42: HOTDOG BACONQUESO | C42: ='BRIOCH-SUBS'!L223 -> 2.0661296 | D42: ='BRIOCH-SUBS'!L225 -> 5.3636364 | E42: ='BRIOCH-SUBS'!L224 -> 5.9 | F42: =D42-C42 -> 3.2975068 | G42: =100-H42 -> 61.47894 | H42: =C42/D42*100 -> 38.52106 | I42: 0.19187671 | J42: 0.61375 | K42: =I42+J42+C42 -> 2.8717563 | L42: =$L$1/1.1 -> 1.3636364 | M42: =D42+1.36 -> 6.7236364 | N42: =E42+1.5 -> 7.4 | O42: =M42-K42 -> 3.8518801 | P42: =100-Q42 -> 57.288644 | Q42: =K42/M42*100 -> 42.711356 | R42: =P42-G42 -> -4.1902965 | S42: =O42-F42 -> 0.55437329
A43: HOTDOG | B43: HOTDOG CHILL BBQ | C43: ='BRIOCH-SUBS'!L241 -> 1.8283224 | D43: ='BRIOCH-SUBS'!L243 -> 6.3636364 | E43: ='BRIOCH-SUBS'!L242 -> 7 | F43: =D43-C43 -> 4.535314 | G43: =100-H43 -> 71.269219 | H43: =C43/D43*100 -> 28.730781 | I43: 0.19187671 | J43: 0.61375 | K43: =I43+J43+C43 -> 2.6339491 | L43: =$L$1/1.1 -> 1.3636364 | M43: =D43+1.36 -> 7.7236364 | N43: =E43+1.5 -> 8.5 | O43: =M43-K43 -> 5.0896873 | P43: =100-Q43 -> 65.897552 | Q43: =K43/M43*100 -> 34.102449 | R43: =P43-G43 -> -5.3716679 | S43: =O43-F43 -> 0.55437329
A45: ENTRANTES | B45: BOX ALITAS | C45: =ENTRANTES!L34 -> 2.4242067 | D45: =ENTRANTES!L36 -> 5.4545455 | E45: =D45*1.1 -> 6 | F45: =D45-C45 -> 3.0303387 | G45: =100-H45 -> 55.55621 | H45: =C45/D45*100 -> 44.44379
A46: ENTRANTES | B46: BOX LAGRIMITAS | C46: =ENTRANTES!L90 -> 1.5589067 | D46: =ENTRANTES!L92 -> 5.4545455 | E46: =D46*1.1 -> 6 | F46: =D46-C46 -> 3.8956387 | G46: =100-H46 -> 71.420044 | H46: =C46/D46*100 -> 28.579956
A47: ENTRANTES | B47: BOX NUGGETS | C47: =ENTRANTES!L6 -> 1.8325067 | D47: =ENTRANTES!L8 -> 5.4545455 | E47: =D47*1.1 -> 6 | F47: =D47-C47 -> 3.6220387 | G47: =100-H47 -> 66.404044 | H47: =C47/D47*100 -> 33.595956
A48: ENTRANTES | B48: BOX PATATAS | C48: =ENTRANTES!L118 -> 0.91663342 | D48: =ENTRANTES!L120 -> 4.5454545 | E48: =D48*1.1 -> 5 | F48: =D48-C48 -> 3.6288211 | G48: =100-H48 -> 79.834065 | H48: =C48/D48*100 -> 20.165935
A49: ENTRANTES | B49: BOX PAPAS PULLED PORK | C49: =ENTRANTES!L174 -> 1.3761221 | D49: =ENTRANTES!L176 -> 6.3636364 | E49: =D49*1.1 -> 7 | F49: =D49-C49 -> 4.9875142 | G49: =100-H49 -> 78.375224 | H49: =C49/D49*100 -> 21.624776
A50: ENTRANTES | B50: PETACA PATATA | C50: =ENTRANTES!L146 -> 0.26404167 | D50: =ENTRANTES!L148 -> 1.8181818 | E50: =D50*1.1 -> 2 | F50: =D50-C50 -> 1.5541402 | G50: =100-H50 -> 85.477708 | H50: =C50/D50*100 -> 14.522292
A51: ENTRANTES | B51: NEW PATATAS CHEESE BACON
A54: POSTRES | B54: TARTA LOTUS | C54: =POSTRES!L50 -> 1.43 | D54: =POSTRES!L52 -> 5.4545455 | E54: =D54*1.1 -> 6 | F54: =D54-C54 -> 4.0245455 | G54: =100-H54 -> 73.783333 | H54: =C54/D54*100 -> 26.216667
A55: POSTRES | B55: TARTA QUESO | C55: =POSTRES!L6 -> 4.3 | D55: =POSTRES!L8 -> 5.4545455 | E55: =D55*1.1 -> 6 | F55: =D55-C55 -> 1.1545455 | G55: =100-H55 -> 21.166667 | H55: =C55/D55*100 -> 78.833333
A56: POSTRES | B56: TARTA DUBAI | C56: =POSTRES!L28 -> 4.3 | D56: =POSTRES!L30 -> 5.9090909 | E56: =D56*1.1 -> 6.5 | F56: =D56-C56 -> 1.6090909 | G56: =100-H56 -> 27.230769 | H56: =C56/D56*100 -> 72.769231
A60: BEBIDA | B60: LATA AQUARIOUS LIMON | C60: 0.72791667 | D60: =E60/1.1 -> 1.4545455 | E60: 1.6 | F60: =D60-C60 -> 0.72662879 | G60: =100-H60 -> 49.955729 | H60: =C60/D60*100 -> 50.044271
A61: BEBIDA | B61: LATA AQUARIOUS NARANJA | C61: 0.72791667 | D61: =E61/1.1 -> 1.4545455 | E61: 1.6 | F61: =D61-C61 -> 0.72662879 | G61: =100-H61 -> 49.955729 | H61: =C61/D61*100 -> 50.044271
A62: BEBIDA | B62: LATA COCACOLA | C62: 0.61375 | D62: =E62/1.1 -> 1.3636364 | E62: 1.5 | F62: =D62-C62 -> 0.74988636 | G62: =100-H62 -> 54.991667 | H62: =C62/D62*100 -> 45.008333
A63: BEBIDA | B63: LATA COCACOLA ZERO | C63: 0.61375 | D63: =E63/1.1 -> 1.3636364 | E63: 1.5 | F63: =D63-C63 -> 0.74988636 | G63: =100-H63 -> 54.991667 | H63: =C63/D63*100 -> 45.008333
A64: BEBIDA | B64: LATA COLACOLA ZERO ZERO | C64: 0.61375 | D64: =E64/1.1 -> 1.3636364 | E64: 1.5 | F64: =D64-C64 -> 0.74988636 | G64: =100-H64 -> 54.991667 | H64: =C64/D64*100 -> 45.008333
A65: BEBIDA | B65: LATA FANTA LIMON | C65: 0.52666667 | D65: =E65/1.1 -> 1.3636364 | E65: 1.5 | F65: =D65-C65 -> 0.8369697 | G65: =100-H65 -> 61.377778 | H65: =C65/D65*100 -> 38.622222
A66: BEBIDA | B66: LATA FANTA NARANJA | C66: 0.52666667 | D66: =E66/1.1 -> 1.3636364 | E66: 1.5 | F66: =D66-C66 -> 0.8369697 | G66: =100-H66 -> 61.377778 | H66: =C66/D66*100 -> 38.622222
A67: BEBIDA | B67: LATA FUZEE TEA LIMON | C67: 0.635 | D67: =E67/1.1 -> 1.4545455 | E67: 1.6 | F67: =D67-C67 -> 0.81954545 | G67: =100-H67 -> 56.34375 | H67: =C67/D67*100 -> 43.65625
A68: BEBIDA | B68: LATA FUZEE TEA MARACUYA | C68: 0.635 | D68: =E68/1.1 -> 1.4545455 | E68: 1.6 | F68: =D68-C68 -> 0.81954545 | G68: =100-H68 -> 56.34375 | H68: =C68/D68*100 -> 43.65625
A71: TARROS | B71: TARRITO ALIOLI | C71: ='TARROS SALSA'!L6 -> 0.19187671 | D71: ='TARROS SALSA'!L8 -> 0.45454545 | E71: ='TARROS SALSA'!L7 -> 0.5 | F71: =D71-C71 -> 0.26266874 | G71: =100-H71 -> 57.787124 | H71: =C71/D71*100 -> 42.212876
A72: TARROS | B72: TARRITO MAYONESA | C72: ='TARROS SALSA'!L17 -> 0.13715 | D72: ='TARROS SALSA'!L19 -> 0.45454545 | E72: ='TARROS SALSA'!L18 -> 0.5 | F72: =D72-C72 -> 0.31739545 | G72: =100-H72 -> 69.827 | H72: =C72/D72*100 -> 30.173
A73: TARROS | B73: TARRITO SALSA WISKY | C73: ='TARROS SALSA'!L37 -> 0.10440526 | D73: ='TARROS SALSA'!L39 -> 0.45454545 | E73: =D73*1.1 -> 0.5 | F73: =D73-C73 -> 0.3501402 | G73: =100-H73 -> 77.030843 | H73: =C73/D73*100 -> 22.969157
A74: TARROS | B74: TARRO KETCHUP | C74: ='TARROS SALSA'!L95 -> 0.15006892 | D74: ='TARROS SALSA'!L97 -> 0.45454545 | E74: =D74*1.1 -> 0.5 | F74: =D74-C74 -> 0.30447654 | G74: =100-H74 -> 66.984838 | H74: =C74/D74*100 -> 33.015162
A75: TARROS | B75: TARRITO SALSA BBQ | C75: ='TARROS SALSA'!L56 -> 0.18493378 | D75: ='TARROS SALSA'!L58 -> 0.45454545 | E75: =D75*1.1 -> 0.5 | F75: =D75-C75 -> 0.26961167 | G75: =100-H75 -> 59.314568 | H75: =C75/D75*100 -> 40.685432
A76: TARROS | B76: TARRITO SALSA MOJO PICON | C76: ='TARROS SALSA'!L27 -> 0.18170085 | D76: ='TARROS SALSA'!L29 -> 0.45454545 | E76: =D76*1.1 -> 0.5 | F76: =D76-C76 -> 0.2728446 | G76: =100-H76 -> 60.025813 | H76: =C76/D76*100 -> 39.974187
A77: TARROS | B77: TARRITO SALSA AMERICAN BURGER | C77: ='TARROS SALSA'!L66 -> 0.251575 | D77: ='TARROS SALSA'!L68 -> 0.90909091 | E77: =D77*1.1 -> 1 | F77: =D77-C77 -> 0.65751591 | G77: =100-H77 -> 72.32675 | H77: =C77/D77*100 -> 27.67325
A78: TARROS | B78: TARRITO SALSA TRUFADA | C78: ='TARROS SALSA'!L85 -> 0.16111675 | D78: ='TARROS SALSA'!L87 -> 1.0909091 | E78: =D78*1.1 -> 1.2 | F78: =D78-C78 -> 0.92979234 | G78: =100-H78 -> 85.230964 | H78: =C78/D78*100 -> 14.769036
A79: TARROS | B79: TARRO SALSA BICHOTA | C79: ='TARROS SALSA'!L75 -> 0.12662868 | D79: ='TARROS SALSA'!L77 -> 1.0909091 | E79: =D79*1.1 -> 1.2 | F79: =D79-C79 -> 0.96428041 | G79: =100-H79 -> 88.392371 | H79: =C79/D79*100 -> 11.607629
A80: TARROS | B80: TARRO RANCHERA | C80: ='TARROS SALSA'!L106 -> 0.27821818 | D80: ='TARROS SALSA'!L108 -> 1.0909091 | E80: =D80*1.1 -> 1.2 | F80: =D80-C80 -> 0.81269091 | G80: =100-H80 -> 74.496667 | H80: =C80/D80*100 -> 25.503333
A81: TARROS | B81: TARRO MAYO SRIRACHA | C81: ='TARROS SALSA'!L46 -> 0.57745137 | D81: ='TARROS SALSA'!L48 -> 1.8181818 | E81: =D81*1.1 -> 2 | F81: =D81-C81 -> 1.2407304 | G81: =100-H81 -> 68.240175 | H81: =C81/D81*100 -> 31.759825

Sheet SCRIPTS VENTAS Y MENU
B3: SUGERIR
B4: SIMPLE ASADO | C4: 26.814056
B5: SIMPLE EMPANADO | C5: 29.509
B6: SIMPLE SOLOMILO | C6: 28.035
B7: VEGETAL POLLO ASADO | C7: 23.169432
B8: VEGETAL EMPANADO | C8: 28.9018
B9: VEGETAL ATUN | C9: 29.2318
B10: CRISTIAN | C10: 23.946186
B11: JAKINIÑO | C11: 25.011913
B12: GUARRITO | C12: 23.738757
B15: SERRANO EMPANADO | C15: 26.512
B16: SERRANO POLLO | C16: 29.8305
B17: SERRANO POLLO ASADO | C17: 26.501586
... B49: TARRO RANCHERA | C49: 25.503333

Sheet UBER- RESUMEN DE COSTES
I1: =SUM(I3:I59) -> 464
A2: Familia | B2: Producto | C2: Coste € | D2: PVP sin IVA | E2: PVP Actual | F2: MARGEN POS UBER € | G2: MARGEN % | H2: Coste % | I2: Unidades Vendidas | J2: Peso venta %
A3: Bocadillos | B3: =BOCATAS!D2 -> SIMPLE DE POLLO | C3: =BOCATAS!L6 -> 1.4018182 | D3: =BOCATAS!L8 -> 3.6363636 | E3: =D3*1.1 -> 4 | F3: =D3-C3 -> 2.2345455 | G3: =BOCATAS!L11 -> 61.45 | H3: =BOCATAS!L10 -> 38.55 | I3: 163 | J3: =I3/SUM($I$3:I201)*100 -> 35.12931
A4: Bocadillos | B4: SIMPLE ASADO | C4: =BOCATAS!L34 -> 1.3407028 | D4: =BOCATAS!L36 -> 5 | E4: =D4*1.1 -> 5.5 | F4: =D4-C4 -> 3.6592972 | G4: =100-H4 -> 73.185944 | H4: =C4/D4*100 -> 26.814056 | I4: 33 | J4: =I4/SUM($I$3:I202)*100 -> 7.112069
A5: Bocadillos | B5: SIMPLE EMPANADO | C5: =BOCATAS!L20 -> 1.3413182 | D5: =BOCATAS!L22 -> 4.5454545 | E5: =D5*1.1 -> 5 | F5: =D5-C5 -> 3.2041364 | G5: =100-H5 -> 70.491 | H5: =C5/D5*100 -> 29.509 | I5: 31 | J5: =I5/SUM($I$3:I203)*100 -> 6.6810345
A6: Bocadillos | B6: SIMPLE SOLOMILO | C6: =BOCATAS!L48 -> 1.2743182 | D6: =BOCATAS!L50 -> 4.5454545 | E6: =D6*1.1 -> 5 | F6: =D6-C6 -> 3.2711364 | G6: =100-H6 -> 71.965 | H6: =C6/D6*100 -> 28.035 | I6: 19 | J6: =I6/SUM($I$3:I204)*100 -> 4.0948276
A7: Bocadillos | B7: VEGETAL POLLO | C7: =BOCATAS!L63 -> 1.3687182 | D7: =BOCATAS!P97 -> 6.2727273 | E7: =D7*1.1 -> 6.9 | F7: =D7-C7 -> 4.9040091 | G7: =100-H7 -> 78.179855 | H7: =C7/D7*100 -> 21.820145 | I7: 218 | J7: =I7/SUM($I$3:I205)*100 -> 46.982759
A8: Bocadillos | B8: VEGETAL POLLO ASADO | C8: =BOCATAS!L95 -> 1.3691028 | D8: =BOCATAS!P97 -> 6.2727273 | E8: =D8*1.1 -> 6.9 | F8: =D8-C8-(E8*0.2) -> 3.5236245 | G8: =F8/D8*100 -> 56.173724 | H8: =100-G8 -> 43.826276 | J8: =I8/SUM($I$3:I206)*100 -> 0
A9: Bocadillos | B9: VEGETAL EMPANADO | C9: =BOCATAS!L113 -> 1.3137182 | D9: =BOCATAS!P115 -> 6.3636364 | E9: =D9*1.1 -> 7 | F9: =D9-C9-(E9*0.2) -> 3.6499182 | G9: =F9/D9*100 -> 57.355857 | H9: =100-G9 -> 42.644143 | J9: =I9/SUM($I$3:I207)*100 -> 0
A10: Bocadillos | B10: VEGETAL ATUN | C10: =BOCATAS!L79 -> 1.3287182 | D10: =BOCATAS!L81 -> 4.5454545 | E10: =D10*1.1 -> 5 | F10: =D10-C10 -> 3.2167364 | G10: =100-H10 -> 70.7682 | H10: =C10/D10*100 -> 29.2318 | J10: =I10/SUM($I$3:I208)*100 -> 0
A11: Bocadillos | B11: BARBARA | C11: =BOCATAS!L131 -> 1.7153182 | D11: =BOCATAS!L133 -> 4.5454545 | E11: =D11*1.1 -> 5 | F11: =D11-C11 -> 2.8301364 | G11: =100-H11 -> 62.263 | H11: =C11/D11*100 -> 37.737 | J11: =I11/SUM($I$3:I209)*100 -> 0
A12: Bocadillos | B12: CRISTIAN | C12: =BOCATAS!L147 -> 1.5238482 | D12: =BOCATAS!L149 -> 6.3636364 | E12: =D12*1.1 -> 7 | F12: =D12-C12 -> 4.8397882 | G12: =100-H12 -> 76.053814 | H12: =C12/D12*100 -> 23.946186 | J12: =I12/SUM($I$3:I210)*100 -> 0
A13: Bocadillos | B13: JAKINIÑO | C13: =BOCATAS!L185 -> 1.8190482 | D13: =BOCATAS!P187 -> 8.1818182 | E13: =D13*1.1 -> 9 | F13: =D13-C13-(E13*0.2) -> 4.56277 | G13: =F13/D13*100 -> 55.767189 | H13: =100-G13 -> 44.232811 | J13: =I13/SUM($I$3:I211)*100 -> 0
A14: Bocadillos | B14: GUARRITO | C14: =BOCATAS!L166 -> 1.5106482 | D14: =BOCATAS!P168 -> 8.0909091 | E14: =D14*1.1 -> 8.9 | F14: =D14-C14-(E14*0.2) -> 4.8002609 | G14: =F14/D14*100 -> 59.329067 | H14: =100-G14 -> 40.670933 | J14: =I14/SUM($I$3:I212)*100 -> 0
A16: SERRANITOS | B16: SERRANO EMPANADO | C16: =SERRANOS!L34 -> 1.5666182 | D16: =SERRANOS!P36 -> 8.3636364 | E16: =D16*1.1 -> 9.2 | F16: =D16-C16-(E16*0.2) -> 4.9570182 | G16: =F16/D16*100 -> 59.268696 | H16: =100-G16 -> 40.731304 | J16: =I16/SUM($I$3:I214)*100 -> 0
A17: SERRANITOS | B17: SERRANO POLLO | C17: =SERRANOS!L6 -> 1.6271182 | D17: =SERRANOS!P8 -> 7.4545455 | E17: =D17*1.1 -> 8.2 | F17: =D17-C17-(E17*0.2) -> 4.1874273 | G17: =F17/D17*100 -> 56.172805 | H17: =100-G17 -> 43.827195 | J17: =I17/SUM($I$3:I215)*100 -> 0
A18: SERRANITOS | B18: SERRANO POLLO ASADO | C18: =SERRANOS!L63 -> 1.5660028 | D18: =SERRANOS!P65 -> 8.3636364 | E18: =D18*1.1 -> 9.2 | F18: =D18-C18-(E18*0.2) -> 4.9576336 | G18: =F18/D18*100 -> 59.276054 | H18: =100-G18 -> 40.723946 | J18: =I18/SUM($I$3:I216)*100 -> 0
A19: SERRANITOS | B19: SERRANO SOLOMILLO | C19: =SERRANOS!L92 -> 1.4996182 | D19: =SERRANOS!P94 -> 8.3636364 | E19: =D19*1.1 -> 9.2 | F19: =D19-C19-(E19*0.2) -> 5.0240182 | G19: =F19/D19*100 -> 60.069783 | H19: =100-G19 -> 39.930217 | J19: =I19/SUM($I$3:I217)*100 -> 0
A20: SERRANITOS | B20: SERRANO PULLED PORK | C20: =SERRANOS!L121 -> 1.7827765 | D20: =SERRANOS!P123 -> 8.3636364 | E20: =D20*1.1 -> 9.2 | F20: =D20-C20-(E20*0.2) -> 4.7408598 | G20: =F20/D20*100 -> 56.684194 | H20: =100-G20 -> 43.315806 | J20: =I20/SUM($I$3:I218)*100 -> 0
A22: BRIOCHES | B22: XMAS CHIKEN | C22: ='BRIOCH-SUBS'!L177 -> 2.0977582 | D22: ='BRIOCH-SUBS'!L179 -> 9 | E22: =D22*1.1 -> 9.9 | F22: =D22-C22-(E22*0.2) -> 4.9222418 | G22: =F22/D22*100 -> 54.691575 | H22: =100-G22 -> 45.308425 | K22: TEMPORADA
A23: BRIOCHES | B23: CESAR BRIOCHE | C23: ='BRIOCH-SUBS'!L149 -> 1.98895 | D23: ='BRIOCH-SUBS'!L159 -> 9 | E23: =D23*1.1 -> 9.9 | F23: =D23-C23-(E23*0.2) -> 5.03105 | G23: =F23/D23*100 -> 55.900556 | H23: =100-G23 -> 44.099444 | J23: =I23/SUM($I$3:I221)*100 -> 0
A24: BRIOCHES | B24: GYPSY | C24: ='BRIOCH-SUBS'!L64 -> 1.9596667 | D24: ='BRIOCH-SUBS'!L74 -> 9 | E24: =D24*1.1 -> 9.9 | F24: =D24-C24-(E24*0.2) -> 5.0603333 | G24: =F24/D24*100 -> 56.225926 | H24: =100-G24 -> 43.774074 | J24: =I24/SUM($I$3:I222)*100 -> 0
A25: BRIOCHES | B25: CHICKEN FRIED | C25: ='BRIOCH-SUBS'!L6 -> 1.9732002 | D25: ='BRIOCH-SUBS'!L16 -> 7.7272727 | E25: =D25*1.1 -> 8.5 | F25: =D25-C25-(E25*0.2) -> 4.0540726 | G25: =F25/D25*100 -> 52.464468 | H25: =100-G25 -> 47.535532 | J25: =I25/SUM($I$3:I223)*100 -> 0
A26: BRIOCHES | B26: CHEESE STEAK | C26: ='BRIOCH-SUBS'!L35 -> 2.3676979 | D26: ='BRIOCH-SUBS'!L37 -> 7.2727273 | E26: =D26*1.1 -> 8 | F26: =D26-C26-(E26*0.2) -> 3.3050294 | G26: =F26/D26*100 -> 45.444154 | H26: =100-G26 -> 54.555846 | J26: =I26/SUM($I$3:I224)*100 -> 0 | K26: PROXIMAMENTE
A27: BRIOCHES | B27: SMASH SERRANO | C27: ='BRIOCH-SUBS'!L93 -> 1.9800455 | D27: ='BRIOCH-SUBS'!L103 -> 10.818182 | E27: =D27*1.1 -> 11.9 | F27: =D27-C27-(E27*0.2) -> 6.4581364 | G27: =F27/D27*100 -> 59.697059 | H27: =100-G27 -> 40.302941 | J27: =I27/SUM($I$3:I225)*100 -> 0
A30: BURGER | B30: CRUJIPOLLO BBQ | C30: =BURGERS!L239 -> 1.8604959 | D30: =BURGERS!L249 -> 9.9090909 | E30: =D30*1.1 -> 10.9 | F30: =D30-C30-(E30*0.2) -> 5.868595 | G30: =F30/D30*100 -> 59.224354 | H30: =100-G30 -> 40.775646 | J30: =I30/SUM($I$3:I228)*100 -> 0
A31: BURGER | B31: CRUJIPOLLO ORIGINAL | C31: =BURGERS!L269 -> 1.5300542 | D31: =BURGERS!L279 -> 8.0909091 | E31: =D31*1.1 -> 8.9 | F31: =D31-C31-(E31*0.2) -> 4.7808549 | G31: =F31/D31*100 -> 59.089218 | H31: =100-G31 -> 40.910782 | J31: =I31/SUM($I$3:I229)*100 -> 0
A32: BURGER | B32: MAKA | C32: =BURGERS!L151 -> 2.2052973 | D32: =BURGERS!L161 -> 11.818182 | E32: =D32*1.1 -> 13 | F32: =D32-C32-(E32*0.2) -> 7.0128845 | G32: =F32/D32*100 -> 59.339792 | H32: =100-G32 -> 40.660208 | J32: =I32/SUM($I$3:I230)*100 -> 0
A33: BURGER | B33: BICHOTA | C33: =BURGERS!L180 -> 2.1501303 | D33: =BURGERS!L190 -> 11.818182 | E33: =D33*1.1 -> 13 | F33: =D33-C33-(E33*0.2) -> 7.0680515 | G33: =F33/D33*100 -> 59.80659 | H33: =100-G33 -> 40.19341 | J33: =I33/SUM($I$3:I231)*100 -> 0
A34: BURGER | B34: DADDY | C34: =BURGERS!L209 -> 2.5895738 | E34: =D34*1.1 -> 0 | F34: =D34-C34-(E34*0.2) -> -2.5895738 | G34: =F34/D34*100 -> #DIV/0! | H34: =100-G34 -> #DIV/0! | J34: =I34/SUM($I$3:I232)*100 -> 0 | K34: RETIRADO
A35: BURGER | B35: DOBLE QUESOS | C35: =BURGERS!L6 -> 2.1871023 | D35: =BURGERS!L16 -> 10.818182 | E35: =D35*1.1 -> 11.9 | F35: =D35-C35-(E35*0.2) -> 6.2510795 | G35: =F35/D35*100 -> 57.783088 | H35: =100-G35 -> 42.216912 | J35: =I35/SUM($I$3:I233)*100 -> 0
A36: BURGER | B36: CERO15 | C36: =BURGERS!L35 -> 2.3754736 | D36: =BURGERS!L45 -> 10.818182 | E36: =D36*1.1 -> 11.9 | F36: =D36-C36-(E36*0.2) -> 6.0627082 | G36: =F36/D36*100 -> 56.041841 | H36: =100-G36 -> 43.958159 | J36: =I36/SUM($I$3:I234)*100 -> 0
A37: BURGER | B37: KAROL | C37: =BURGERS!L122 -> 2.5701467 | D37: =BURGERS!L132 -> 9.9090909 | E37: =D37*1.1 -> 10.9 | F37: =D37-C37-(E37*0.2) -> 5.1589442 | G37: =F37/D37*100 -> 52.062739 | H37: =100-G37 -> 47.937261 | J37: =I37/SUM($I$3:I235)*100 -> 0 | K37: RETIRADO
A38: BURGER | B38: BARRIERA | C38: =BURGERS!L93 -> 2.6506748 | D38: =BURGERS!L103 -> 9 | E38: =D38*1.1 -> 9.9 | F38: =D38-C38-(E38*0.2) -> 4.3693252 | G38: =F38/D38*100 -> 48.548058 | H38: =100-G38 -> 51.451942 | J38: =I38/SUM($I$3:I236)*100 -> 0
A39: BURGER | B39: CALLEJERA | C39: =BURGERS!L64 -> 2.4731124 | D39: =BURGERS!L74 -> 10.818182 | E39: =D39*1.1 -> 11.9 | F39: =D39-C39-(E39*0.2) -> 5.9650694 | G39: =F39/D39*100 -> 55.139297 | H39: =100-G39 -> 44.860703 | J39: =I39/SUM($I$3:I237)*100 -> 0 | K39: NUEVA
A41: ENTRANTES | B41: BOX ALITAS | C41: =ENTRANTES!L34 -> 2.4242067 | D41: =ENTRANTES!L44 -> 6.3636364 | E41: =D41*1.1 -> 7 | F41: =D41-C41-(E41*0.2) -> 2.5394297 | G41: =F41/D41*100 -> 39.905323 | H41: =100-G41 -> 60.094677 | J41: =I41/SUM($I$3:I239)*100 -> 0 | K41: RETIRADO
A42: ENTRANTES | B42: BOX LAGRIMITAS | C42: =ENTRANTES!L90 -> 1.5589067 | D42: =ENTRANTES!L100 -> 6.3636364 | E42: =D42*1.1 -> 7 | F42: =D42-C42-(E42*0.2) -> 3.4047297 | G42: =F42/D42*100 -> 53.502895 | H42: =100-G42 -> 46.497105 | J42: =I42/SUM($I$3:I240)*100 -> 0
A43: ENTRANTES | B43: BOX NUGGETS | C43: =ENTRANTES!L6 -> 1.8325067 | D43: =ENTRANTES!L16 -> 7.0909091 | E43: =D43*1.1 -> 7.8 | F43: =D43-C43-(E43*0.2) -> 3.6984024 | G43: =F43/D43*100 -> 52.156957 | H43: =100-G43 -> 47.843043 | J43: =I43/SUM($I$3:I241)*100 -> 0
A44: ENTRANTES | B44: BOX PATATAS | C44: =ENTRANTES!L118 -> 0.91663342 | D44: =ENTRANTES!L128 -> 5.9090909 | E44: =D44*1.1 -> 6.5 | F44: =D44-C44-(E44*0.2) -> 3.6924575 | G44: =F44/D44*100 -> 62.487742 | H44: =100-G44 -> 37.512258 | J44: =I44/SUM($I$3:I242)*100 -> 0
A45: ENTRANTES | B45: BOX PAPAS PULLED PORK | C45: =ENTRANTES!L174 -> 1.3761221 | D45: =ENTRANTES!L184 -> 6.8181818 | E45: =D45*1.1 -> 7.5 | F45: =D45-C45-(E45*0.2) -> 3.9420597 | G45: =F45/D45*100 -> 57.816876 | H45: =100-G45 -> 42.183124 | J45: =I45/SUM($I$3:I243)*100 -> 0
A46: ENTRANTES | B46: PETACA PATATA | C46: =ENTRANTES!L146 -> 0.26404167 | D46: =ENTRANTES!L156 -> 2.6363636 | E46: =D46*1.1 -> 2.9 | F46: =D46-C46-(E46*0.2) -> 1.792322 | G46: =F46/D46*100 -> 67.984626 | H46: =100-G46 -> 32.015374 | J46: =I46/SUM($I$3:I244)*100 -> 0
A47: ENTRANTES | B47: NEW PATATAS CHEESE BACON | K47: PROXIMAMENTE
A50: POSTRES | B50: TARTA LOTUS | C50: =POSTRES!L50 -> 1.43 | D50: =POSTRES!L60 -> 7.2727273 | E50: =D50*1.1 -> 8 | F50: =D50-C50-(E50*0.2) -> 4.2427273 | G50: =F50/D50*100 -> 58.3375 | H50: =100-G50 -> 41.6625 | J50: =I50/SUM($I$3:I248)*100 -> 0 | K50: RESOLVER
A51: POSTRES | B51: TARTA QUESO | C51: =POSTRES!L6 -> 4.3 | D51: =POSTRES!L16 -> 7.2727273 | E51: =D51*1.1 -> 8 | F51: =D51-C51-(E51*0.2) -> 1.3727273 | G51: =F51/D51*100 -> 18.875 | H51: =100-G51 -> 81.125 | J51: =I51/SUM($I$3:I249)*100 -> 0
A52: POSTRES | B52: TARTA DUBAI | C52: =POSTRES!L28 -> 4.3 | D52: =POSTRES!L38 -> 7.2727273 | E52: =D52*1.1 -> 8 | F52: =D52-C52-(E52*0.2) -> 1.3727273 | G52: =F52/D52*100 -> 18.875 | H52: =100-G52 -> 81.125 | K52: RETIRADO
A55: HOTDOG | B55: HOT DOG CHILL BBQ | C55: ='BRIOCH-SUBS'!L241 -> 1.8283224 | D55: ='BRIOCH-SUBS'!P242 -> 7.5 | E55: =D55*1.1 -> 8.25 | F55: =D55-C55-(E55*0.2) -> 4.0216776 | G55: =F55/D55*100 -> 53.622368 | H55: =100-G55 -> 46.377632 | J55: =I55/SUM($I$3:I253)*100 -> 0 | K55: RESOLVER

Sheet MENUS
C2: PRODUCTO | D2: MENU SERRANO DE POLLO+LATA+TARRO
B5: ID | C5: Nombre del Plato | D5: Unidad de medida | E5: Precio Unidad | F5: Cantidad Bruta | G5: Cantidad Cocinada/limpia | H5: Merma % | I5: Coste | K5: INDICE | O5: INDICE UBER
B6: {=+XLOOKUP(C6,'Base de datos'!C:C,'Base de datos'!A:A,"",FALSE)} | D6: Kg | E6: {=+XLOOKUP(B6,'Base de datos'!A:A,'Base de datos'!H:H,0)} -> 0 | H6: =IFERROR(1-G6/F6,"") | I6: =IFERROR(E6*F6,"") -> 0 | K6: Coste Total | L6: =SUM(I6:I19) -> 2.4327449 | O6: Coste Total | P6: =L6 -> 2.4327449
B7: =K31 -> PVP | C7: =C31 | D7: Kg | H7: =IFERROR(1-G7/F7,"") | I7: =IFERROR(E7*F7,"") -> 0 | K7: PVP | L7: 8 | O7: PVP | P7: 8.2
B8: {=+XLOOKUP(C8,'Base de datos'!C:C,'Base de datos'!A:A,"",FALSE)} -> 63 | C8: PECHUGA POLLO FILETEADA 25 SADA | D8: Kg | E8: {=+XLOOKUP(B8,'Base de datos'!A:A,'Base de datos'!H:H,0)} -> 6.15 | F8: 0.11 | G8: 0.1 | H8: =IFERROR(1-G8/F8,"") -> 0.090909091 | I8: =IFERROR(E8*F8,"") -> 0.6765 | K8: Precio venta (s/IVA) | L8: =L7/1.1 -> 7.2727273 | O8: Precio venta (s/IVA) | P8: =P7/1.1 -> 7.4545455
B9: {=+XLOOKUP(C9,'Base de datos'!C:C,'Base de datos'!A:A,"",FALSE)} -> 110 | C9: PAN BAGUETTE LA PARRA | D9: Unidad | E9: {=+XLOOKUP(B9,'Base de datos'!A:A,'Base de datos'!H:H,0)} -> 0.28181818 | F9: 1 | G9: 1 | H9: =IFERROR(1-G9/F9,"") -> 0 | I9: =IFERROR(E9*F9,"") -> 0.28181818 | K9: IVA | L9: 0.1 | O9: IVA | P9: 0.1
B10: {=+XLOOKUP(C10,'Base de datos'!C:C,'Base de datos'!A:A,"",FALSE)} -> 96 | C10: TOMATE DANIELA | D10: Kg | E10: {=+XLOOKUP(B10,'Base de datos'!A:A,'Base de datos'!H:H,0)} -> 1.8 | F10: 0.01 | G10: 0.01 | H10: =IFERROR(1-G10/F10,"") -> 0 | I10: =IFERROR(E10*F10,"") -> 0.018 | K10: Coste de Producto | L10: =L6/L8*100 -> 33.450242 | M10: % | O10: Coste de Producto | P10: =P6/P8*100 -> 32.634383 | Q10: %
B11: {=+XLOOKUP(C11,'Base de datos'!C:C,'Base de datos'!A:A,"",FALSE)} -> 72 | C11: PIMIENTO | D11: Kg | E11: {=+XLOOKUP(B11,'Base de datos'!A:A,'Base de datos'!H:H,0)} -> 2 | F11: 0.01 | G11: 0.01 | H11: =IFERROR(1-G11/F11,"") -> 0 | I11: =IFERROR(E11*F11,"") -> 0.02 | K11: Margen Bruto | L11: =100-L10 -> 66.549758 | M11: % | O11: Margen Bruto | P11: =P8-P6 -> 5.0218006 | Q11: €
B12: {=+XLOOKUP(C12,'Base de datos'!C:C,'Base de datos'!A:A,"",FALSE)} -> 37 | C12: JAMON LONCHEADO CUMBRE IB. | D12: Kg | E12: {=+XLOOKUP(B12,'Base de datos'!A:A,'Base de datos'!H:H,0)} -> 7 | F12: 0.02 | G12: 0.02 | H12: =IFERROR(1-G12/F12,"") -> 0 | I12: =IFERROR(E12*F12,"") -> 0.14 | O12: Margen Bruto post Uber | P12: =P8-P6-(P7*0.2) -> 3.3818006 | Q12: €
B13: {=+XLOOKUP(C13,'Base de datos'!C:C,'Base de datos'!A:A,"",FALSE)} -> 34 | C13: HUEVO LÍQUIDO GRANJA | D13: Litro | E13: {=+XLOOKUP(B13,'Base de datos'!A:A,'Base de datos'!H:H,0)} -> 3.75 | F13: 0.02 | G13: 0.02 | H13: =IFERROR(1-G13/F13,"") -> 0 | I13: =IFERROR(E13*F13,"") -> 0.075 | K13: SERRANO POLLO | L13: 6 | O13: Margen Bruto post Uber | P13: =P12/P8 -> 0.45365617 | Q13: %
B14: {=+XLOOKUP(C14,'Base de datos'!C:C,'Base de datos'!A:A,"",FALSE)} | D14: Kg | E14: {=+XLOOKUP(B14,'Base de datos'!A:A,'Base de datos'!H:H,0)} -> 0 | I14: =IFERROR(E14*F14,"") -> 0 | K14: TARRO ALIOLI | L14: 0.5
B15: {=+XLOOKUP(C15,'Base de datos'!C:C,'Base de datos'!A:A,"",FALSE)} -> 93 | C15: SERVILLETA 40X40 100UD | D15: Unidad | E15: {=+XLOOKUP(B15,'Base de datos'!A:A,'Base de datos'!H:H,0)} -> 0.0277 | F15: 1 | G15: 1 | H15: =IFERROR(1-G15/F15,"") -> 0 | I15: =IFERROR(E15*F15,"") -> 0.0277 | K15: BEBIDA COCACOLA | L15: 1.5
B16: {=+XLOOKUP(C16,'Base de datos'!C:C,'Base de datos'!A:A,"",FALSE)} -> 29 | C16: ENVASE SERRANO IP10 .25 | D16: Unidad | E16: {=+XLOOKUP(B16,'Base de datos'!A:A,'Base de datos'!H:H,0)} -> 0.1946 | F16: 1 | G16: 1 | H16: =IFERROR(1-G16/F16,"") -> 0 | I16: =IFERROR(E16*F16,"") -> 0.1946 | K16: TOTAL | L16: =SUM(L13:L15) -> 8
B17: {=+XLOOKUP(C17,'Base de datos'!C:C,'Base de datos'!A:A,"",FALSE)} -> 58 | C17: PATATAS FRY & DIP 25 | D17: Kg | E17: {=+XLOOKUP(B17,'Base de datos'!A:A,'Base de datos'!H:H,0)} -> 2.15 | F17: 0.09 | H17: =IFERROR(1-G17/F17,"") -> 1 | I17: =IFERROR(E17*F17,"") -> 0.1935
B18: {=+XLOOKUP(C18,'Base de datos'!C:C,'Base de datos'!A:A,"",FALSE)} -> 103 | C18: LATA COCACOLA | D18: Kg | E18: {=+XLOOKUP(B18,'Base de datos'!A:A,'Base de datos'!H:H,0)} -> 0.61375 | F18: 1 | H18: =IFERROR(1-G18/F18,"") -> 1 | I18: =IFERROR(E18*F18,"") -> 0.61375
B19: {=+XLOOKUP(C19,'Base de datos'!C:C,'Base de datos'!A:A,"",FALSE)} -> 166 | C19: TARRITO ALIOLI | D19: Kg | E19: {=+XLOOKUP(B19,'Base de datos'!A:A,'Base de datos'!H:H,0)} -> 0.19187671 | F19: 1 | H19: =IFERROR(1-G19/F19,"") -> 1 | I19: =IFERROR(E19*F19,"") -> 0.19187671
C21: Notas de elaboración
B30: {=+XLOOKUP(C30,'Base de datos'!C:C,'Base de datos'!A:A,"",FALSE)} | D30: Kg | E30: {=+XLOOKUP(B30,'Base de datos'!A:A,'Base de datos'!H:H,0)} -> 0 | H30: =IFERROR(1-G30/F30,"") | I30: =IFERROR(E30*F30,"") -> 0 | K30: Coste Total | L30: =SUM(I30:I35) -> 4.3
B31: =K49 | C31: =C49 | D31: Kg | E31: =K55 -> IVA | H31: =IFERROR(1-G31/F31,"") | I31: =IFERROR(E31*F31,"") | K31: PVP | L31: 6.5
B32: {=+XLOOKUP(C32,'Base de datos'!C:C,'Base de datos'!A:A,"",FALSE)} -> 97 | C32: TARTAS DUBAI | D32: Kg | E32: {=+XLOOKUP(B32,'Base de datos'!A:A,'Base de datos'!H:H,0)} -> 4.3 | F32: 1 | G32: 1 | H32: =IFERROR(1-G32/F32,"") -> 0 | I32: =IFERROR(E32*F32,"") -> 4.3 | K32: Precio venta (s/IVA) | L32: =L31/1.1 -> 5.9090909
B33: {=+XLOOKUP(C33,'Base de datos'!C:C,'Base de datos'!A:A,"",FALSE)} | D33: Unidad | E33: {=+XLOOKUP(B33,'Base de datos'!A:A,'Base de datos'!H:H,0)} -> 0 | I33: =IFERROR(E33*F33,"") -> 0 | K33: IVA | L33: 0.1
B34: {=+XLOOKUP(C34,'Base de datos'!C:C,'Base de datos'!A:A,"",FALSE)} | D34: Kg | E34: {=+XLOOKUP(B34,'Base de datos'!A:A,'Base de datos'!H:H,0)} -> 0 | I34: =IFERROR(E34*F34,"") -> 0 | K34: Coste de Producto | L34: =L30/L32*100 -> 72.769231 | M34: %
B35: {=+XLOOKUP(C35,'Base de datos'!C:C,'Base de datos'!A:A,"",FALSE)} | D35: Unidad | E35: {=+XLOOKUP(B35,'Base de datos'!A:A,'Base de datos'!H:H,0)} -> 0 | I35: =IFERROR(E35*F35,"") -> 0 | K35: Margen Bruto | L35: =100-L34 -> 27.230769 | M35: %
C37: Notas de elaboración 1 | K37: INDICE UBER
K38: Coste Total | L38: =L30 -> 4.3
K39: PVP | L39: 8
C40: DESCATALOGADA | K40: Precio venta (s/IVA) | L40: =L39/1.1 -> 7.2727273
K41: IVA | L41: 0.1
K42: Coste de Producto | L42: =L38/L40*100 -> 59.125 | M42: %
K43: Margen Bruto | L43: =L40-L38 -> 2.9727273 | M43: €
K44: Margen Bruto post Uber | L44: =L40-L38-(L39*0.2) -> 1.3727273 | M44: €
K45: Margen Bruto post Uber | L45: =L44/L40 -> 0.18875 | M45: %
C48: PRODUCTO | D48: TARTA LOTUS | K48: IR A BASE DE DATOS
B51: ID | C51: Nombre del Plato | D51: Unidad de medida | E51: Precio Unidad | F51: Cantidad Bruta | G51: Cantidad Cocinada/limpia | H51: Merma % | I51: Coste | K51: INDICE
B52: {=+XLOOKUP(C52,'Base de datos'!C:C,'Base de datos'!A:A,"",FALSE)} | D52: Kg | E52: {=+XLOOKUP(B52,'Base de datos'!A:A,'Base de datos'!H:H,0)} -> 0 | H52: =IFERROR(1-G52/F52,"") | I52: =IFERROR(E52*F52,"") -> 0 | K52: Coste Total | L52: =SUM(I52:I57) -> 1.43
B53: =K69 | C53: =C69 | D53: Kg | E53: =K75 | H53: =IFERROR(1-G53/F53,"") | I53: =IFERROR(E53*F53,"") -> 0 | K53: PVP | L53: 6
B54: {=+XLOOKUP(C54,'Base de datos'!C:C,'Base de datos'!A:A,"",FALSE)} -> 92 | C54: TARTA LOTUS | D54: Kg | E54: {=+XLOOKUP(B54,'Base de datos'!A:A,'Base de datos'!H:H,0)} -> 1.43 | F54: 1 | G54: 1 | H54: =IFERROR(1-G54/F54,"") -> 0 | I54: =IFERROR(E54*F54,"") -> 1.43 | K54: Precio venta (s/IVA) | L54: =L53/1.1 -> 5.4545455
B55: {=+XLOOKUP(C55,'Base de datos'!C:C,'Base de datos'!A:A,"",FALSE)} | D55: Unidad | E55: {=+XLOOKUP(B55,'Base de datos'!A:A,'Base de datos'!H:H,0)} -> 0 | I55: =IFERROR(E55*F55,"") -> 0 | K55: IVA | L55: 0.1
B56: {=+XLOOKUP(C56,'Base de datos'!C:C,'Base de datos'!A:A,"",FALSE)} | D56: Kg | E56: {=+XLOOKUP(B56,'Base de datos'!A:A,'Base de datos'!H:H,0)} -> 0 | I56: =IFERROR(E56*F56,"") -> 0 | K56: Coste de Producto | L56: =L52/L54*100 -> 26.216667 | M56: %
B57: {=+XLOOKUP(C57,'Base de datos'!C:C,'Base de datos'!A:A,"",FALSE)} | D57: Unidad | E57: {=+XLOOKUP(B57,'Base de datos'!A:A,'Base de datos'!H:H,0)} -> 0 | I57: =IFERROR(E57*F57,"") -> 0 | K57: Margen Bruto | L57: =100-L56 -> 73.783333 | M57: %
C59: Notas de elaboración | K59: INDICE UBER
K60: Coste Total | L60: =L52 -> 1.43
K61: PVP | L61: 8
K62: Precio venta (s/IVA) | L62: =L61/1.1 -> 7.2727273
K63: IVA | L63: 0.1
K64: Coste de Producto | L64: =L60/L62*100 -> 19.6625 | M64: %
K65: Margen Bruto | L65: =L62-L60 -> 5.8427273 | M65: €
K66: Margen Bruto post Uber | L66: =L62-L60-(L61*0.2) -> 4.2427273 | M66: €
K67: Margen Bruto post Uber | L67: =L66/L62 -> 0.583375 | M67: %

Sheet TAREASNOTAS
B4: TAREAS
B5: VER ESCANDALLO HOTDOG
B6: MEDIA PONDERADA EN CELDA DE RESUMEN DE COSTE
B7: RAPPEL R2R APLICAO

Sheet VENTAS TOTALES
A1: Categoría | B1: Producto | C1: Unidades | D1: Total (€) | E1: ULTIMA ACTUALIZACION | G1: 46090
A2: Burgers | B2: Bichota Campeona 2023 Sevilla League | C2: 608 | D2: 6129
A3: Burgers | B3: Doblesquesos | C3: 634 | D3: 5293.5
A4: Serranitos | B4: Serranito Pollo | C4: 837 | D4: 5073
A5: Burgers | B5: Cero15 | C5: 450 | D5: 3677.2
A6: Burgers & MENU | B6: Dobles Quesos | C6: 282 | D6: 3324.8
A7: Burgers | B7: Barriera Cheese burger PM | C7: 386 | D7: 2968.4
A8: Burgers & MENU | B8: CAMPEONA SEVILLA BURGER LEAGUE “LA BICHOTA” | C8: 222 | D8: 2768.1
A9: SERRANITOS & BAGUETTES by SOFI | B9: SERRANITO de POLLO + patatas | C9: 316 | D9: 2712.1
A10: Burgers | B10: Sofi | C10: 312 | D10: 2628.7
A11: Bocatas | B11: Joaquinto | C11: 288 | D11: 2312.7
A12: Serranitos | B12: Serranito Pollo Asado | C12: 279 | D12: 1862.5
A13: Serranitos | B13: Serranito Solomillo | C13: 253 | D13: 1780.5
... A146: TARRO EXTRA | B146: TARRO KETCHUP EXTRA | C146: 1 | D146: 0.75

Sheet Bebidas
B2: Instrucciones: 1. Solo editar sobre las celdas en blanco y naranja 2. Si se pone aperitivo de cortesía con la bebida rellenar en la celda naranja (MEDIA del coste de aperitivos) 3. Meter IVA
B4: Coste aperitivo | C4: 0.1
B5: IVA | C5: 0.1
C7: Coste total | D7: Coste apertivo | E7: Coste bebida | F7: PVP con IVA | G7: PVP sin IVA | H7: Margen Bruto | I7: Coste de Producto%
B8: CERVEZAS
C9: =SUM($C$4+E9) -> 0.1 | G9: =F9/1.21 -> 0 | H9: =G9-C9 -> -0.1 | I9: =1-(H9/G9) -> #DIV/0!
C10: =SUM($C$4+E10) -> 0.1 | G10: =F10/1.21 -> 0 | H10: =G10-C10 -> -0.1 | I10: =1-(H10/G10) -> #DIV/0!
C11: 0.1 | G11: =F11/1.21 -> 0 | H11: =G11-C11 -> -0.1 | I11: =1-(H11/G11) -> #DIV/0!
C12: =SUM($C$4+E12) -> 0.1 | G12: =F12/1.21 -> 0 | H12: =G12-C12 -> -0.1 | I12: =1-(H12/G12) -> #DIV/0!
C13: =SUM($C$4+E13) -> 0.1 | G13: =F13/1.21 -> 0 | H13: =G13-C13 -> -0.1 | I13: =1-(H13/G13) -> #DIV/0!
C14: =SUM($C$4+E14) -> 0.1 | G14: =F14/1.21 -> 0 | H14: =G14-C14 -> -0.1 | I14: =1-(H14/G14) -> #DIV/0!
C15: =SUM($C$4+E15) -> 0.1 | G15: =F15/1.21 -> 0 | H15: =G15-C15 -> -0.1 | I15: =1-(H15/G15) -> #DIV/0!
C16: =SUM($C$4+E16) -> 0.1 | G16: =F16/1.21 -> 0 | H16: =G16-C16 -> -0.1 | I16: =1-(H16/G16) -> #DIV/0!
C17: =SUM($C$4+E17) -> 0.1 | G17: =F17/1.21 -> 0 | H17: =G17-C17 -> -0.1 | I17: =1-(H17/G17) -> #DIV/0!
C18: =SUM($C$4+E18) -> 0.1 | G18: =F18/1.21 -> 0 | H18: =G18-C18 -> -0.1 | I18: =1-(H18/G18) -> #DIV/0!
B19: REFRESCOS | C19: =SUM($C$4+E19) -> 0.1
B20: ='Base de datos'!C102 -> LATA AQUARIOUS LIMON | C20: =SUM($C$4+E20) -> 0.82791667 | E20: ='Base de datos'!H102 -> 0.72791667 | F20: 1.6 | G20: =F20/1.21 -> 1.322314 | H20: =G20-C20 -> 0.49439738 | I20: =1-(H20/G20) -> 0.62611198
B21: ='Base de datos'!C103 -> LATA AQUARIOUS NARANJA | C21: =SUM($C$4+E21) -> 0.82791667 | E21: ='Base de datos'!H103 -> 0.72791667 | F21: 1.6 | G21: =F21/1.21 -> 1.322314 | H21: =G21-C21 -> 0.49439738 | I21: =1-(H21/G21) -> 0.62611198
B22: ='Base de datos'!C104 -> LATA COCACOLA | C22: =SUM($C$4+E22) -> 0.71375 | E22: ='Base de datos'!H104 -> 0.61375 | F22: 1.5 | G22: =F22/1.21 -> 1.2396694 | H22: =G22-C22 -> 0.52591942 | I22: =1-(H22/G22) -> 0.57575833
B23: ='Base de datos'!C105 -> LATA COCACOLA ZERO | C23: =SUM($C$4+E23) -> 0.71375 | E23: ='Base de datos'!H105 -> 0.61375 | F23: 1.5 | G23: =F23/1.21 -> 1.2396694 | H23: =G23-C23 -> 0.52591942 | I23: =1-(H23/G23) -> 0.57575833
B24: ='Base de datos'!C106 -> LATA COLACOLA ZERO ZERO | C24: =SUM($C$4+E24) -> 0.71375 | E24: ='Base de datos'!H106 -> 0.61375 | F24: 1.5 | G24: =F24/1.21 -> 1.2396694 | H24: =G24-C24 -> 0.52591942 | I24: =1-(H24/G24) -> 0.57575833
B25: ='Base de datos'!C107 -> LATA FANTA LIMON | C25: =SUM($C$4+E25) -> 0.62666667 | E25: ='Base de datos'!H107 -> 0.52666667 | F25: 1.5 | G25: =F25/1.21 -> 1.2396694 | H25: =G25-C25 -> 0.61300275 | I25: =1-(H25/G25) -> 0.50551111
B26: ='Base de datos'!C108 -> LATA FANTA NARANJA | C26: =SUM($C$4+E26) -> 0.62666667 | E26: ='Base de datos'!H108 -> 0.52666667 | F26: 1.5 | G26: =F26/1.21 -> 1.2396694 | H26: =G26-C26 -> 0.61300275 | I26: =1-(H26/G26) -> 0.50551111
B27: ='Base de datos'!C109 -> LATA FUZEE TEA LIMON | C27: =SUM($C$4+E27) -> 0.735 | E27: ='Base de datos'!H109 -> 0.635 | F27: 1.6 | G27: =F27/1.21 -> 1.322314 | H27: =G27-C27 -> 0.58731405 | I27: =1-(H27/G27) -> 0.55584375
B28: ='Base de datos'!C110 -> LATA FUZEE TEA MARACUYA | C28: =SUM($C$4+E28) -> 0.735 | E28: ='Base de datos'!H110 -> 0.635 | F28: 1.6 | G28: =F28/1.21 -> 1.322314 | H28: =G28-C28 -> 0.58731405 | I28: =1-(H28/G28) -> 0.55584375
C29: =SUM($C$4+E29) -> 0.1 | G29: =F29/1.21 -> 0 | H29: =G29-C29 -> -0.1 | I29: =1-(H29/G29) -> #DIV/0!
C30: =SUM($C$4+E30) -> 0.1 | G30: =F30/1.1 -> 0 | H30: =G30-C30 -> -0.1 | I30: =1-(H30/G30) -> #DIV/0!
C31: =SUM($C$4+E31) -> 0.1 | G31: =F31/1.21 -> 0 | H31: =G31-C31 -> -0.1 | I31: =1-(H31/G31) -> #DIV/0!
C32: =SUM($C$4+E32) -> 0.1 | G32: =F32/1.21 -> 0 | H32: =G32-C32 -> -0.1 | I32: =1-(H32/G32) -> #DIV/0!
C33: =SUM($C$4+E33) -> 0.1 | G33: =F33/1.1 -> 0 | H33: =G33-C33 -> -0.1 | I33: =1-(H33/G33) -> #DIV/0!
B34: Copas de vino
C35: =SUM(E35) -> 0 | G35: =F35/1.21 -> 0 | H35: =G35-C35 -> 0 | I35: =1-(H35/G35) -> #DIV/0! | K35: AGUILA Y ORO APLICANDO UN 10% DE MERMA
C36: =SUM(E36) -> 0 | G36: =F36/1.21 -> 0 | H36: =G36-C36 -> 0 | I36: =1-(H36/G36) -> #DIV/0!
C37: =SUM(E37) -> 0 | G37: =F37/1.21 -> 0 | H37: =G37-C37 -> 0 | I37: =1-(H37/G37) -> #DIV/0!
C38: =SUM(E38) -> 0 | G38: =F38/1.21 -> 0 | H38: =G38-C38 -> 0 | I38: =1-(H38/G38) -> #DIV/0!
C39: =SUM(E39) -> 0 | G39: =F39/1.21 -> 0 | H39: =G39-C39 -> 0 | I39: =1-(H39/G39) -> #DIV/0!
C40: =SUM(E40) -> 0 | G40: =F40/1.21 -> 0 | H40: =G40-C40 -> 0 | I40: =1-(H40/G40) -> #DIV/0!
C41: =SUM(E41) -> 0 | G41: =F41/1.21 -> 0 | H41: =G41-C41 -> 0 | I41: =1-(H41/G41) -> #DIV/0!
C42: =SUM(E42) -> 0 | G42: =F42/1.21 -> 0 | H42: =G42-C42 -> 0 | I42: =1-(H42/G42) -> #DIV/0!
C43: =SUM(E43) -> 0 | G43: =F43/1.21 -> 0 | H43: =G43-C43 -> 0 | I43: =1-(H43/G43) -> #DIV/0!
C44: =SUM(E44) -> 0 | G44: =F44/1.21 -> 0 | H44: =G44-C44 -> 0 | I44: =1-(H44/G44) -> #DIV/0!
C45: =SUM(E45) -> 0 | G45: =F45/1.21 -> 0 | H45: =G45-C45 -> 0 | I45: =1-(H45/G45) -> #DIV/0!
B46: Botellas de vino
C47: =SUM(E47) -> 0 | G47: =F47/1.21 -> 0 | H47: =G47-C47 -> 0 | I47: =1-(H47/G47) -> #DIV/0!
C48: =SUM(E48) -> 0 | G48: =F48/1.21 -> 0 | H48: =G48-C48 -> 0 | I48: =1-(H48/G48) -> #DIV/0!
C49: =SUM(E49) -> 0 | G49: =F49/1.21 -> 0 | H49: =G49-C49 -> 0 | I49: =1-(H49/G49) -> #DIV/0!
C50: =SUM(E50) -> 0 | G50: =F50/1.21 -> 0 | H50: =G50-C50 -> 0 | I50: =1-(H50/G50) -> #DIV/0!
C51: =SUM(E51) -> 0 | G51: =F51/1.21 -> 0 | H51: =G51-C51 -> 0 | I51: =1-(H51/G51) -> #DIV/0!
C52: =SUM(E52) -> 0 | G52: =F52/1.21 -> 0 | H52: =G52-C52 -> 0 | I52: =1-(H52/G52) -> #DIV/0!
C53: =SUM(E53) -> 0 | G53: =F53/1.21 -> 0 | H53: =G53-C53 -> 0 | I53: =1-(H53/G53) -> #DIV/0!
C54: =SUM(E54) -> 0 | G54: =F54/1.21 -> 0 | H54: =G54-C54 -> 0 | I54: =1-(H54/G54) -> #DIV/0!
C55: =SUM(E55) -> 0 | G55: =F55/1.21 -> 0 | H55: =G55-C55 -> 0 | I55: =1-(H55/G55) -> #DIV/0!
C56: =SUM(E56) -> 0 | G56: =F56/1.21 -> 0 | H56: =G56-C56 -> 0 | I56: =1-(H56/G56) -> #DIV/0!
C57: =SUM(E57) -> 0 | G57: =F57/1.21 -> 0 | H57: =G57-C57 -> 0 | I57: =1-(H57/G57) -> #DIV/0!
C58: =SUM(E58) -> 0 | G58: =F58/1.21 -> 0 | H58: =G58-C58 -> 0 | I58: =1-(H58/G58) -> #DIV/0!
B62: Beneficio bruto promedio | C62: =AVERAGE(I9:I45) -> #DIV/0!

Sheet SALSAS
C2: PRODUCTO | D2: SALSAS PROPIAS
B5: ID | C5: Nombre del Plato | D5: Unidad de medida | E5: Precio Unidad | F5: Cantidad Bruta | G5: Cantidad Cocinada/limpia | H5: Merma % | I5: Coste | K5: INDICE
B6: {=+XLOOKUP(C6,'Base de datos'!C:C,'Base de datos'!A:A,"",FALSE)} | D6: Kg | E6: {=+XLOOKUP(B6,'Base de datos'!A:A,'Base de datos'!H:H,0)} -> 0 | H6: =IFERROR(1-G6/F6,"") | I6: =IFERROR(E6*F6,"") -> 0 | K6: Coste Total | L6: =SUM(I6:I17) -> 0.011561974
B7: =K79 -> E.3 | C7: =C79 -> MOJO PICON | D7: Kg | E7: =K35 -> 1.1561974 | F7: 0.01 | H7: =IFERROR(1-G7/F7,"") -> 1 | I7: =IFERROR(E7*F7,"") -> 0.011561974 | K7: PVP | L7: 4
K8: Precio venta (s/IVA) | L8: =L7/1.1 -> 3.6363636
K9: IVA | L9: 0.1
K10: Coste de Producto | L10: =L6/L8*100 -> 0.31795428 | M10: %
K11: Margen Bruto | L11: =100-L10 -> 99.682046 | M11: %
B14: {=+XLOOKUP(C14,'Base de datos'!C:C,'Base de datos'!A:A,"",FALSE)} | D14: Kg | E14: {=+XLOOKUP(B14,'Base de datos'!A:A,'Base de datos'!H:H,0)} -> 0 | I14: =IFERROR(E14*F14,"") -> 0
B15: {=+XLOOKUP(C15,'Base de datos'!C:C,'Base de datos'!A:A,"",FALSE)} | D15: Kg | E15: {=+XLOOKUP(B15,'Base de datos'!A:A,'Base de datos'!H:H,0)} -> 0 | I15: =IFERROR(E15*F15,"") -> 0
B16: {=+XLOOKUP(C16,'Base de datos'!C:C,'Base de datos'!A:A,"",FALSE)} | D16: Kg | E16: {=+XLOOKUP(B16,'Base de datos'!A:A,'Base de datos'!H:H,0)} -> 0 | I16: =IFERROR(E16*F16,"") -> 0
B17: {=+XLOOKUP(C17,'Base de datos'!C:C,'Base de datos'!A:A,"",FALSE)} | D17: Kg | E17: {=+XLOOKUP(B17,'Base de datos'!A:A,'Base de datos'!H:H,0)} -> 0 | H17: =IFERROR(1-G17/F17,"") | I17: =IFERROR(E17*F17,"") -> 0
C19: Notas de elaboración
B29: ID | C29: ALIOLI | D29: Unidad | E29: Precio Unidad | F29: Cantidad Bruta | G29: Cantidad Cocinada/limpia | H29: Merma % | I29: Coste | K29: E.1
B30: {=+XLOOKUP(C30,'Base de datos'!C:C,'Base de datos'!A:A,"",FALSE)} -> 2 | C30: Aceite de girasol Adl | D30: Kg | E30: {=+XLOOKUP(B30,'Base de datos'!A:A,'Base de datos'!H:H,0)} -> 1.518 | F30: 5.2 | H30: =IFERROR(1-G30/F30,"") -> 1 | I30: =IFERROR(E30*F30,"") -> 7.8936 | K30: Coste Total
B31: {=+XLOOKUP(C31,'Base de datos'!C:C,'Base de datos'!A:A,"",FALSE)} -> 118 | C31: AJO | D31: Kg | E31: {=+XLOOKUP(B31,'Base de datos'!A:A,'Base de datos'!H:H,0)} -> 5 | F31: 0.15 | H31: =IFERROR(1-G31/F31,"") -> 1 | I31: =IFERROR(E31*F31,"") -> 0.75 | K31: =SUM(I30:I39) -> 8.7871
B32: {=+XLOOKUP(C32,'Base de datos'!C:C,'Base de datos'!A:A,"",FALSE)} -> 119 | C32: SAL | D32: Kg | E32: {=+XLOOKUP(B32,'Base de datos'!A:A,'Base de datos'!H:H,0)} -> 0.43 | F32: 0.16 | H32: =IFERROR(1-G32/F32,"") -> 1 | I32: =IFERROR(E32*F32,"") -> 0.0688 | K32: Cantidad Fabricación
B33: {=+XLOOKUP(C33,'Base de datos'!C:C,'Base de datos'!A:A,"",FALSE)} -> 100 | C33: VINAGRE | D33: Kg | E33: {=+XLOOKUP(B33,'Base de datos'!A:A,'Base de datos'!H:H,0)} -> 0.83 | F33: 0.09 | H33: =IFERROR(1-G33/F33,"") -> 1 | I33: =IFERROR(E33*F33,"") -> 0.0747 | K33: =SUM(F30:F39) -> 7.6
B34: {=+XLOOKUP(C34,'Base de datos'!C:C,'Base de datos'!A:A,"",FALSE)} | C34: CLARA PASTEURIZADA | D34: Kg | E34: {=+XLOOKUP(B34,'Base de datos'!A:A,'Base de datos'!H:H,0)} -> 0 | F34: 1 | H34: =IFERROR(1-G34/F34,"") -> 1 | I34: =IFERROR(E34*F34,"") -> 0 | K34: Precio Base
B35: {=+XLOOKUP(C35,'Base de datos'!C:C,'Base de datos'!A:A,"",FALSE)} | C35: HUEVO PASTEURIZADO | D35: Kg | E35: {=+XLOOKUP(B35,'Base de datos'!A:A,'Base de datos'!H:H,0)} -> 0 | F35: 1 | H35: =IFERROR(1-G35/F35,"") -> 1 | I35: =IFERROR(E35*F35,"") -> 0 | K35: =K31/K33 -> 1.1561974
B36: {=+XLOOKUP(C36,'Base de datos'!C:C,'Base de datos'!A:A,"",FALSE)} | D36: Kg | E36: {=+XLOOKUP(B36,'Base de datos'!A:A,'Base de datos'!H:H,0)} -> 0 | H36: =IFERROR(1-G36/F36,"") | I36: =IFERROR(E36*F36,"") -> 0 | K36: Nº de Raciones según receta
B37: {=+XLOOKUP(C37,'Base de datos'!C:C,'Base de datos'!A:A,"",FALSE)} | D37: Kg | E37: {=+XLOOKUP(B37,'Base de datos'!A:A,'Base de datos'!H:H,0)} -> 0 | H37: =IFERROR(1-G37/F37,"") | I37: =IFERROR(E37*F37,"") -> 0 | K37: =K33/F7 -> 760
B38: {=+XLOOKUP(C38,'Base de datos'!C:C,'Base de datos'!A:A,"",FALSE)} | D38: Kg | E38: {=+XLOOKUP(B38,'Base de datos'!A:A,'Base de datos'!H:H,0)} -> 0 | H38: =IFERROR(1-G38/F38,"") | I38: =IFERROR(E38*F38,"") -> 0
B39: {=+XLOOKUP(C39,'Base de datos'!C:C,'Base de datos'!A:A,"",FALSE)} | D39: Kg | E39: {=+XLOOKUP(B39,'Base de datos'!A:A,'Base de datos'!H:H,0)} -> 0 | H39: =IFERROR(1-G39/F39,"") | I39: =IFERROR(E39*F39,"") -> 0
C41: Notas de elaboración 1
C42: Alioli 8kg Ajo 5,19€/kg 150gr ajo 160gr Sal 90gr Vinagre 1LClara 1LHuevo 5,2L aceite girasol
B54: ID | C54: MAYONESA | D54: Unidad | E54: Precio Unidad | F54: Cantidad Bruta | G54: Cantidad Cocinada/limpia | H54: Merma % | I54: Coste | K54: E.2
B55: {=+XLOOKUP(C55,'Base de datos'!C:C,'Base de datos'!A:A,"",FALSE)} -> 2 | C55: Aceite de girasol Adl | D55: Kg | E55: {=+XLOOKUP(B55,'Base de datos'!A:A,'Base de datos'!H:H,0)} -> 1.518 | F55: 5.2 | H55: =IFERROR(1-G55/F55,"") -> 1 | I55: =IFERROR(E55*F55,"") -> 7.8936 | K55: Coste Total
B56: {=+XLOOKUP(C56,'Base de datos'!C:C,'Base de datos'!A:A,"",FALSE)} | D56: Kg | E56: {=+XLOOKUP(B56,'Base de datos'!A:A,'Base de datos'!H:H,0)} -> 0 | H56: =IFERROR(1-G56/F56,"") | I56: =IFERROR(E56*F56,"") -> 0 | K56: =SUM(I55:I64) -> 14.2871
B57: {=+XLOOKUP(C57,'Base de datos'!C:C,'Base de datos'!A:A,"",FALSE)} -> 119 | C57: SAL | D57: Kg | E57: {=+XLOOKUP(B57,'Base de datos'!A:A,'Base de datos'!H:H,0)} -> 0.43 | F57: 0.16 | H57: =IFERROR(1-G57/F57,"") -> 1 | I57: =IFERROR(E57*F57,"") -> 0.0688 | K57: Cantidad Fabricación
B58: {=+XLOOKUP(C58,'Base de datos'!C:C,'Base de datos'!A:A,"",FALSE)} -> 100 | C58: VINAGRE | D58: Kg | E58: {=+XLOOKUP(B58,'Base de datos'!A:A,'Base de datos'!H:H,0)} -> 0.83 | F58: 0.09 | H58: =IFERROR(1-G58/F58,"") -> 1 | I58: =IFERROR(E58*F58,"") -> 0.0747 | K58: =SUM(F55:F64) -> 7.45
B59: {=+XLOOKUP(C59,'Base de datos'!C:C,'Base de datos'!A:A,"",FALSE)} -> 32 | C59: CLARA LIQUIDA GRANJA | D59: Kg | E59: {=+XLOOKUP(B59,'Base de datos'!A:A,'Base de datos'!H:H,0)} -> 2.5 | F59: 1 | H59: =IFERROR(1-G59/F59,"") -> 1 | I59: =IFERROR(E59*F59,"") -> 2.5 | K59: Precio Base
B60: {=+XLOOKUP(C60,'Base de datos'!C:C,'Base de datos'!A:A,"",FALSE)} -> 34 | C60: HUEVO LÍQUIDO GRANJA | D60: Kg | E60: {=+XLOOKUP(B60,'Base de datos'!A:A,'Base de datos'!H:H,0)} -> 3.75 | F60: 1 | H60: =IFERROR(1-G60/F60,"") -> 1 | I60: =IFERROR(E60*F60,"") -> 3.75 | K60: =K56/K58 -> 1.9177315
B61: {=+XLOOKUP(C61,'Base de datos'!C:C,'Base de datos'!A:A,"",FALSE)} | D61: Kg | E61: {=+XLOOKUP(B61,'Base de datos'!A:A,'Base de datos'!H:H,0)} -> 0 | H61: =IFERROR(1-G61/F61,"") | I61: =IFERROR(E61*F61,"") -> 0 | K61: Nº de Raciones según receta
B62: {=+XLOOKUP(C62,'Base de datos'!C:C,'Base de datos'!A:A,"",FALSE)} | D62: Kg | E62: {=+XLOOKUP(B62,'Base de datos'!A:A,'Base de datos'!H:H,0)} -> 0 | H62: =IFERROR(1-G62/F62,"") | I62: =IFERROR(E62*F62,"") -> 0 | K62: =K58/F32 -> 46.5625
B63: {=+XLOOKUP(C63,'Base de datos'!C:C,'Base de datos'!A:A,"",FALSE)} | D63: Kg | E63: {=+XLOOKUP(B63,'Base de datos'!A:A,'Base de datos'!H:H,0)} -> 0 | H63: =IFERROR(1-G63/F63,"") | I63: =IFERROR(E63*F63,"") -> 0
B64: {=+XLOOKUP(C64,'Base de datos'!C:C,'Base de datos'!A:A,"",FALSE)} | D64: Kg | E64: {=+XLOOKUP(B64,'Base de datos'!A:A,'Base de datos'!H:H,0)} -> 0 | H64: =IFERROR(1-G64/F64,"") | I64: =IFERROR(E64*F64,"") -> 0
C66: Notas de elaboración 1
C67: MAYONESA 8kg 150gr ajo 160gr Sal 90gr Vinagre 1LClara 1LHuevo 5,2L aceite girasol
B79: ID | C79: MOJO PICON | D79: Unidad | E79: Precio Unidad | F79: Cantidad Bruta | G79: Cantidad Cocinada/limpia | H79: Merma % | I79: Coste | K79: E.3
B80: {=+XLOOKUP(C80,'Base de datos'!C:C,'Base de datos'!A:A,"",FALSE)} -> 2 | C80: Aceite de girasol Adl | D80: Kg | E80: {=+XLOOKUP(B80,'Base de datos'!A:A,'Base de datos'!H:H,0)} -> 1.518 | F80: 1 | H80: =IFERROR(1-G80/F80,"") -> 1 | I80: =IFERROR(E80*F80,"") -> 1.518 | K80: Coste Total
B81: {=+XLOOKUP(C81,'Base de datos'!C:C,'Base de datos'!A:A,"",FALSE)} -> 119 | C81: SAL | D81: Kg | E81: {=+XLOOKUP(B81,'Base de datos'!A:A,'Base de datos'!H:H,0)} -> 0.43 | F81: 0.01 | H81: =IFERROR(1-G81/F81,"") -> 1 | I81: =IFERROR(E81*F81,"") -> 0.0043 | K81: =SUM(I80:I90) -> 4.3738826
B82: {=+XLOOKUP(C82,'Base de datos'!C:C,'Base de datos'!A:A,"",FALSE)} -> 121 | C82: COMINO | D82: Kg | E82: {=+XLOOKUP(B82,'Base de datos'!A:A,'Base de datos'!H:H,0)} -> 18.875 | F82: 0.03 | H82: =IFERROR(1-G82/F82,"") -> 1 | I82: =IFERROR(E82*F82,"") -> 0.56625 | K82: Cantidad Fabricación
B83: {=+XLOOKUP(C83,'Base de datos'!C:C,'Base de datos'!A:A,"",FALSE)} -> 123 | C83: GUINDILLA | D83: Kg | E83: {=+XLOOKUP(B83,'Base de datos'!A:A,'Base de datos'!H:H,0)} -> 38.1 | F83: 0.001 | H83: =IFERROR(1-G83/F83,"") -> 1 | I83: =IFERROR(E83*F83,"") -> 0.0381 | K83: =SUM(F80:F90) -> 2.448
B84: {=+XLOOKUP(C84,'Base de datos'!C:C,'Base de datos'!A:A,"",FALSE)} -> 124 | C84: PIMIENTO ROJO | D84: Kg | E84: {=+XLOOKUP(B84,'Base de datos'!A:A,'Base de datos'!H:H,0)} -> 1.79 | F84: 0.2 | H84: =IFERROR(1-G84/F84,"") -> 1 | I84: =IFERROR(E84*F84,"") -> 0.358 | K84: Precio Base
B85: {=+XLOOKUP(C85,'Base de datos'!C:C,'Base de datos'!A:A,"",FALSE)} -> 122 | C85: PIMENTON DULCE | D85: Kg | E85: {=+XLOOKUP(B85,'Base de datos'!A:A,'Base de datos'!H:H,0)} -> 7.9625 | F85: 0.015 | H85: =IFERROR(1-G85/F85,"") -> 1 | I85: =IFERROR(E85*F85,"") -> 0.1194375 | K85: =K81/K83 -> 1.7867168
B86: {=+XLOOKUP(C86,'Base de datos'!C:C,'Base de datos'!A:A,"",FALSE)} -> 126 | C86: PIMENTON PICANTE | D86: Kg | E86: {=+XLOOKUP(B86,'Base de datos'!A:A,'Base de datos'!H:H,0)} -> 8.325 | F86: 0.01 | H86: =IFERROR(1-G86/F86,"") -> 1 | I86: =IFERROR(E86*F86,"") -> 0.08325 | K86: Nº de Raciones según receta
B87: {=+XLOOKUP(C87,'Base de datos'!C:C,'Base de datos'!A:A,"",FALSE)} -> 127 | C87: PIMIENTA | D87: Kg | E87: {=+XLOOKUP(B87,'Base de datos'!A:A,'Base de datos'!H:H,0)} -> 17.054545 | F87: 0.002 | H87: =IFERROR(1-G87/F87,"") -> 1 | I87: =IFERROR(E87*F87,"") -> 0.034109091 | K87: =K83/F57 -> 15.3
B88: {=+XLOOKUP(C88,'Base de datos'!C:C,'Base de datos'!A:A,"",FALSE)} -> 100 | C88: VINAGRE | D88: Kg | E88: {=+XLOOKUP(B88,'Base de datos'!A:A,'Base de datos'!H:H,0)} -> 0.83 | F88: 0.18 | H88: =IFERROR(1-G88/F88,"") -> 1 | I88: =IFERROR(E88*F88,"") -> 0.1494
B89: {=+XLOOKUP(C89,'Base de datos'!C:C,'Base de datos'!A:A,"",FALSE)} -> 110 | C89: PAN BAGUETTE LA PARRA | D89: Kg | E89: {=+XLOOKUP(B89,'Base de datos'!A:A,'Base de datos'!H:H,0)} -> 0.28181818 | F89: 0.3 | H89: =IFERROR(1-G89/F89,"") -> 1 | I89: =IFERROR(E89*F89,"") -> 0.084545455
B90: {=+XLOOKUP(C90,'Base de datos'!C:C,'Base de datos'!A:A,"",FALSE)} -> 125 | C90: TOMATE FRITO BOTE | D90: Kg | E90: {=+XLOOKUP(B90,'Base de datos'!A:A,'Base de datos'!H:H,0)} -> 2.0264151 | F90: 0.7 | H90: =IFERROR(1-G90/F90,"") -> 1 | I90: =IFERROR(E90*F90,"") -> 1.4184906
C92: Notas de elaboración 1
C93: Mojo picón
C94: Aceite
C95: 180ml de vinagre
C96: Pimiento Rojo
C97: Especias
C98: Ajos
C99: Pan aguado para reblandecer
C101: Thermomix 8-9
C102: Hasta que quede cremoso .
C103: Opcional añadir para expesor más pan.
C105: Cantidad total 1,5kg
B108: ID | C108: SALSA BICHOTA | D108: Unidad | E108: Precio Unidad | F108: Cantidad Bruta | G108: Cantidad Cocinada/limpia | H108: Merma % | I108: Coste | K108: E.3
B109: {=+XLOOKUP(C109,'Base de datos'!C:C,'Base de datos'!A:A,"",FALSE)} -> 131 | C109: MAYONESA SOFI | D109: Kg | E109: {=+XLOOKUP(B109,'Base de datos'!A:A,'Base de datos'!H:H,0)} -> 1.92 | F109: 0.5 | H109: =IFERROR(1-G109/F109,"") -> 1 | I109: =IFERROR(E109*F109,"") -> 0.96 | K109: Coste Total
B110: {=+XLOOKUP(C110,'Base de datos'!C:C,'Base de datos'!A:A,"",FALSE)} -> 130 | C110: CURRY | D110: Kg | E110: {=+XLOOKUP(B110,'Base de datos'!A:A,'Base de datos'!H:H,0)} -> 8.75 | F110: 0.01 | H110: =IFERROR(1-G110/F110,"") -> 1 | I110: =IFERROR(E110*F110,"") -> 0.0875 | K110: =SUM(I109:I119) -> 3.2326699
B111: {=+XLOOKUP(C111,'Base de datos'!C:C,'Base de datos'!A:A,"",FALSE)} -> 83 | C111: SALSA BBQ BAREA | D111: Kg | E111: {=+XLOOKUP(B111,'Base de datos'!A:A,'Base de datos'!H:H,0)} -> 1.6378378 | F111: 0.2 | H111: =IFERROR(1-G111/F111,"") -> 1 | I111: =IFERROR(E111*F111,"") -> 0.32756757 | K111: Cantidad Fabricación
B112: {=+XLOOKUP(C112,'Base de datos'!C:C,'Base de datos'!A:A,"",FALSE)} -> 88 | C112: SALSA MOSTAZA MIEL | D112: Kg | E112: {=+XLOOKUP(B112,'Base de datos'!A:A,'Base de datos'!H:H,0)} -> 4.6491228 | F112: 0.2 | H112: =IFERROR(1-G112/F112,"") -> 1 | I112: =IFERROR(E112*F112,"") -> 0.92982456 | K112: =SUM(F109:F119) -> 2.217
B113: {=+XLOOKUP(C113,'Base de datos'!C:C,'Base de datos'!A:A,"",FALSE)} -> 137 | C113: MOSTAZA DIJON | D113: Kg | E113: {=+XLOOKUP(B113,'Base de datos'!A:A,'Base de datos'!H:H,0)} -> 9.2777778 | F113: 0.1 | H113: =IFERROR(1-G113/F113,"") -> 1 | I113: =IFERROR(E113*F113,"") -> 0.92777778 | K113: Precio Base
B114: {=+XLOOKUP(C114,'Base de datos'!C:C,'Base de datos'!A:A,"",FALSE)} | D114: Kg | E114: {=+XLOOKUP(B114,'Base de datos'!A:A,'Base de datos'!H:H,0)} -> 0 | F114: 0.015 | H114: =IFERROR(1-G114/F114,"") -> 1 | I114: =IFERROR(E114*F114,"") -> 0 | K114: =K110/K112 -> 1.4581281
B115: {=+XLOOKUP(C115,'Base de datos'!C:C,'Base de datos'!A:A,"",FALSE)} | D115: Kg | E115: {=+XLOOKUP(B115,'Base de datos'!A:A,'Base de datos'!H:H,0)} -> 0 | F115: 0.01 | H115: =IFERROR(1-G115/F115,"") -> 1 | I115: =IFERROR(E115*F115,"") -> 0 | K115: Nº de Raciones según receta
B116: {=+XLOOKUP(C116,'Base de datos'!C:C,'Base de datos'!A:A,"",FALSE)} | D116: Kg | E116: {=+XLOOKUP(B116,'Base de datos'!A:A,'Base de datos'!H:H,0)} -> 0 | F116: 0.002 | H116: =IFERROR(1-G116/F116,"") -> 1 | I116: =IFERROR(E116*F116,"") -> 0 | K116: =K112/F86 -> 221.7
B117: {=+XLOOKUP(C117,'Base de datos'!C:C,'Base de datos'!A:A,"",FALSE)} | D117: Kg | E117: {=+XLOOKUP(B117,'Base de datos'!A:A,'Base de datos'!H:H,0)} -> 0 | F117: 0.18 | H117: =IFERROR(1-G117/F117,"") -> 1 | I117: =IFERROR(E117*F117,"") -> 0
B118: {=+XLOOKUP(C118,'Base de datos'!C:C,'Base de datos'!A:A,"",FALSE)} | D118: Kg | E118: {=+XLOOKUP(B118,'Base de datos'!A:A,'Base de datos'!H:H,0)} -> 0 | F118: 0.3 | H118: =IFERROR(1-G118/F118,"") -> 1 | I118: =IFERROR(E118*F118,"") -> 0
B119: {=+XLOOKUP(C119,'Base de datos'!C:C,'Base de datos'!A:A,"",FALSE)} | D119: Kg | E119: {=+XLOOKUP(B119,'Base de datos'!A:A,'Base de datos'!H:H,0)} -> 0 | F119: 0.7 | H119: =IFERROR(1-G119/F119,"") -> 1 | I119: =IFERROR(E119*F119,"") -> 0
C121: Notas de elaboración 1
B139: ID | C139: SALSA TRUFA | D139: Unidad | E139: Precio Unidad | F139: Cantidad Bruta | G139: Cantidad Cocinada/limpia | H139: Merma % | I139: Coste | K139: E.3
B140: {=+XLOOKUP(C140,'Base de datos'!C:C,'Base de datos'!A:A,"",FALSE)} -> 131 | C140: MAYONESA SOFI | D140: Kg | E140: {=+XLOOKUP(B140,'Base de datos'!A:A,'Base de datos'!H:H,0)} -> 1.92 | F140: 0.5 | H140: =IFERROR(1-G140/F140,"") -> 1 | I140: =IFERROR(E140*F140,"") -> 0.96 | K140: Coste Total
B141: {=+XLOOKUP(C141,'Base de datos'!C:C,'Base de datos'!A:A,"",FALSE)} -> 98 | C141: TRUFA | D141: Kg | E141: {=+XLOOKUP(B141,'Base de datos'!A:A,'Base de datos'!H:H,0)} -> 50 | F141: 0.08 | H141: =IFERROR(1-G141/F141,"") -> 1 | I141: =IFERROR(E141*F141,"") -> 4 | K141: =SUM(I140:I150) -> 4.96
B142: {=+XLOOKUP(C142,'Base de datos'!C:C,'Base de datos'!A:A,"",FALSE)} | D142: Kg | E142: {=+XLOOKUP(B142,'Base de datos'!A:A,'Base de datos'!H:H,0)} -> 0 | F142: 0.2 | H142: =IFERROR(1-G142/F142,"") -> 1 | I142: =IFERROR(E142*F142,"") -> 0 | K142: Cantidad Fabricación
B143: {=+XLOOKUP(C143,'Base de datos'!C:C,'Base de datos'!A:A,"",FALSE)} | D143: Kg | E143: {=+XLOOKUP(B143,'Base de datos'!A:A,'Base de datos'!H:H,0)} -> 0 | F143: 0.2 | H143: =IFERROR(1-G143/F143,"") -> 1 | I143: =IFERROR(E143*F143,"") -> 0 | K143: =SUM(F140:F150) -> 2.287
B144: {=+XLOOKUP(C144,'Base de datos'!C:C,'Base de datos'!A:A,"",FALSE)} | D144: Kg | E144: {=+XLOOKUP(B144,'Base de datos'!A:A,'Base de datos'!H:H,0)} -> 0 | F144: 0.1 | H144: =IFERROR(1-G144/F144,"") -> 1 | I144: =IFERROR(E144*F144,"") -> 0 | K144: Precio Base
B145: {=+XLOOKUP(C145,'Base de datos'!C:C,'Base de datos'!A:A,"",FALSE)} | D145: Kg | E145: {=+XLOOKUP(B145,'Base de datos'!A:A,'Base de datos'!H:H,0)} -> 0 | F145: 0.015 | H145: =IFERROR(1-G145/F145,"") -> 1 | I145: =IFERROR(E145*F145,"") -> 0 | K145: =K141/K143 -> 2.1687801
B146: {=+XLOOKUP(C146,'Base de datos'!C:C,'Base de datos'!A:A,"",FALSE)} | D146: Kg | E146: {=+XLOOKUP(B146,'Base de datos'!A:A,'Base de datos'!H:H,0)} -> 0 | F146: 0.01 | H146: =IFERROR(1-G146/F146,"") -> 1 | I146: =IFERROR(E146*F146,"") -> 0 | K146: Nº de Raciones según receta
B147: {=+XLOOKUP(C147,'Base de datos'!C:C,'Base de datos'!A:A,"",FALSE)} | D147: Kg | E147: {=+XLOOKUP(B147,'Base de datos'!A:A,'Base de datos'!H:H,0)} -> 0 | F147: 0.002 | H147: =IFERROR(1-G147/F147,"") -> 1 | I147: =IFERROR(E147*F147,"") -> 0 | K147: =K143/F117 -> 12.705556
B148: {=+XLOOKUP(C148,'Base de datos'!C:C,'Base de datos'!A:A,"",FALSE)} | D148: Kg | E148: {=+XLOOKUP(B148,'Base de datos'!A:A,'Base de datos'!H:H,0)} -> 0 | F148: 0.18 | H148: =IFERROR(1-G148/F148,"") -> 1 | I148: =IFERROR(E148*F148,"") -> 0
B149: {=+XLOOKUP(C149,'Base de datos'!C:C,'Base de datos'!A:A,"",FALSE)} | D149: Kg | E149: {=+XLOOKUP(B149,'Base de datos'!A:A,'Base de datos'!H:H,0)} -> 0 | F149: 0.3 | H149: =IFERROR(1-G149/F149,"") -> 1 | I149: =IFERROR(E149*F149,"") -> 0
B150: {=+XLOOKUP(C150,'Base de datos'!C:C,'Base de datos'!A:A,"",FALSE)} | D150: Kg | E150: {=+XLOOKUP(B150,'Base de datos'!A:A,'Base de datos'!H:H,0)} -> 0 | F150: 0.7 | H150: =IFERROR(1-G150/F150,"") -> 1 | I150: =IFERROR(E150*F150,"") -> 0
C152: Notas de elaboración 1
B168: ID | C168: SALSA WISKY | D168: Unidad | E168: Precio Unidad | F168: Cantidad Bruta | G168: Cantidad Cocinada/limpia | H168: Merma % | I168: Coste | K168: E.3
B169: {=+XLOOKUP(C169,'Base de datos'!C:C,'Base de datos'!A:A,"",FALSE)} -> 2 | C169: Aceite de girasol Adl | D169: Kg | E169: {=+XLOOKUP(B169,'Base de datos'!A:A,'Base de datos'!H:H,0)} -> 1.518 | F169: 1 | H169: =IFERROR(1-G169/F169,"") -> 1 | I169: =IFERROR(E169*F169,"") -> 1.518 | K169: Coste Total
B170: {=+XLOOKUP(C170,'Base de datos'!C:C,'Base de datos'!A:A,"",FALSE)} -> 118 | C170: AJO | D170: Kg | E170: {=+XLOOKUP(B170,'Base de datos'!A:A,'Base de datos'!H:H,0)} -> 5 | F170: 0.35 | H170: =IFERROR(1-G170/F170,"") -> 1 | I170: =IFERROR(E170*F170,"") -> 1.75 | K170: =SUM(I169:I179) -> 4.753
B171: {=+XLOOKUP(C171,'Base de datos'!C:C,'Base de datos'!A:A,"",FALSE)} -> 140 | C171: CALDO CARNE AVECREM POLVO | D171: Kg | E171: {=+XLOOKUP(B171,'Base de datos'!A:A,'Base de datos'!H:H,0)} -> 7.25 | F171: 0.1 | H171: =IFERROR(1-G171/F171,"") -> 1 | I171: =IFERROR(E171*F171,"") -> 0.725 | K171: Cantidad Fabricación
B172: {=+XLOOKUP(C172,'Base de datos'!C:C,'Base de datos'!A:A,"",FALSE)} -> 141 | C172: VINO BLANCO | D172: Kg | E172: {=+XLOOKUP(B172,'Base de datos'!A:A,'Base de datos'!H:H,0)} -> 0.76 | F172: 1 | H172: =IFERROR(1-G172/F172,"") -> 1 | I172: =IFERROR(E172*F172,"") -> 0.76 | K172: =SUM(F169:F179) -> 3.757
B173: {=+XLOOKUP(C173,'Base de datos'!C:C,'Base de datos'!A:A,"",FALSE)} | D173: Kg | E173: {=+XLOOKUP(B173,'Base de datos'!A:A,'Base de datos'!H:H,0)} -> 0 | F173: 0.1 | H173: =IFERROR(1-G173/F173,"") -> 1 | I173: =IFERROR(E173*F173,"") -> 0 | K173: Precio Base
B174: {=+XLOOKUP(C174,'Base de datos'!C:C,'Base de datos'!A:A,"",FALSE)} | D174: Kg | E174: {=+XLOOKUP(B174,'Base de datos'!A:A,'Base de datos'!H:H,0)} -> 0 | F174: 0.015 | H174: =IFERROR(1-G174/F174,"") -> 1 | I174: =IFERROR(E174*F174,"") -> 0 | K174: =K170/K172 -> 1.2651051
B175: {=+XLOOKUP(C175,'Base de datos'!C:C,'Base de datos'!A:A,"",FALSE)} | D175: Kg | E175: {=+XLOOKUP(B175,'Base de datos'!A:A,'Base de datos'!H:H,0)} -> 0 | F175: 0.01 | H175: =IFERROR(1-G175/F175,"") -> 1 | I175: =IFERROR(E175*F175,"") -> 0 | K175: Nº de Raciones según receta
B176: {=+XLOOKUP(C176,'Base de datos'!C:C,'Base de datos'!A:A,"",FALSE)} | D176: Kg | E176: {=+XLOOKUP(B176,'Base de datos'!A:A,'Base de datos'!H:H,0)} -> 0 | F176: 0.002 | H176: =IFERROR(1-G176/F176,"") -> 1 | I176: =IFERROR(E176*F176,"") -> 0 | K176: =K172/F146 -> 375.7
B177: {=+XLOOKUP(C177,'Base de datos'!C:C,'Base de datos'!A:A,"",FALSE)} | D177: Kg | E177: {=+XLOOKUP(B177,'Base de datos'!A:A,'Base de datos'!H:H,0)} -> 0 | F177: 0.18 | H177: =IFERROR(1-G177/F177,"") -> 1 | I177: =IFERROR(E177*F177,"") -> 0
B178: {=+XLOOKUP(C178,'Base de datos'!C:C,'Base de datos'!A:A,"",FALSE)} | D178: Kg | E178: {=+XLOOKUP(B178,'Base de datos'!A:A,'Base de datos'!H:H,0)} -> 0 | F178: 0.3 | H178: =IFERROR(1-G178/F178,"") -> 1 | I178: =IFERROR(E178*F178,"") -> 0
...

Sheet ELABORACIONES
C2: PRODUCTO | D2: ELABORACIONES PROPIAS
B5: ID | C5: Nombre del Plato | D5: Unidad de medida | E5: Precio Unidad | F5: Cantidad Bruta | G5: Cantidad Cocinada/limpia | H5: Merma % | I5: Coste | K5: INDICE
B6: =K13 -> E.1 | C6: =C13 -> CHICHARRON DE CADIZ | D6: Kg | E6: =K19 -> 4.7633249 | F6: 0.02 | H6: =IFERROR(1-G6/F6,"") -> 1 | I6: =IFERROR(E6*F6,"") -> 0.095266498 | K6: Coste Total | L6: =SUM(I6:I11) -> 0.095266498
C7: MECHADA DE CERDO | F7: 0.04 | K7: PVP | L7: 4
K8: Precio venta (s/IVA) | L8: =L7/1.1 -> 3.6363636
K9: IVA | L9: 0.1
K10: Coste de Producto | L10: =L6/L8*100 -> 2.6198287 | M10: %
K11: Margen Bruto | L11: =100-L10 -> 97.380171 | M11: %
B13: ID | C13: CHICHARRON DE CADIZ | D13: Unidad | E13: Precio Unidad | F13: Cantidad Bruta | G13: Cantidad Cocinada/limpia | H13: Merma % | I13: Coste | K13: E.1
B14: {=+XLOOKUP(C14,'Base de datos'!C:C,'Base de datos'!A:A,"",FALSE)} -> 128 | C14: PAPADA | D14: Kg | E14: {=+XLOOKUP(B14,'Base de datos'!A:A,'Base de datos'!H:H,0)} -> 5 | F14: 10 | G14: 6.5 | H14: =IFERROR(1-G14/F14,"") -> 0.35 | I14: =IFERROR(E14*F14,"") -> 50 | K14: Coste Total
B15: {=+XLOOKUP(C15,'Base de datos'!C:C,'Base de datos'!A:A,"",FALSE)} -> 129 | C15: OREGANO | D15: Kg | E15: {=+XLOOKUP(B15,'Base de datos'!A:A,'Base de datos'!H:H,0)} -> 11.7 | F15: 0.025 | H15: =IFERROR(1-G15/F15,"") -> 1 | I15: =IFERROR(E15*F15,"") -> 0.2925 | K15: =SUM(I14:I23) -> 52.134591
B16: {=+XLOOKUP(C16,'Base de datos'!C:C,'Base de datos'!A:A,"",FALSE)} -> 119 | C16: SAL | D16: Kg | E16: {=+XLOOKUP(B16,'Base de datos'!A:A,'Base de datos'!H:H,0)} -> 0.43 | F16: 0.2 | H16: =IFERROR(1-G16/F16,"") -> 1 | I16: =IFERROR(E16*F16,"") -> 0.086 | K16: Cantidad Fabricación
B17: {=+XLOOKUP(C17,'Base de datos'!C:C,'Base de datos'!A:A,"",FALSE)} -> 127 | C17: PIMIENTA | D17: Kg | E17: {=+XLOOKUP(B17,'Base de datos'!A:A,'Base de datos'!H:H,0)} -> 17.054545 | F17: 0.02 | H17: =IFERROR(1-G17/F17,"") -> 1 | I17: =IFERROR(E17*F17,"") -> 0.34109091 | K17: =SUM(F14:F23) -> 10.945
B18: {=+XLOOKUP(C18,'Base de datos'!C:C,'Base de datos'!A:A,"",FALSE)} -> 118 | C18: AJO | D18: Kg | E18: {=+XLOOKUP(B18,'Base de datos'!A:A,'Base de datos'!H:H,0)} -> 5 | F18: 0.2 | H18: =IFERROR(1-G18/F18,"") -> 1 | I18: =IFERROR(E18*F18,"") -> 1 | K18: Precio Base
B19: {=+XLOOKUP(C19,'Base de datos'!C:C,'Base de datos'!A:A,"",FALSE)} -> 100 | C19: VINAGRE | D19: Kg | E19: {=+XLOOKUP(B19,'Base de datos'!A:A,'Base de datos'!H:H,0)} -> 0.83 | F19: 0.5 | H19: =IFERROR(1-G19/F19,"") -> 1 | I19: =IFERROR(E19*F19,"") -> 0.415 | K19: =K15/K17 -> 4.7633249
B20: {=+XLOOKUP(C20,'Base de datos'!C:C,'Base de datos'!A:A,"",FALSE)} | D20: Kg | E20: {=+XLOOKUP(B20,'Base de datos'!A:A,'Base de datos'!H:H,0)} -> 0 | H20: =IFERROR(1-G20/F20,"") | I20: =IFERROR(E20*F20,"") -> 0 | K20: Nº de Raciones según receta
B21: {=+XLOOKUP(C21,'Base de datos'!C:C,'Base de datos'!A:A,"",FALSE)} | D21: Kg | E21: {=+XLOOKUP(B21,'Base de datos'!A:A,'Base de datos'!H:H,0)} -> 0 | H21: =IFERROR(1-G21/F21,"") | I21: =IFERROR(E21*F21,"") -> 0 | K21: =K17/F6 -> 547.25
B22: {=+XLOOKUP(C22,'Base de datos'!C:C,'Base de datos'!A:A,"",FALSE)} | D22: Kg | E22: {=+XLOOKUP(B22,'Base de datos'!A:A,'Base de datos'!H:H,0)} -> 0 | H22: =IFERROR(1-G22/F22,"") | I22: =IFERROR(E22*F22,"") -> 0
B23: {=+XLOOKUP(C23,'Base de datos'!C:C,'Base de datos'!A:A,"",FALSE)} | D23: Kg | E23: {=+XLOOKUP(B23,'Base de datos'!A:A,'Base de datos'!H:H,0)} -> 0 | H23: =IFERROR(1-G23/F23,"") | I23: =IFERROR(E23*F23,"") -> 0
C25: Notas de elaboración 1
C28: Chicharrón de Cadiz 10kg
C29: Reduce un 35%
C31: 25gr orégano (8,85/kg)
C32: 200gr sal
C33: 20gr pimienta negra
C34: 200gr ajo
C35: 500ml litro vinagre
C36: 1 y 500ml de agua
C37: Moler
C39: Macerar 24h
C41: Hornear 200gr unos 40min sin precalentar horno
B44: ID | C44: POSTRE LOTUS | D44: Unidad | E44: Precio Unidad | F44: Cantidad Bruta | G44: Cantidad Cocinada/limpia | H44: Merma % | I44: Coste | K44: E.1
B45: {=+XLOOKUP(C45,'Base de datos'!C:C,'Base de datos'!A:A,"",FALSE)} | K45: Coste Total
B46: {=+XLOOKUP(C46,'Base de datos'!C:C,'Base de datos'!A:A,"",FALSE)} | K46: =SUM(I45:I54) -> 0
B47: {=+XLOOKUP(C47,'Base de datos'!C:C,'Base de datos'!A:A,"",FALSE)} | K47: Cantidad Fabricación
B48: {=+XLOOKUP(C48,'Base de datos'!C:C,'Base de datos'!A:A,"",FALSE)} | K48: =SUM(F45:F54) -> 0
B49: {=+XLOOKUP(C49,'Base de datos'!C:C,'Base de datos'!A:A,"",FALSE)} | K49: Precio Base
B50: {=+XLOOKUP(C50,'Base de datos'!C:C,'Base de datos'!A:A,"",FALSE)} | K50: =K46/K48 -> #DIV/0!
B51: {=+XLOOKUP(C51,'Base de datos'!C:C,'Base de datos'!A:A,"",FALSE)} | K51: Nº de Raciones según receta
B52: {=+XLOOKUP(C52,'Base de datos'!C:C,'Base de datos'!A:A,"",FALSE)} | D52: Kg | E52: {=+XLOOKUP(B52,'Base de datos'!A:A,'Base de datos'!H:H,0)} -> 0 | H52: =IFERROR(1-G52/F52,"") | I52: =IFERROR(E52*F52,"") -> 0 | K52: =K48/F21 -> #DIV/0!
B53: {=+XLOOKUP(C53,'Base de datos'!C:C,'Base de datos'!A:A,"",FALSE)} | D53: Kg | E53: {=+XLOOKUP(B53,'Base de datos'!A:A,'Base de datos'!H:H,0)} -> 0 | H53: =IFERROR(1-G53/F53,"") | I53: =IFERROR(E53*F53,"") -> 0
B54: {=+XLOOKUP(C54,'Base de datos'!C:C,'Base de datos'!A:A,"",FALSE)} | D54: Kg | E54: {=+XLOOKUP(B54,'Base de datos'!A:A,'Base de datos'!H:H,0)} -> 0 | H54: =IFERROR(1-G54/F54,"") | I54: =IFERROR(E54*F54,"") -> 0
C56: Notas de elaboración 1
B75: ID | C75: MECHADA | D75: Unidad | E75: Precio Unidad | F75: Cantidad Bruta | G75: Cantidad Cocinada/limpia | H75: Merma % | I75: Coste | K75: E.1
B76: {=+XLOOKUP(C76,'Base de datos'!C:C,'Base de datos'!A:A,"",FALSE)} -> 158 | C76: CABEZA DE CERDO | D76: Kg | E76: {=+XLOOKUP(B76,'Base de datos'!A:A,'Base de datos'!H:H,0)} -> 4 | F76: 2 | G76: 1.4 | H76: =IFERROR(1-G76/F76,"") -> 0.3 | I76: =IFERROR(E76*F76,"") -> 8 | K76: Coste Total
B77: {=+XLOOKUP(C77,'Base de datos'!C:C,'Base de datos'!A:A,"",FALSE)} -> 100 | C77: VINAGRE | D77: Kg | E77: {=+XLOOKUP(B77,'Base de datos'!A:A,'Base de datos'!H:H,0)} -> 0.83 | F77: 0.2 | H77: =IFERROR(1-G77/F77,"") -> 1 | I77: =IFERROR(E77*F77,"") -> 0.166 | K77: =SUM(I76:I85) -> 9.4408455
B78: {=+XLOOKUP(C78,'Base de datos'!C:C,'Base de datos'!A:A,"",FALSE)} -> 119 | C78: SAL | D78: Kg | E78: {=+XLOOKUP(B78,'Base de datos'!A:A,'Base de datos'!H:H,0)} -> 0.43 | F78: 0.01 | H78: =IFERROR(1-G78/F78,"") -> 1 | I78: =IFERROR(E78*F78,"") -> 0.0043 | K78: Cantidad Fabricación
B79: {=+XLOOKUP(C79,'Base de datos'!C:C,'Base de datos'!A:A,"",FALSE)} -> 159 | C79: TOMILLO | D79: Kg | E79: {=+XLOOKUP(B79,'Base de datos'!A:A,'Base de datos'!H:H,0)} -> 10 | F79: 0.01 | H79: =IFERROR(1-G79/F79,"") -> 1 | I79: =IFERROR(E79*F79,"") -> 0.1 | K79: =SUM(F76:F85) -> 2.43
B80: {=+XLOOKUP(C80,'Base de datos'!C:C,'Base de datos'!A:A,"",FALSE)} -> 118 | C80: AJO | D80: Kg | E80: {=+XLOOKUP(B80,'Base de datos'!A:A,'Base de datos'!H:H,0)} -> 5 | F80: 0.2 | H80: =IFERROR(1-G80/F80,"") -> 1 | I80: =IFERROR(E80*F80,"") -> 1 | K80: Precio Base
B81: {=+XLOOKUP(C81,'Base de datos'!C:C,'Base de datos'!A:A,"",FALSE)} -> 127 | C81: PIMIENTA | D81: Kg | E81: {=+XLOOKUP(B81,'Base de datos'!A:A,'Base de datos'!H:H,0)} -> 17.054545 | F81: 0.01 | H81: =IFERROR(1-G81/F81,"") -> 1 | I81: =IFERROR(E81*F81,"") -> 0.17054545 | K81: =K77/K79 -> 3.8851216
B82: {=+XLOOKUP(C82,'Base de datos'!C:C,'Base de datos'!A:A,"",FALSE)} | D82: Kg | E82: {=+XLOOKUP(B82,'Base de datos'!A:A,'Base de datos'!H:H,0)} -> 0 | H82: =IFERROR(1-G82/F82,"") | I82: =IFERROR(E82*F82,"") -> 0 | K82: Nº de Raciones según receta
B83: {=+XLOOKUP(C83,'Base de datos'!C:C,'Base de datos'!A:A,"",FALSE)} | D83: Kg | E83: {=+XLOOKUP(B83,'Base de datos'!A:A,'Base de datos'!H:H,0)} -> 0 | H83: =IFERROR(1-G83/F83,"") | I83: =IFERROR(E83*F83,"") -> 0 | K83: =K79/F7 -> 60.75
B84: {=+XLOOKUP(C84,'Base de datos'!C:C,'Base de datos'!A:A,"",FALSE)} | D84: Kg | E84: {=+XLOOKUP(B84,'Base de datos'!A:A,'Base de datos'!H:H,0)} -> 0 | H84: =IFERROR(1-G84/F84,"") | I84: =IFERROR(E84*F84,"") -> 0
B85: {=+XLOOKUP(C85,'Base de datos'!C:C,'Base de datos'!A:A,"",FALSE)} | D85: Kg | E85: {=+XLOOKUP(B85,'Base de datos'!A:A,'Base de datos'!H:H,0)} -> 0 | H85: =IFERROR(1-G85/F85,"") | I85: =IFERROR(E85*F85,"") -> 0
C87: Notas de elaboración 1
C90: SE MARINA TODO
C91: HORNO 170 GRADOS , UNA HORA Y MEDIA

Sheet INDICE 25
B5: BURGER | C5: PVP | D5: COSTE | E5: %MARGEN | F5: OPCION | J5: Categoría | K5: Producto | L5: Unidades
B6: CRUJIPOLLO BBQ | C6: 8 | D6: 1.77 | E6: 75.71 | F6: Puzzle | J6: Bebidas | K6: CocaCola | L6: 136
B7: CRUJIPOLLO ORIGINAL | C7: 7 | D7: 1.55 | E7: 75.66 | F7: Puzzle | J7: Bebidas | K7: Fuzetea | L7: 23
B8: MAKA | C8: 9.9 | D8: 2.48 | E8: 72.436027 | F8: Estrella | J8: Bebidas | K8: Agua Botella | L8: 20
B9: BICHOTA | C9: 10 | D9: 2.5 | E9: 72.265198 | F9: Puzzle | J9: Bebidas | K9: Aquarius | L9: 13
B10: DADDY | C10: 9.9 | D10: 2.94 | E10: 70.644243 | J10: Bebidas | K10: Fanta | L10: 13
B11: DOBLE QUESOS | C11: 8 | D11: 2.54 | E11: 65.100104 | F11: Vaca | J11: Bebidas | K11: Cerveza Cruzcampo 0,0% | L11: 1
B12: CERO15 | C12: 8 | D12: 2.55 | E12: 64.946792 | F12: Vaca | J12: Bebidas | K12: SevenUp | L12: 1
B13: KAROL | C13: 8 | D13: 2.6 | E13: 64.188242 | J13: BEBIDAS. | K13: COCACOLA ORIGINAL 33cl | L13: 10
B14: BARRIERA | C14: 7 | D14: 2.67 | E14: 58.052223 | F14: Vaca | J14: BEBIDAS. | K14: COCACOLA ZERO 33cl | L14: 7
J15: BEBIDAS. | K15: FANTA LIMON 33CL | L15: 6
J16: BEBIDAS. | K16: COCACOLA ZERO ZERO 33cl | L16: 2
J17: BEBIDAS. | K17: FUZETEA MARACUYA 33cl | L17: 2
B18: BAGUETTES | C18: Column 5 | D18: COSTE | E18: %MARGEN | F18: Columna 1 | J18: BEBIDAS. | K18: AQUARIOUS LIMON 33CL | L18: 1
B19: BARBARA | D19: 1.34 | E19: 62.26 | F19: Vaca | J19: BEBIDAS. | K19: FUZETEA LIMON 33cl | L19: 1
B20: CRISTIAN | D20: 1.53 | E20: 75.974143 | F20: Estrella | J20: Bocatas | K20: Joaquinto | L20: 68
B21: GUARRITO | D21: 1.52 | E21: 76.18 | F21: Puzzle | J21: Bocatas | K21: Guarrito | L21: 61
B22: JAKINIÑO | D22: 1.82 | E22: 74.918375 | F22: Estrella | J22: BOCATAS SIMPLES | K22: SIMPLE DE POLLO | L22: 30
B23: SERRANO EMPANADO | D23: 1.57 | E23: =SERRANOS!L39 -> 73.488 | F23: Estrella | J23: BOCATAS SIMPLES | K23: SIMPLE DE ASADO | L23: 11
B24: SERRANO EMPANADO + 3 Q | J24: Bocatas | K24: Barbara | L24: 59
B25: SERRANO POLLO | D25: 1.63 | E25: =SERRANOS!L11 -> 70.1695 | F25: Vaca | J25: Bocatas | K25: Cristian | L25: 59
B26: SERRANO POLLO + 3 Q | J26: Serranitos | K26: Serranito Pollo Asado | L26: 58
B27: SERRANO POLLO ASADO | D27: 1.57 | E27: =SERRANOS!L68 -> 73.498414 | F27: Estrella | J27: Burgers & MENU | K27: Menú Dobles Quesos +PATATAS + bebida + tarro | L27: 56
B28: SERRANO POLLO ASADO + 3 Q | J28: BOCATAS SIMPLES | K28: SIMPLE EMPANADO | L28: 11
B29: SERRANO SOLOMILLO | D29: 1.5 | E29: 76.43 | F29: Puzzle | J29: BOCATAS SIMPLES | K29: SIMPLE SOLOMILLO | L29: 10
B30: SERRANO SOLOMILLO + 3 Q | J30: Bocatas Vegetales | K30: Vegetal Pollo | L30: 54
B31: SIMPLE ASADO | D31: 1.4 | E31: 61.44 | F31: Perro | J31: Bocatas Vegetales | K31: Vegetal Atún | L31: 29
B32: SIMPLE EMPANADO | D32: 1.34 | E32: =BOCATAS!L25 -> 70.491 | F32: Perro | J32: Bocatas Vegetales | K32: Vegetal Pollo Asado | L32: 21
B33: SIMPLE POLLO | D33: 1.4 | E33: =BOCATAS!L11 -> 61.45 | F33: Perro | J33: Bocatas Vegetales | K33: Vegetal Empanado | L33: 6
B34: SIMPLE SOLOMILO | D34: 1.27 | E34: =BOCATAS!L53 -> 71.965 | F34: Perro | J34: Box | K34: Box Patatas
B35: VEGETAL ATUN | D35: 1.33 | E35: 70.7682 | F35: Perro | J35: Box | K35: Box Lagrimitas | L35: 30
B36: VEGETAL EMPANADO | D36: 1.31 | E36: 72.42 | F36: Puzzle | J36: Box | K36: Box Alitas | L36: 26
B37: VEGETAL POLLO | D37: 1.37 | E37: 69.89 | F37: Vaca | J37: Box | K37: Box Nuggets | L37: 25
B38: VEGETAL POLLO ASADO | D38: 1.37 | E38: 76.83 | F38: Estrella | J38: Box | K38: Box Papas Pulled Pork | L38: 22
J39: Box | K39: BOX Tekillos | L39: 13
J40: Brioches | K40: Smash Serrano Burger | L40: 26
J41: Brioches | K41: Sofi chicken fried | L41: 26
J42: Brioches | K42: Perrito | L42: 17
J43: Brioches | K43: Gipsy | L43: 14
B44: BRIOCHES | C44: Column 5 | D44: COSTE | E44: %MARGEN | F44: Columna 1 | J44: Brioches | K44: Perrito/Hotdog + Bacon + Queso | L44: 10
B45: NAVIDAD | D45: 2.13 | E45: 76.363798 | J45: Brioches | K45: Perrito/Hotdog + Bacon.Queso.Cebolla | L45: 3
B46: GYPSY | D46: 1.97 | E46: 72.919713 | F46: Estrella | J46: Burgers | K46: Bichota Campeona 2023 Sevilla League | L46: 142
B47: CHICKEN FRIED | D47: 2.01 | E47: 72.66816 | F47: Estrella | J47: Burgers | K47: Doblesquesos | L47: 135
B48: CHEESE STEAK | E48: 72.29 | J48: Burgers | K48: Cero15 | L48: 98
B49: SMASH SERRANO | D49: 2.58 | E49: 64.59 | F49: Vaca | J49: Burgers | K49: Sofi | L49: 88
J50: Burgers | K50: Barriera Cheese burger PM | L50: 86
J51: Burgers | K51: Maka | L51: 65
B52: ENTRANTES | C52: Column 5 | D52: COSTE | E52: % MARGEN | F52: Columna 2 | J52: Burgers | K52: Crujipollo BBQ | L52: 21
B53: BOX PATATAS | D53: 0.7 | E53: 84.564065 | F53: Estrella | J53: Burgers | K53: Crujipollo Original | L53: 20
B54: BOX PAPAS PULLED PORK | D54: 0.98 | E54: 84.563902 | F54: Estrella | J54: Burgers | K54: Black Limited Edition | L54: 19
B55: BOX LAGRIMITAS | D55: 1.56 | E55: 71.420044 | F55: Estrella | J55: Burgers & MENU | K55: BICHOTA + LATA + PATATAS( CAMPEONA 2023 BURGER SEVILLA🏆) | L55: 74
B56: BOX NUGGETS | D56: 1.83 | E56: 66.404044 | F56: Perro | J56: Burgers & MENU | K56: MENU DOBLE BARRIERA CHEESE-BACON + PATATAS + LATA | L56: 71
B57: BOX ALITAS | D57: 2.42 | E57: 55.55621 | F57: Perro | J57: Burgers & MENU | K57: Menú Cero15 + PATATAS + bebida + tarro | L57: 52
B58: BOX TEKILLOS | D58: 2.81 | E58: 48.43921 | F58: Vaca | J58: Burgers & MENU | K58: Nueva BURGER + BLACK EDICIÓN LIMITADA patatas incluidas | L58: 50 | N58: =L50+L56 -> 157
J59: Burgers & MENU | K59: Dobles Quesos | L59: 47
J60: Burgers & MENU | K60: Cero15 | L60: 43
B61: PRUEBA PATATAS | C61: Column 5 | D61: COSTE | E61: % MARGEN | F61: Columna 2 | J61: Burgers & MENU | K61: CAMPEONA SEVILLA BURGER LEAGUE “LA BICHOTA” | L61: 41
B62: CARTUCHO PATATAS EXTRA | E62: 81.122598 | J62: Burgers & MENU | K62: CRUJIPOLLO ORIGINAL | L62: 19
J63: Burgers & MENU | K63: MAKA | L63: 17
J64: Burgers & MENU | K64: Menú CRUJIPOLLO BBQ NUEVA RECETA | L64: 16
J65: Burgers & MENU | K65: Menú CRUJI ORIGINAL + bebida | L65: 11
J66: Burgers & MENU | K66: CRUJIPOLLO BBQ NUEVA RECETA | L66: 8
J67: Las Box | K67: TEKILLOS + SALSA | L67: 63
B68: POSTRES | C68: Column 5 | D68: COSTE | E68: % MARGEN | F68: Columna 2 | J68: Las Box | K68: Lagrimitas | L68: 47
B69: TARTA LOTUS | J69: Las Box | K69: Patatas | L69: 40
B70: TARTA QUESO | J70: Las Box | K70: Patatas + PULLED PORK | L70: 31
J71: Las Box | K71: Alitas | L71: 17
J72: Las Box | K72: Nuggets | L72: 17
B73: TARROS SALSAS | C73: Column 5 | D73: COSTE | E73: % MARGEN | F73: % MARGEN.2 | J73: Las Box | K73: Patatas Bravas | L73: 6
B74: TARRO SALSA BICHOTA | D74: 0.13 | E74: 88.392371 | J74: NUEVOS BRIOCHS!! | K74: NUEVO ! Sofi Chicken Fried | L74: 39
B75: TARRO MAYO TRUFA | D75: 0.16 | E75: 85.230964 | J75: NUEVOS BRIOCHS!! | K75: Gipsy Smash | L75: 19
B76: TARRO WISKY | D76: 0.1 | E76: 77.030843 | F76: 84.687229 | J76: NUEVOS BRIOCHS!! | K76: Menú SMASH BURGER SERRANITO + Bebida Incl. | L76: 15
B77: TARRO SALSA AMERICANA | D77: 0.26 | E77: 71.1085 | J77: NUEVOS BRIOCHS!! | K77: Hot Dog Chill BBQ | L77: 8
B78: TARRO RANCHERA | D78: 0.32 | E78: 71.065417 | J78: NUEVOS BRIOCHS!! | K78: SMASH BURGER SERRANITO | L78: 3
B79: TARRO MAYO SRIRACHA | D79: 0.58 | E79: 68.240175 | J79: Postres | K79: Tarta de Lotus Cream (200 g) | L79: 26
B80: TARRO KETCHUP | D80: 0.15 | E80: 66.984838 | F80: 77.989892 | J80: Salsas | K80: Tarro Alioli OFERTA | L80: 345
B81: TARRO MOJO PICON | D81: 0.18 | E81: 60.025813 | F81: 73.350542 | J81: Salsas | K81: Tarro Bichota | L81: 9
B82: TARRO BARBACOA | D82: 0.18 | E82: 59.314568 | J82: Salsas | K82: Tarro Cheddar | L82: 8
B83: TARRO MAYONESA | D83: 0.19 | E83: 58.226858 | F83: 72.151238 | J83: Serranitos | K83: Serranito Pollo | L83: 227
B84: TARRO ALIOLI | D84: 0.19 | E84: 57.787124 | F84: 71.858082 | J84: Serranitos | K84: Serranito Solomillo | L84: 60
J85: Serranitos | K85: Serranito Pollo Empanado | L85: 39
J86: SERRANITOS & BAGUETTES by SOFI | K86: Menú Serranito + bebida + tarro | L86: 100 | N86: =L91+L32 -> 47
J87: SERRANITOS & BAGUETTES by SOFI | K87: Menú Jakiniño + bebida + tarro | L87: 97
J88: SERRANITOS & BAGUETTES by SOFI | K88: SERRANITO de POLLO | L88: 72
J89: SERRANITOS & BAGUETTES by SOFI | K89: Menú Serranito EMPANADO + bebida + tarro | L89: 45
J90: SERRANITOS & BAGUETTES by SOFI | K90: Menú Serranito POLLO ASADO + bebida + tarro | L90: 45
J91: SERRANITOS & BAGUETTES by SOFI | K91: VEGETAL de POLLO ASAO | L91: 26
J92: SERRANITOS & BAGUETTES by SOFI | K92: MENÚ VEGETAL + BEBIDA + TARRO | L92: 10
J93: SERRANITOS & BAGUETTES by SOFI | K93: Menú SMASH BURGER SERRANITO + Bebida Incl. | L93: 7
J94: SERRANITOS & BAGUETTES by SOFI | K94: SMASH BURGER SERRANITO | L94: 4
J95: TARRO EXTRA | K95: TARRO ALIOLI EXTRA | L95: 12
J96: TARRO EXTRA | K96: Tarro Mojo Picon | L96: 8
J97: TARRO EXTRA | K97: Tarro American Burger | L97: 6
J98: TARRO EXTRA | K98: TARRO MAYONESA EXTRA | L98: 3
... J105: TARRO OFERTA | K105: Tarro Barbacoa OFERTA | L105: 4

Sheet CONTEO PRODUCTOS VENDIDOS.
A1: Categoría | B1: Producto | C1: Unidades | D1: Total (€)
A2: BEBIDAS. | B2: AGUA BEZOYA 50cl | C2: 8 | D2: 9.6 | E2: =C98 -> 163 | F2: SIMPLE DE POLLO
A3: Bebidas | B3: Agua Botella | C3: 112 | D3: 168 | E3: =C97 -> 33 | F3: SIMPLE ASADO | G3: 33
A4: BEBIDAS. | B4: AQUARIOUS LIMON 33CL | C4: 1 | D4: 1.6 | E4: =C99 -> 31 | F4: SIMPLE EMPANADO | G4: 31
A5: Bebidas | B5: Aquarius | C5: 29 | D5: 46.4 | E5: =C100 -> 19 | F5: SIMPLE SOLOMILO | G5: 19
A6: BEBIDAS. | B6: AQUIARIOUS NARANJA 33CL | C6: 4 | D6: 6.4 | E6: =C138+C63 -> 218 | F6: VEGETAL POLLO | G6: 218
A7: Bocatas | B7: Barbara | C7: 249 | D7: 1252.5 | E7: =C63+C139+C136+C135 -> 173 | F7: VEGETAL POLLO ASADO | G7: 173
A8: Burgers & MENU | B8: BARRIERA CHEESE BURGER + PATATAS | C8: 63 | D8: 630.7 | E8: =C137 -> 25 | F8: VEGETAL EMPANADO | G8: 25
A9: Burgers | B9: Barriera Cheese burger PM | C9: 301 | D9: 2307.9 | E9: =C134 -> 35 | F9: VEGETAL ATUN | G9: 35
A10: Burgers & MENU | B10: BICHOTA + LATA + PATATAS( CAMPEONA 2023 BURGER SEVILLA🏆) | C10: 52 | D10: 639.6 | E10: =C7 -> 249 | F10: BARBARA | G10: 249
A11: Burgers | B11: Bichota Campeona 2023 Sevilla League | C11: 480 | D11: 4848 | E11: =C36 -> 188 | F11: CRISTIAN | G11: 188
A12: Burgers | B12: Black Limited Edition | C12: 2 | D12: 20.8 | E12: =C68+C54+C55 -> 374 | F12: JAKINIÑO | G12: 374
A13: Box | B13: Box Alitas | C13: 63 | D13: 380.6 | E13: =C51 -> 197 | F13: GUARRITO | G13: 197
A14: ENTRANTES | B14: Box Alitas | C14: 22 | D14: 132.5
A15: Box | B15: Box Lagrimitas | C15: 70 | D15: 421.4 | E15: =C70+C89+C93 -> 183 | F15: SERRANO EMPANADO | G15: 183
A16: ENTRANTES | B16: Box Lagrimitas | C16: 43 | D16: 259.9 | E16: =C90+C88+C87+C69 -> 1105 | F16: SERRANO POLLO | G16: 1105
A17: Box | B17: Box Nuggets | C17: 76 | D17: 456.7 | E17: =C71+C92+C91 -> 357 | F17: SERRANO POLLO ASADO | G17: 357
A18: ENTRANTES | B18: Box Nuggets | C18: 22 | D18: 132 | E18: =C95+C94 -> 270 | F18: SERRANO SOLOMILLO | G18: 270
A19: Box | B19: Box Papas Pulled Pork | C19: 52 | D19: 364 | F19: SERRANO PULLED PORK
A20: ENTRANTES | B20: Box Papas Pulled Pork | C20: 39 | D20: 273
A21: Box | B21: Box Patatas | C21: 88 | D21: 445.6 | F21: XMAS CHIKEN
A22: ENTRANTES | B22: Box Patatas | C22: 76 | D22: 386.3 | E22: =C75 -> 15 | F22: CESAR BRIOCHE | G22: 15
A23: Box | B23: BOX Tekillos | C23: 24 | D23: 147.5 | E23: =C49+C50 -> 71 | F23: GYPSY | G23: 71
A24: Burgers & MENU | B24: CAMPEONA SEVILLA BURGER LEAGUE “LA BICHOTA” | C24: 176 | D24: 2174.7 | E24: =C105+C106+C74 -> 210 | F24: CHICKEN FRIED | G24: 210
A25: Burgers | B25: Cero15 | C25: 366 | D25: 2998.5 | F25: CHEESE STEAK
A26: Burgers & MENU | B26: CERO15 | C26: 108 | D26: 1284.2 | E26: =C103++C102+C73+C72 -> 144 | F26: SMASH SERRANO | G26: 144
A27: Burgers & MENU | B27: Cero15 | C27: 29 | D27: 289.1
A28: Bebidas | B28: Cerveza Cruzcampo 0,0% | C28: 2 | D28: 3
A29: Brioches | B29: CESAR FRIED | C29: 8 | D29: 68 | E29: =C37+C38+C64 -> 131 | F29: CRUJIPOLLO BBQ | G29: 131
A30: Bebidas | B30: CocaCola | C30: 439 | D30: 670.5 | E30: =C39+C40+C62 -> 98 | F30: CRUJIPOLLO ORIGINAL | G30: 98
A31: BEBIDAS. | B31: COCACOLA ORIGINAL 33cl | C31: 55 | D31: 82.5 | E31: =C59+C60 -> 210 | F31: MAKA | G31: 210
A32: BEBIDAS. | B32: COCACOLA ZERO 33cl | C32: 56 | D32: 84 | E32: =C10+C11 -> 532 | F32: BICHOTA | G32: 532
A33: BEBIDAS. | B33: COCACOLA ZERO ZERO 33cl | C33: 19 | D33: 28.5 | F33: DADDY
A34: Burgers | B34: CREA TU CRUJI | C34: 8 | D34: 62 | E34: =C41+C42+C67 -> 781 | F34: DOBLE QUESOS | G34: 781
A35: Burgers | B35: CREATU BURGER | C35: 5 | D35: 55.4 | E35: =C25+C26+C27+C61 -> 525 | F35: CERO15 | G35: 525
A36: Bocatas | B36: Cristian | C36: 188 | D36: 1321 | F36: KAROL
A37: Burgers | B37: Crujipollo BBQ | C37: 95 | D37: 760 | E37: =C8+C9+C65+C66 -> 383 | F37: BARRIERA | G37: 383
A38: Burgers & MENU | B38: CRUJIPOLLO BBQ NUEVA RECETA | C38: 24 | D38: 242.7
A39: Burgers | B39: Crujipollo Original | C39: 58 | D39: 413.5
A40: Burgers & MENU | B40: CRUJIPOLLO ORIGINAL | C40: 35 | D40: 322.8 | E40: =C13+C14 -> 85 | F40: BOX ALITAS | G40: 85
A41: Burgers & MENU | B41: Dobles Quesos | C41: 228 | D41: 2678.7 | E41: =C15+C16 -> 113 | F41: BOX LAGRIMITAS | G41: 113
A42: Burgers | B42: Doblesquesos | C42: 510 | D42: 4253.5 | E42: =C17+C18 -> 98 | F42: BOX NUGGETS | G42: 98
A43: Bebidas | B43: Fanta | C43: 66 | D43: 99 | E43: =C21+C22 -> 164 | F43: BOX PATATAS | G43: 164
A44: BEBIDAS. | B44: FANTA LIMON 33CL | C44: 12 | D44: 18 | E44: =C20+C19 -> 91 | F44: BOX PAPAS PULLED PORK | G44: 91
A45: BEBIDAS. | B45: FANTA NARANJA 33CL | C45: 16 | D45: 24 | E45: =C85+C86 -> 60 | F45: PETACA PATATA | G45: 60
A46: Bebidas | B46: Fuzetea | C46: 55 | D46: 88 | F46: NEW PATATAS CHEESE BACON
A47: BEBIDAS. | B47: FUZETEA LIMON 33cl | C47: 10 | D47: 18
A48: BEBIDAS. | B48: FUZETEA MARACUYA 33cl | C48: 12 | D48: 21.6
A49: Brioches | B49: Gipsy | C49: 34 | D49: 341.6 | E49: =C132+C129 -> 44 | F49: TARTA LOTUS | G49: 44
A50: NUEVOS BRIOCHS!! | B50: Gipsy Smash | C50: 37 | D50: 366.3 | E50: =C130+C131 -> 13 | F50: TARTA QUESO | G50: 13
A51: Bocatas | B51: Guarrito | C51: 197 | D51: 1387.7 | F51: TARTA DUBAI
A52: NUEVOS BRIOCHS!! | B52: Hot Dog Chill BBQ | C52: 5 | D52: 35
A53: NUEVOS BRIOCHS!! | B53: HOT DOG SWEET BBQ | C53: 9 | D53: 74.6
A54: SERRANITOS & BAGUETTES by SOFI | B54: Jakiniño + patatas | C54: 107 | D54: 995.9 | E54: =C53+C52+C82+C83+C84 -> 136 | F54: HOTDOG | G54: 136
A55: Bocatas | B55: Joaquinto | C55: 230 | D55: 1845
A56: Bebidas | B56: Kas | C56: 1 | D56: 2.3
A57: Las Box | B57: Lagrimitas | C57: 36 | D57: 236.5
A58: ENTRANTES Y COMPLEMENTOS | B58: Lagrimitas | C58: 24 | D58: 157.5
A59: Burgers | B59: Maka | C59: 145 | D59: 1445.5
A60: Burgers & MENU | B60: MAKA | C60: 65 | D60: 845
A61: Burgers & MENU | B61: Menú Cero15 + PATATAS + bebida + tarro | C61: 22 | D61: 271.4
A62: Burgers & MENU | B62: Menú CRUJI ORIGINAL + bebida | C62: 5 | D62: 46
A63: SERRANITOS & BAGUETTES by SOFI | B63: MENÚ VEGETAL + BEBIDA + TARRO | C63: 9 | D63: 76
A64: Burgers & MENU | B64: Menú CRUJIPOLLO BBQ NUEVA RECETA | C64: 12 | D64: 108
A65: Burgers & MENU | B65: MENU DOBLE BARRIERA CHEESE-BACON + PATATAS | C65: 2 | D65: 19.8
A66: Burgers & MENU | B66: MENU DOBLE BARRIERA CHEESE-BACON + PATATAS + LATA | C66: 17 | D66: 169.8
... A141: 🎁EDICIÓN LIMITADA | B141: XMAS CHICKEN CRUNCH SUB — LIMITED XMAS DROP | C141: 4 | D141: 39.6

Sheet ENTRANTES
C2: PRODUCTO | D2: BOX NUGGETS
B5: ID | C5: Nombre del Plato | D5: Unidad de medida | E5: Precio Unidad | F5: Cantidad Bruta | G5: Cantidad Cocinada/limpia | H5: Merma % | I5: Coste | K5: INDICE
B6: {=+XLOOKUP(C6,'Base de datos'!C:C,'Base de datos'!A:A,"",FALSE)} | D6: Kg | E6: {=+XLOOKUP(B6,'Base de datos'!A:A,'Base de datos'!H:H,0)} -> 0 | H6: =IFERROR(1-G6/F6,"") | I6: =IFERROR(E6*F6,"") -> 0 | K6: Coste Total | L6: =SUM(I6:I17) -> 1.8325067
B7: =K29 | C7: =C29 | D7: Kg | E7: =K35 -> PVP | H7: =IFERROR(1-G7/F7,"") | I7: =IFERROR(E7*F7,"") | K7: PVP | L7: 6
B8: {=+XLOOKUP(C8,'Base de datos'!C:C,'Base de datos'!A:A,"",FALSE)} -> 42 | C8: NUGGETS POLLO PRIELA | D8: Kg | E8: {=+XLOOKUP(B8,'Base de datos'!A:A,'Base de datos'!H:H,0)} -> 7.2 | F8: 0.178 | H8: =IFERROR(1-G8/F8,"") -> 1 | I8: =IFERROR(E8*F8,"") -> 1.2816 | K8: Precio venta (s/IVA) | L8: =L7/1.1 -> 5.4545455
B9: {=+XLOOKUP(C9,'Base de datos'!C:C,'Base de datos'!A:A,"",FALSE)} -> 132 | C9: ALIOLI SOFI | D9: Kg | E9: {=+XLOOKUP(B9,'Base de datos'!A:A,'Base de datos'!H:H,0)} -> 3.0145342 | F9: 0.05 | H9: =IFERROR(1-G9/F9,"") -> 1 | I9: =IFERROR(E9*F9,"") -> 0.15072671 | K9: IVA | L9: 0.1
K10: Coste de Producto | L10: =L6/L8*100 -> 33.595956 | M10: %
K11: Margen Bruto | L11: =100-L10 -> 66.404044 | M11: %
K13: INDICE UBER
K14: Coste Total | L14: =L6 -> 1.8325067
B15: {=+XLOOKUP(C15,'Base de datos'!C:C,'Base de datos'!A:A,"",FALSE)} -> 93 | C15: SERVILLETA 40X40 100UD | D15: Unidad | E15: {=+XLOOKUP(B15,'Base de datos'!A:A,'Base de datos'!H:H,0)} -> 0.0277 | F15: 1 | G15: 1 | H15: =IFERROR(1-G15/F15,"") -> 0 | I15: =IFERROR(E15*F15,"") -> 0.0277 | K15: PVP | L15: 7.8
B16: {=+XLOOKUP(C16,'Base de datos'!C:C,'Base de datos'!A:A,"",FALSE)} -> 9 | C16: CAJA BOX 780 | D16: Unidad | E16: {=+XLOOKUP(B16,'Base de datos'!A:A,'Base de datos'!H:H,0)} -> 0.17898 | F16: 1 | G16: 1 | H16: =IFERROR(1-G16/F16,"") -> 0 | I16: =IFERROR(E16*F16,"") -> 0.17898 | K16: Precio venta (s/IVA) | L16: =L15/1.1 -> 7.0909091
B17: {=+XLOOKUP(C17,'Base de datos'!C:C,'Base de datos'!A:A,"",FALSE)} -> 58 | C17: PATATAS FRY & DIP 25 | D17: Kg | E17: {=+XLOOKUP(B17,'Base de datos'!A:A,'Base de datos'!H:H,0)} -> 2.15 | F17: 0.09 | H17: =IFERROR(1-G17/F17,"") -> 1 | I17: =IFERROR(E17*F17,"") -> 0.1935 | K17: IVA | L17: 0.1
K18: Coste de Producto | L18: =L14/L16*100 -> 25.843043 | M18: %
C19: Notas de elaboración | K19: Margen Bruto | L19: =L16-L14 -> 5.2584024 | M19: €
K20: Margen Bruto post Uber | L20: =L16-L14-(L15*0.2) -> 3.6984024 | M20: €
C21: REVISAR EN LOCAL | K21: Margen Bruto post Uber | L21: =L20/L16 -> 0.52156957 | M21: %
C23: 8 nugets
C24: =0.178/8 -> 0.02225
C30: PRODUCTO | D30: BOX ALITAS
B33: ID | C33: Nombre del Plato | D33: Unidad de medida | E33: Precio Unidad | F33: Cantidad Bruta | G33: Cantidad Cocinada/limpia | H33: Merma % | I33: Coste | K33: INDICE
B34: {=+XLOOKUP(C34,'Base de datos'!C:C,'Base de datos'!A:A,"",FALSE)} | D34: Kg | E34: {=+XLOOKUP(B34,'Base de datos'!A:A,'Base de datos'!H:H,0)} -> 0 | H34: =IFERROR(1-G34/F34,"") | I34: =IFERROR(E34*F34,"") -> 0 | K34: Coste Total | L34: =SUM(I34:I45) -> 2.4242067
B35: =ALITAS!K29 -> #REF! | C35: =ALITAS!C29 -> #REF! | D35: Kg | E35: =ALITAS!K35 -> #REF! | H35: =IFERROR(1-G35/F35,"") | I35: =IFERROR(E35*F35,"") | K35: PVP | L35: 6
B36: {=+XLOOKUP(C36,'Base de datos'!C:C,'Base de datos'!A:A,"",FALSE)} -> 143 | C36: ALITAS POLLO BBQ | D36: Kg | E36: {=+XLOOKUP(B36,'Base de datos'!A:A,'Base de datos'!H:H,0)} -> 6.55 | F36: 0.286 | G36: 0.27 | H36: =IFERROR(1-G36/F36,"") -> 0.055944056 | I36: =IFERROR(E36*F36,"") -> 1.8733 | K36: Precio venta (s/IVA) | L36: =L35/1.1 -> 5.4545455
B37: {=+XLOOKUP(C37,'Base de datos'!C:C,'Base de datos'!A:A,"",FALSE)} -> 132 | C37: ALIOLI SOFI | D37: Kg | E37: {=+XLOOKUP(B37,'Base de datos'!A:A,'Base de datos'!H:H,0)} -> 3.0145342 | F37: 0.05 | H37: =IFERROR(1-G37/F37,"") -> 1 | I37: =IFERROR(E37*F37,"") -> 0.15072671 | K37: IVA | L37: 0.1
K38: Coste de Producto | L38: =L34/L36*100 -> 44.44379 | M38: %
K39: Margen Bruto | L39: =100-L38 -> 55.55621 | M39: %
K41: INDICE UBER
K42: Coste Total | L42: =L34 -> 2.4242067
B43: {=+XLOOKUP(C43,'Base de datos'!C:C,'Base de datos'!A:A,"",FALSE)} -> 93 | C43: SERVILLETA 40X40 100UD | D43: Unidad | E43: {=+XLOOKUP(B43,'Base de datos'!A:A,'Base de datos'!H:H,0)} -> 0.0277 | F43: 1 | G43: 1 | H43: =IFERROR(1-G43/F43,"") -> 0 | I43: =IFERROR(E43*F43,"") -> 0.0277 | K43: PVP | L43: 7
B44: {=+XLOOKUP(C44,'Base de datos'!C:C,'Base de datos'!A:A,"",FALSE)} -> 9 | C44: CAJA BOX 780 | D44: Unidad | E44: {=+XLOOKUP(B44,'Base de datos'!A:A,'Base de datos'!H:H,0)} -> 0.17898 | F44: 1 | G44: 1 | H44: =IFERROR(1-G44/F44,"") -> 0 | I44: =IFERROR(E44*F44,"") -> 0.17898 | K44: Precio venta (s/IVA) | L44: =L43/1.1 -> 6.3636364
B45: {=+XLOOKUP(C45,'Base de datos'!C:C,'Base de datos'!A:A,"",FALSE)} -> 58 | C45: PATATAS FRY & DIP 25 | D45: Kg | E45: {=+XLOOKUP(B45,'Base de datos'!A:A,'Base de datos'!H:H,0)} -> 2.15 | F45: 0.09 | H45: =IFERROR(1-G45/F45,"") -> 1 | I45: =IFERROR(E45*F45,"") -> 0.1935 | K45: IVA | L45: 0.1
K46: Coste de Producto | L46: =L42/L44*100 -> 38.094677 | M46: %
C47: Notas de elaboración | K47: Margen Bruto | L47: =L44-L42 -> 3.9394297 | M47: €
K48: Margen Bruto post Uber | L48: =L44-L42-(L43*0.2) -> 2.5394297 | M48: €
C49: REVISAR EN LOCAL | K49: Margen Bruto post Uber | L49: =L48/L44 -> 0.39905323 | M49: %
C58: PRODUCTO | D58: BOX TEKILLOS
B61: ID | C61: Nombre del Plato | D61: Unidad de medida | E61: Precio Unidad | F61: Cantidad Bruta | G61: Cantidad Cocinada/limpia | H61: Merma % | I61: Coste | K61: INDICE
B62: {=+XLOOKUP(C62,'Base de datos'!C:C,'Base de datos'!A:A,"",FALSE)} | D62: Kg | E62: {=+XLOOKUP(B62,'Base de datos'!A:A,'Base de datos'!H:H,0)} -> 0 | H62: =IFERROR(1-G62/F62,"") | I62: =IFERROR(E62*F62,"") -> 0 | K62: Coste Total | L62: =SUM(I62:I73) -> 1.5235317
B63: =TEKILLOS!K29 -> #REF! | C63: =TEKILLOS!C29 -> #REF! | D63: Kg | E63: =TEKILLOS!K35 -> #REF! | H63: =IFERROR(1-G63/F63,"") | I63: =IFERROR(E63*F63,"") | K63: PVP | L63: 5
B64: {=+XLOOKUP(C64,'Base de datos'!C:C,'Base de datos'!A:A,"",FALSE)} -> 145 | C64: TEKILLOS QUESO GOUDA | D64: Unidad | E64: {=+XLOOKUP(B64,'Base de datos'!A:A,'Base de datos'!H:H,0)} -> 0.38870833 | F64: 3 | H64: =IFERROR(1-G64/F64,"") -> 1 | I64: =IFERROR(E64*F64,"") -> 1.166125 | K64: Precio venta (s/IVA) | L64: =L63/1.1 -> 4.5454545
B65: {=+XLOOKUP(C65,'Base de datos'!C:C,'Base de datos'!A:A,"",FALSE)} -> 132 | C65: ALIOLI SOFI | D65: Kg | E65: {=+XLOOKUP(B65,'Base de datos'!A:A,'Base de datos'!H:H,0)} -> 3.0145342 | F65: 0.05 | H65: =IFERROR(1-G65/F65,"") -> 1 | I65: =IFERROR(E65*F65,"") -> 0.15072671 | K65: IVA | L65: 0.1
K66: Coste de Producto | L66: =L62/L64*100 -> 33.517698 | M66: %
K67: Margen Bruto | L67: =100-L66 -> 66.482302 | M67: %
K69: INDICE UBER
K70: Coste Total | L70: =L62 -> 1.5235317
B71: {=+XLOOKUP(C71,'Base de datos'!C:C,'Base de datos'!A:A,"",FALSE)} -> 93 | C71: SERVILLETA 40X40 100UD | D71: Unidad | E71: {=+XLOOKUP(B71,'Base de datos'!A:A,'Base de datos'!H:H,0)} -> 0.0277 | F71: 1 | G71: 1 | H71: =IFERROR(1-G71/F71,"") -> 0 | I71: =IFERROR(E71*F71,"") -> 0.0277 | K71: PVP | L71: 7
B72: {=+XLOOKUP(C72,'Base de datos'!C:C,'Base de datos'!A:A,"",FALSE)} -> 9 | C72: CAJA BOX 780 | D72: Unidad | E72: {=+XLOOKUP(B72,'Base de datos'!A:A,'Base de datos'!H:H,0)} -> 0.17898 | F72: 1 | G72: 1 | H72: =IFERROR(1-G72/F72,"") -> 0 | I72: =IFERROR(E72*F72,"") -> 0.17898 | K72: Precio venta (s/IVA) | L72: =L71/1.1 -> 6.3636364
K73: IVA | L73: 0.1
K74: Coste de Producto | L74: =L70/L72*100 -> 23.941213 | M74: %
C75: Notas de elaboración | K75: Margen Bruto | L75: =L72-L70 -> 4.8401047 | M75: €
K76: Margen Bruto post Uber | L76: =L72-L70-(L71*0.2) -> 3.4401047 | M76: €
C77: REVISAR EN LOCAL | K77: Margen Bruto post Uber | L77: =L76/L72 -> 0.54058787 | M77: %
C86: PRODUCTO | D86: BOX LAGRIMITAS
B89: ID | C89: Nombre del Plato | D89: Unidad de medida | E89: Precio Unidad | F89: Cantidad Bruta | G89: Cantidad Cocinada/limpia | H89: Merma % | I89: Coste | K89: INDICE
B90: {=+XLOOKUP(C90,'Base de datos'!C:C,'Base de datos'!A:A,"",FALSE)} | D90: Kg | E90: {=+XLOOKUP(B90,'Base de datos'!A:A,'Base de datos'!H:H,0)} -> 0 | H90: =IFERROR(1-G90/F90,"") | I90: =IFERROR(E90*F90,"") -> 0 | K90: Coste Total | L90: =SUM(I90:I101) -> 1.5589067
B91: =LAGRIMITAS!K29 -> #REF! | C91: =LAGRIMITAS!C29 -> #REF! | D91: Kg | E91: =LAGRIMITAS!K35 -> #REF! | H91: =IFERROR(1-G91/F91,"") | I91: =IFERROR(E91*F91,"") | K91: PVP | L91: 6
B92: {=+XLOOKUP(C92,'Base de datos'!C:C,'Base de datos'!A:A,"",FALSE)} -> 38 | C92: LAGRIMITAS | D92: Kg | E92: {=+XLOOKUP(B92,'Base de datos'!A:A,'Base de datos'!H:H,0)} -> 6 | F92: 0.168 | G92: 0.16 | H92: =IFERROR(1-G92/F92,"") -> 0.047619048 | I92: =IFERROR(E92*F92,"") -> 1.008 | K92: Precio venta (s/IVA) | L92: =L91/1.1 -> 5.4545455
B93: {=+XLOOKUP(C93,'Base de datos'!C:C,'Base de datos'!A:A,"",FALSE)} -> 132 | C93: ALIOLI SOFI | D93: Kg | E93: {=+XLOOKUP(B93,'Base de datos'!A:A,'Base de datos'!H:H,0)} -> 3.0145342 | F93: 0.05 | H93: =IFERROR(1-G93/F93,"") -> 1 | I93: =IFERROR(E93*F93,"") -> 0.15072671 | K93: IVA | L93: 0.1
K94: Coste de Producto | L94: =L90/L92*100 -> 28.579956 | M94: %
K95: Margen Bruto | L95: =100-L94 -> 71.420044 | M95: %
K97: INDICE UBER
K98: Coste Total | L98: =L90 -> 1.5589067
B99: {=+XLOOKUP(C99,'Base de datos'!C:C,'Base de datos'!A:A,"",FALSE)} -> 93 | C99: SERVILLETA 40X40 100UD | D99: Unidad | E99: {=+XLOOKUP(B99,'Base de datos'!A:A,'Base de datos'!H:H,0)} -> 0.0277 | F99: 1 | G99: 1 | H99: =IFERROR(1-G99/F99,"") -> 0 | I99: =IFERROR(E99*F99,"") -> 0.0277 | K99: PVP | L99: 7
B100: {=+XLOOKUP(C100,'Base de datos'!C:C,'Base de datos'!A:A,"",FALSE)} -> 9 | C100: CAJA BOX 780 | D100: Unidad | E100: {=+XLOOKUP(B100,'Base de datos'!A:A,'Base de datos'!H:H,0)} -> 0.17898 | F100: 1 | G100: 1 | H100: =IFERROR(1-G100/F100,"") -> 0 | I100: =IFERROR(E100*F100,"") -> 0.17898 | K100: Precio venta (s/IVA) | L100: =L99/1.1 -> 6.3636364
B101: {=+XLOOKUP(C101,'Base de datos'!C:C,'Base de datos'!A:A,"",FALSE)} -> 58 | C101: PATATAS FRY & DIP 25 | D101: Kg | E101: {=+XLOOKUP(B101,'Base de datos'!A:A,'Base de datos'!H:H,0)} -> 2.15 | F101: 0.09 | H101: =IFERROR(1-G101/F101,"") -> 1 | I101: =IFERROR(E101*F101,"") -> 0.1935 | K101: IVA | L101: 0.1
K102: Coste de Producto | L102: =L98/L100*100 -> 24.497105 | M102: %
C103: Notas de elaboración | K103: Margen Bruto | L103: =L100-L98 -> 4.8047297 | M103: €
K104: Margen Bruto post Uber | L104: =L100-L98-(L99*0.2) -> 3.4047297 | M104: €
C105: REVISAR EN LOCAL | K105: Margen Bruto post Uber | L105: =L104/L100 -> 0.53502895 | M105: %
C114: PRODUCTO | D114: BOX PATATAS
B117: ID | C117: Nombre del Plato | D117: Unidad de medida | E117: Precio Unidad | F117: Cantidad Bruta | G117: Cantidad Cocinada/limpia | H117: Merma % | I117: Coste | K117: INDICE
B118: {=+XLOOKUP(C118,'Base de datos'!C:C,'Base de datos'!A:A,"",FALSE)} | D118: Kg | E118: {=+XLOOKUP(B118,'Base de datos'!A:A,'Base de datos'!H:H,0)} -> 0 | H118: =IFERROR(1-G118/F118,"") | I118: =IFERROR(E118*F118,"") -> 0 | K118: Coste Total | L118: =SUM(I118:I129) -> 0.91663342
B119: ='BOX PATATAS'!K29 -> #REF! | C119: ='BOX PATATAS'!C29 -> #REF! | D119: Kg | E119: ='BOX PATATAS'!K35 -> #REF! | H119: =IFERROR(1-G119/F119,"") | I119: =IFERROR(E119*F119,"") | K119: PVP | L119: 5
K120: Precio venta (s/IVA) | L120: =L119/1.1 -> 4.5454545
B121: {=+XLOOKUP(C121,'Base de datos'!C:C,'Base de datos'!A:A,"",FALSE)} -> 132 | C121: ALIOLI SOFI | D121: Kg | E121: {=+XLOOKUP(B121,'Base de datos'!A:A,'Base de datos'!H:H,0)} -> 3.0145342 | F121: 0.05 | H121: =IFERROR(1-G121/F121,"") -> 1 | I121: =IFERROR(E121*F121,"") -> 0.15072671 | K121: IVA | L121: 0.1
B122: {=+XLOOKUP(C122,'Base de datos'!C:C,'Base de datos'!A:A,"",FALSE)} -> 132 | C122: ALIOLI SOFI | D122: Kg | E122: {=+XLOOKUP(B122,'Base de datos'!A:A,'Base de datos'!H:H,0)} -> 3.0145342 | F122: 0.05 | H122: =IFERROR(1-G122/F122,"") -> 1 | I122: =IFERROR(E122*F122,"") -> 0.15072671 | K122: Coste de Producto | L122: =L118/L120*100 -> 20.165935 | M122: %
K123: Margen Bruto | L123: =100-L122 -> 79.834065 | M123: %
K125: INDICE UBER
K126: Coste Total | L126: =L118 -> 0.91663342
B127: {=+XLOOKUP(C127,'Base de datos'!C:C,'Base de datos'!A:A,"",FALSE)} -> 93 | C127: SERVILLETA 40X40 100UD | D127: Unidad | E127: {=+XLOOKUP(B127,'Base de datos'!A:A,'Base de datos'!H:H,0)} -> 0.0277 | F127: 1 | G127: 1 | H127: =IFERROR(1-G127/F127,"") -> 0 | I127: =IFERROR(E127*F127,"") -> 0.0277 | K127: PVP | L127: 6.5
B128: {=+XLOOKUP(C128,'Base de datos'!C:C,'Base de datos'!A:A,"",FALSE)} -> 9 | C128: CAJA BOX 780 | D128: Unidad | E128: {=+XLOOKUP(B128,'Base de datos'!A:A,'Base de datos'!H:H,0)} -> 0.17898 | F128: 1 | G128: 1 | H128: =IFERROR(1-G128/F128,"") -> 0 | I128: =IFERROR(E128*F128,"") -> 0.17898 | K128: Precio venta (s/IVA) | L128: =L127/1.1 -> 5.9090909
B129: {=+XLOOKUP(C129,'Base de datos'!C:C,'Base de datos'!A:A,"",FALSE)} -> 58 | C129: PATATAS FRY & DIP 25 | D129: Kg | E129: {=+XLOOKUP(B129,'Base de datos'!A:A,'Base de datos'!H:H,0)} -> 2.15 | F129: 0.19 | H129: =IFERROR(1-G129/F129,"") -> 1 | I129: =IFERROR(E129*F129,"") -> 0.4085 | K129: IVA | L129: 0.1
K130: Coste de Producto | L130: =L126/L128*100 -> 15.512258 | M130: %
C131: Notas de elaboración | K131: Margen Bruto | L131: =L128-L126 -> 4.9924575 | M131: €
K132: Margen Bruto post Uber | L132: =L128-L126-(L127*0.2) -> 3.6924575 | M132: €
K133: Margen Bruto post Uber | L133: =L132/L128 -> 0.62487742 | M133: %
C142: PRODUCTO | D142: PATATAS CARTUCHO
B145: ID | C145: Nombre del Plato | D145: Unidad de medida | E145: Precio Unidad | F145: Cantidad Bruta | G145: Cantidad Cocinada/limpia | H145: Merma % | I145: Coste | K145: INDICE
B146: {=+XLOOKUP(C146,'Base de datos'!C:C,'Base de datos'!A:A,"",FALSE)} | D146: Kg | E146: {=+XLOOKUP(B146,'Base de datos'!A:A,'Base de datos'!H:H,0)} -> 0 | H146: =IFERROR(1-G146/F146,"") | I146: =IFERROR(E146*F146,"") -> 0 | K146: Coste Total | L146: =SUM(I146:I157) -> 0.26404167
B147: ='CARTUCHO PATATAS'!K29 -> #REF! | C147: ='CARTUCHO PATATAS'!C29 -> #REF! | D147: Kg | E147: ='CARTUCHO PATATAS'!K35 -> #REF! | H147: =IFERROR(1-G147/F147,"") | I147: =IFERROR(E147*F147,"") | K147: PVP | L147: 2
K148: Precio venta (s/IVA) | L148: =L147/1.1 -> 1.8181818
K149: IVA | L149: 0.1
K150: Coste de Producto | L150: =L146/L148*100 -> 14.522292 | M150: %
K151: Margen Bruto | L151: =100-L150 -> 85.477708 | M151: %
K153: INDICE UBER
K154: Coste Total | L154: =L146 -> 0.26404167
B155: {=+XLOOKUP(C155,'Base de datos'!C:C,'Base de datos'!A:A,"",FALSE)} | K155: PVP | L155: 2.9
B156: {=+XLOOKUP(C156,'Base de datos'!C:C,'Base de datos'!A:A,"",FALSE)} -> 69 | C156: Petaca patatas | D156: Unidad | E156: {=+XLOOKUP(B156,'Base de datos'!A:A,'Base de datos'!H:H,0)} -> 0.070541667 | F156: 1 | G156: 1 | H156: =IFERROR(1-G156/F156,"") -> 0 | I156: =IFERROR(E156*F156,"") -> 0.070541667 | K156: Precio venta (s/IVA) | L156: =L155/1.1 -> 2.6363636
B157: {=+XLOOKUP(C157,'Base de datos'!C:C,'Base de datos'!A:A,"",FALSE)} -> 58 | C157: PATATAS FRY & DIP 25 | D157: Kg | E157: {=+XLOOKUP(B157,'Base de datos'!A:A,'Base de datos'!H:H,0)} -> 2.15 | F157: 0.09 | H157: =IFERROR(1-G157/F157,"") -> 1 | I157: =IFERROR(E157*F157,"") -> 0.1935 | K157: IVA | L157: 0.1
...

Sheet SERRANOS
C2: PRODUCTO | D2: SERRANO DE POLLO
B5: ID | C5: Nombre del Plato | D5: Unidad de medida | E5: Precio Unidad | F5: Cantidad Bruta | G5: Cantidad Cocinada/limpia | H5: Merma % | I5: Coste | K5: INDICE | O5: INDICE UBER
B6: {=+XLOOKUP(C6,'Base de datos'!C:C,'Base de datos'!A:A,"",FALSE)} | H6: =IFERROR(1-G6/F6,"") | K6: Coste Total | L6: =SUM(I6:I17) -> 1.6271182 | O6: Coste Total | P6: =L6 -> 1.6271182
B7: =K29 | H7: =IFERROR(1-G7/F7,"") | K7: PVP | L7: 6 | O7: PVP | P7: 8.2
B8: {=+XLOOKUP(C8,'Base de datos'!C:C,'Base de datos'!A:A,"",FALSE)} -> 63 | C8: PECHUGA POLLO FILETEADA 25 SADA | D8: Kg | E8: {=+XLOOKUP(B8,'Base de datos'!A:A,'Base de datos'!H:H,0)} -> 6.15 | F8: 0.11 | G8: 0.1 | H8: =IFERROR(1-G8/F8,"") -> 0.090909091 | I8: =IFERROR(E8*F8,"") -> 0.6765 | K8: Precio venta (s/IVA) | L8: =L7/1.1 -> 5.4545455 | O8: Precio venta (s/IVA) | P8: =P7/1.1 -> 7.4545455
B9: {=+XLOOKUP(C9,'Base de datos'!C:C,'Base de datos'!A:A,"",FALSE)} -> 110 | C9: PAN BAGUETTE LA PARRA | D9: Unidad | E9: {=+XLOOKUP(B9,'Base de datos'!A:A,'Base de datos'!H:H,0)} -> 0.28181818 | F9: 1 | G9: 1 | H9: =IFERROR(1-G9/F9,"") -> 0 | I9: =IFERROR(E9*F9,"") -> 0.28181818 | K9: IVA | L9: 0.1 | O9: IVA | P9: 0.1
B10: {=+XLOOKUP(C10,'Base de datos'!C:C,'Base de datos'!A:A,"",FALSE)} -> 96 | C10: TOMATE DANIELA | D10: Kg | E10: {=+XLOOKUP(B10,'Base de datos'!A:A,'Base de datos'!H:H,0)} -> 1.8 | F10: 0.01 | G10: 0.01 | H10: =IFERROR(1-G10/F10,"") -> 0 | I10: =IFERROR(E10*F10,"") -> 0.018 | K10: Coste de Producto | L10: =L6/L8*100 -> 29.8305 | M10: % | O10: Coste de Producto | P10: =P6/P8*100 -> 21.827195 | Q10: %
B11: {=+XLOOKUP(C11,'Base de datos'!C:C,'Base de datos'!A:A,"",FALSE)} -> 72 | C11: PIMIENTO | D11: Kg | E11: {=+XLOOKUP(B11,'Base de datos'!A:A,'Base de datos'!H:H,0)} -> 2 | F11: 0.01 | G11: 0.01 | H11: =IFERROR(1-G11/F11,"") -> 0 | I11: =IFERROR(E11*F11,"") -> 0.02 | K11: Margen Bruto | L11: =100-L10 -> 70.1695 | M11: % | O11: Margen Bruto | P11: =P8-P6 -> 5.8274273 | Q11: €
B12: {=+XLOOKUP(C12,'Base de datos'!C:C,'Base de datos'!A:A,"",FALSE)} -> 37 | C12: JAMON LONCHEADO CUMBRE IB. | D12: Kg | E12: {=+XLOOKUP(B12,'Base de datos'!A:A,'Base de datos'!H:H,0)} -> 7 | F12: 0.02 | G12: 0.02 | H12: =IFERROR(1-G12/F12,"") -> 0 | I12: =IFERROR(E12*F12,"") -> 0.14 | O12: Margen Bruto post Uber | P12: =P8-P6-(P7*0.2) -> 4.1874273 | Q12: €
B13: {=+XLOOKUP(C13,'Base de datos'!C:C,'Base de datos'!A:A,"",FALSE)} -> 34 | C13: HUEVO LÍQUIDO GRANJA | D13: Litro | E13: {=+XLOOKUP(B13,'Base de datos'!A:A,'Base de datos'!H:H,0)} -> 3.75 | F13: 0.02 | G13: 0.02 | H13: =IFERROR(1-G13/F13,"") -> 0 | I13: =IFERROR(E13*F13,"") -> 0.075 | O13: Margen Bruto post Uber | P13: =P12/P8 -> 0.56172805 | Q13: %
B14: {=+XLOOKUP(C14,'Base de datos'!C:C,'Base de datos'!A:A,"",FALSE)} | D14: Kg | E14: {=+XLOOKUP(B14,'Base de datos'!A:A,'Base de datos'!H:H,0)} -> 0 | I14: =IFERROR(E14*F14,"") -> 0
B15: {=+XLOOKUP(C15,'Base de datos'!C:C,'Base de datos'!A:A,"",FALSE)} -> 93 | C15: SERVILLETA 40X40 100UD | D15: Unidad | E15: {=+XLOOKUP(B15,'Base de datos'!A:A,'Base de datos'!H:H,0)} -> 0.0277 | F15: 1 | G15: 1 | H15: =IFERROR(1-G15/F15,"") -> 0 | I15: =IFERROR(E15*F15,"") -> 0.0277
B16: {=+XLOOKUP(C16,'Base de datos'!C:C,'Base de datos'!A:A,"",FALSE)} -> 29 | C16: ENVASE SERRANO IP10 .25 | D16: Unidad | E16: {=+XLOOKUP(B16,'Base de datos'!A:A,'Base de datos'!H:H,0)} -> 0.1946 | F16: 1 | G16: 1 | H16: =IFERROR(1-G16/F16,"") -> 0 | I16: =IFERROR(E16*F16,"") -> 0.1946
B17: {=+XLOOKUP(C17,'Base de datos'!C:C,'Base de datos'!A:A,"",FALSE)} -> 58 | C17: PATATAS FRY & DIP 25 | D17: Kg | E17: {=+XLOOKUP(B17,'Base de datos'!A:A,'Base de datos'!H:H,0)} -> 2.15 | F17: 0.09 | H17: =IFERROR(1-G17/F17,"") -> 1 | I17: =IFERROR(E17*F17,"") -> 0.1935
C19: Notas de elaboración
C30: PRODUCTO | D30: SERRANO EMPANADO
B33: ID | C33: Nombre del Plato | D33: Unidad de medida | E33: Precio Unidad | F33: Cantidad Bruta | G33: Cantidad Cocinada/limpia | H33: Merma % | I33: Coste | K33: INDICE | O33: INDICE UBER
K34: Coste Total | L34: =SUM(I34:I45) -> 1.5666182 | O34: Coste Total | P34: =L34 -> 1.5666182
K35: PVP | L35: 6.5 | O35: PVP | P35: 9.2
B36: {=+XLOOKUP(C36,'Base de datos'!C:C,'Base de datos'!A:A,"",FALSE)} -> 62 | C36: PECHUGA EMPANADA 25 | D36: Kg | E36: {=+XLOOKUP(B36,'Base de datos'!A:A,'Base de datos'!H:H,0)} -> 5.6 | F36: 0.11 | G36: 0.1 | H36: =IFERROR(1-G36/F36,"") -> 0.090909091 | I36: =IFERROR(E36*F36,"") -> 0.616 | K36: Precio venta (s/IVA) | L36: =L35/1.1 -> 5.9090909 | O36: Precio venta (s/IVA) | P36: =P35/1.1 -> 8.3636364
B37: {=+XLOOKUP(C37,'Base de datos'!C:C,'Base de datos'!A:A,"",FALSE)} -> 110 | C37: PAN BAGUETTE LA PARRA | D37: Unidad | E37: {=+XLOOKUP(B37,'Base de datos'!A:A,'Base de datos'!H:H,0)} -> 0.28181818 | F37: 1 | G37: 1 | H37: =IFERROR(1-G37/F37,"") -> 0 | I37: =IFERROR(E37*F37,"") -> 0.28181818 | K37: IVA | L37: 0.1 | O37: IVA | P37: 0.1
B38: {=+XLOOKUP(C38,'Base de datos'!C:C,'Base de datos'!A:A,"",FALSE)} -> 96 | C38: TOMATE DANIELA | D38: Kg | E38: {=+XLOOKUP(B38,'Base de datos'!A:A,'Base de datos'!H:H,0)} -> 1.8 | F38: 0.01 | G38: 0.01 | H38: =IFERROR(1-G38/F38,"") -> 0 | I38: =IFERROR(E38*F38,"") -> 0.018 | K38: Coste de Producto | L38: =L34/L36*100 -> 26.512 | M38: % | O38: Coste de Producto | P38: =P34/P36*100 -> 18.731304 | Q38: %
B39: {=+XLOOKUP(C39,'Base de datos'!C:C,'Base de datos'!A:A,"",FALSE)} -> 72 | C39: PIMIENTO | D39: Kg | E39: {=+XLOOKUP(B39,'Base de datos'!A:A,'Base de datos'!H:H,0)} -> 2 | F39: 0.01 | G39: 0.01 | H39: =IFERROR(1-G39/F39,"") -> 0 | I39: =IFERROR(E39*F39,"") -> 0.02 | K39: Margen Bruto | L39: =100-L38 -> 73.488 | M39: % | O39: Margen Bruto | P39: =P36-P34 -> 6.7970182 | Q39: €
B40: {=+XLOOKUP(C40,'Base de datos'!C:C,'Base de datos'!A:A,"",FALSE)} -> 37 | C40: JAMON LONCHEADO CUMBRE IB. | D40: Kg | E40: {=+XLOOKUP(B40,'Base de datos'!A:A,'Base de datos'!H:H,0)} -> 7 | F40: 0.02 | G40: 0.02 | H40: =IFERROR(1-G40/F40,"") -> 0 | I40: =IFERROR(E40*F40,"") -> 0.14 | O40: Margen Bruto post Uber | P40: =P36-P34-(P35*0.2) -> 4.9570182 | Q40: €
B41: {=+XLOOKUP(C41,'Base de datos'!C:C,'Base de datos'!A:A,"",FALSE)} -> 34 | C41: HUEVO LÍQUIDO GRANJA | D41: Litro | E41: {=+XLOOKUP(B41,'Base de datos'!A:A,'Base de datos'!H:H,0)} -> 3.75 | F41: 0.02 | G41: 0.02 | H41: =IFERROR(1-G41/F41,"") -> 0 | I41: =IFERROR(E41*F41,"") -> 0.075 | O41: Margen Bruto post Uber | P41: =P40/P36 -> 0.59268696 | Q41: %
B42: {=+XLOOKUP(C42,'Base de datos'!C:C,'Base de datos'!A:A,"",FALSE)} | D42: Kg | E42: {=+XLOOKUP(B42,'Base de datos'!A:A,'Base de datos'!H:H,0)} -> 0 | I42: =IFERROR(E42*F42,"") -> 0
B43: {=+XLOOKUP(C43,'Base de datos'!C:C,'Base de datos'!A:A,"",FALSE)} -> 93 | C43: SERVILLETA 40X40 100UD | D43: Unidad | E43: {=+XLOOKUP(B43,'Base de datos'!A:A,'Base de datos'!H:H,0)} -> 0.0277 | F43: 1 | G43: 1 | H43: =IFERROR(1-G43/F43,"") -> 0 | I43: =IFERROR(E43*F43,"") -> 0.0277
B44: {=+XLOOKUP(C44,'Base de datos'!C:C,'Base de datos'!A:A,"",FALSE)} -> 29 | C44: ENVASE SERRANO IP10 .25 | D44: Unidad | E44: {=+XLOOKUP(B44,'Base de datos'!A:A,'Base de datos'!H:H,0)} -> 0.1946 | F44: 1 | G44: 1 | H44: =IFERROR(1-G44/F44,"") -> 0 | I44: =IFERROR(E44*F44,"") -> 0.1946
B45: {=+XLOOKUP(C45,'Base de datos'!C:C,'Base de datos'!A:A,"",FALSE)} -> 58 | C45: PATATAS FRY & DIP 25 | D45: Kg | E45: {=+XLOOKUP(B45,'Base de datos'!A:A,'Base de datos'!H:H,0)} -> 2.15 | F45: 0.09 | H45: =IFERROR(1-G45/F45,"") -> 1 | I45: =IFERROR(E45*F45,"") -> 0.1935
C47: Notas de elaboración
C59: PRODUCTO | D59: SERRANO POLLO ASADO
B62: ID | C62: Nombre del Plato | D62: Unidad de medida | E62: Precio Unidad | F62: Cantidad Bruta | G62: Cantidad Cocinada/limpia | H62: Merma % | I62: Coste | K62: INDICE | O62: INDICE UBER
B63: {=+XLOOKUP(C63,'Base de datos'!C:C,'Base de datos'!A:A,"",FALSE)} | D63: Kg | E63: {=+XLOOKUP(B63,'Base de datos'!A:A,'Base de datos'!H:H,0)} -> 0 | H63: =IFERROR(1-G63/F63,"") | I63: =IFERROR(E63*F63,"") -> 0 | K63: Coste Total | L63: =SUM(I63:I74) -> 1.5660028 | O63: Coste Total | P63: =L63 -> 1.5660028
B64: ='SERRANO POLLO ASADO'!K29 -> #REF! | C64: ='SERRANO POLLO ASADO'!C29 -> #REF! | D64: Kg | E64: ='SERRANO POLLO ASADO'!K35 -> #REF! | H64: =IFERROR(1-G64/F64,"") | I64: =IFERROR(E64*F64,"") | K64: PVP | L64: 6.5 | O64: PVP | P64: 9.2
B65: {=+XLOOKUP(C65,'Base de datos'!C:C,'Base de datos'!A:A,"",FALSE)} -> 74 | C65: POLLO ASADO | D65: Kg | E65: {=+XLOOKUP(B65,'Base de datos'!A:A,'Base de datos'!H:H,0)} -> 6.1538462 | F65: 0.1 | G65: 0.1 | H65: =IFERROR(1-G65/F65,"") -> 0 | I65: =IFERROR(E65*F65,"") -> 0.61538462 | K65: Precio venta (s/IVA) | L65: =L64/1.1 -> 5.9090909 | O65: Precio venta (s/IVA) | P65: =P64/1.1 -> 8.3636364
B66: {=+XLOOKUP(C66,'Base de datos'!C:C,'Base de datos'!A:A,"",FALSE)} -> 110 | C66: PAN BAGUETTE LA PARRA | D66: Unidad | E66: {=+XLOOKUP(B66,'Base de datos'!A:A,'Base de datos'!H:H,0)} -> 0.28181818 | F66: 1 | G66: 1 | H66: =IFERROR(1-G66/F66,"") -> 0 | I66: =IFERROR(E66*F66,"") -> 0.28181818 | K66: IVA | L66: 0.1 | O66: IVA | P66: 0.1
B67: {=+XLOOKUP(C67,'Base de datos'!C:C,'Base de datos'!A:A,"",FALSE)} -> 96 | C67: TOMATE DANIELA | D67: Kg | E67: {=+XLOOKUP(B67,'Base de datos'!A:A,'Base de datos'!H:H,0)} -> 1.8 | F67: 0.01 | G67: 0.01 | H67: =IFERROR(1-G67/F67,"") -> 0 | I67: =IFERROR(E67*F67,"") -> 0.018 | K67: Coste de Producto | L67: =L63/L65*100 -> 26.501586 | M67: % | O67: Coste de Producto | P67: =P63/P65*100 -> 18.723946 | Q67: %
B68: {=+XLOOKUP(C68,'Base de datos'!C:C,'Base de datos'!A:A,"",FALSE)} -> 72 | C68: PIMIENTO | D68: Kg | E68: {=+XLOOKUP(B68,'Base de datos'!A:A,'Base de datos'!H:H,0)} -> 2 | F68: 0.01 | G68: 0.01 | H68: =IFERROR(1-G68/F68,"") -> 0 | I68: =IFERROR(E68*F68,"") -> 0.02 | K68: Margen Bruto | L68: =100-L67 -> 73.498414 | M68: % | O68: Margen Bruto | P68: =P65-P63 -> 6.7976336 | Q68: €
B69: {=+XLOOKUP(C69,'Base de datos'!C:C,'Base de datos'!A:A,"",FALSE)} -> 37 | C69: JAMON LONCHEADO CUMBRE IB. | D69: Kg | E69: {=+XLOOKUP(B69,'Base de datos'!A:A,'Base de datos'!H:H,0)} -> 7 | F69: 0.02 | G69: 0.02 | H69: =IFERROR(1-G69/F69,"") -> 0 | I69: =IFERROR(E69*F69,"") -> 0.14 | O69: Margen Bruto post Uber | P69: =P65-P63-(P64*0.2) -> 4.9576336 | Q69: €
B70: {=+XLOOKUP(C70,'Base de datos'!C:C,'Base de datos'!A:A,"",FALSE)} -> 34 | C70: HUEVO LÍQUIDO GRANJA | D70: Litro | E70: {=+XLOOKUP(B70,'Base de datos'!A:A,'Base de datos'!H:H,0)} -> 3.75 | F70: 0.02 | G70: 0.02 | H70: =IFERROR(1-G70/F70,"") -> 0 | I70: =IFERROR(E70*F70,"") -> 0.075 | O70: Margen Bruto post Uber | P70: =P69/P65 -> 0.59276054 | Q70: %
B71: {=+XLOOKUP(C71,'Base de datos'!C:C,'Base de datos'!A:A,"",FALSE)} | D71: Kg | E71: {=+XLOOKUP(B71,'Base de datos'!A:A,'Base de datos'!H:H,0)} -> 0 | I71: =IFERROR(E71*F71,"") -> 0
B72: {=+XLOOKUP(C72,'Base de datos'!C:C,'Base de datos'!A:A,"",FALSE)} -> 93 | C72: SERVILLETA 40X40 100UD | D72: Unidad | E72: {=+XLOOKUP(B72,'Base de datos'!A:A,'Base de datos'!H:H,0)} -> 0.0277 | F72: 1 | G72: 1 | H72: =IFERROR(1-G72/F72,"") -> 0 | I72: =IFERROR(E72*F72,"") -> 0.0277
B73: {=+XLOOKUP(C73,'Base de datos'!C:C,'Base de datos'!A:A,"",FALSE)} -> 29 | C73: ENVASE SERRANO IP10 .25 | D73: Unidad | E73: {=+XLOOKUP(B73,'Base de datos'!A:A,'Base de datos'!H:H,0)} -> 0.1946 | F73: 1 | G73: 1 | H73: =IFERROR(1-G73/F73,"") -> 0 | I73: =IFERROR(E73*F73,"") -> 0.1946
B74: {=+XLOOKUP(C74,'Base de datos'!C:C,'Base de datos'!A:A,"",FALSE)} -> 58 | C74: PATATAS FRY & DIP 25 | D74: Kg | E74: {=+XLOOKUP(B74,'Base de datos'!A:A,'Base de datos'!H:H,0)} -> 2.15 | F74: 0.09 | H74: =IFERROR(1-G74/F74,"") -> 1 | I74: =IFERROR(E74*F74,"") -> 0.1935
C76: Notas de elaboración
C88: PRODUCTO | D88: SERRANO SOLOMILLO
B91: ID | C91: Nombre del Plato | D91: Unidad de medida | E91: Precio Unidad | F91: Cantidad Bruta | G91: Cantidad Cocinada/limpia | H91: Merma % | I91: Coste | K91: INDICE | O91: INDICE UBER
B92: {=+XLOOKUP(C92,'Base de datos'!C:C,'Base de datos'!A:A,"",FALSE)} | D92: Kg | E92: {=+XLOOKUP(B92,'Base de datos'!A:A,'Base de datos'!H:H,0)} -> 0 | H92: =IFERROR(1-G92/F92,"") | I92: =IFERROR(E92*F92,"") -> 0 | K92: Coste Total | L92: =SUM(I92:I103) -> 1.4996182 | O92: Coste Total | P92: =L92 -> 1.4996182
B93: ='SERRANO SOLOMILLO'!K29 -> #REF! | C93: ='SERRANO SOLOMILLO'!C29 -> #REF! | D93: Kg | E93: ='SERRANO SOLOMILLO'!K35 -> #REF! | H93: =IFERROR(1-G93/F93,"") | I93: =IFERROR(E93*F93,"") | K93: PVP | L93: 7 | O93: PVP | P93: 9.2
B94: {=+XLOOKUP(C94,'Base de datos'!C:C,'Base de datos'!A:A,"",FALSE)} -> 116 | C94: SOLOMILLO CERDO | D94: Kg | E94: {=+XLOOKUP(B94,'Base de datos'!A:A,'Base de datos'!H:H,0)} -> 5.49 | F94: 0.1 | G94: 0.1 | H94: =IFERROR(1-G94/F94,"") -> 0 | I94: =IFERROR(E94*F94,"") -> 0.549 | K94: Precio venta (s/IVA) | L94: =L93/1.1 -> 6.3636364 | O94: Precio venta (s/IVA) | P94: =P93/1.1 -> 8.3636364
B95: {=+XLOOKUP(C95,'Base de datos'!C:C,'Base de datos'!A:A,"",FALSE)} -> 110 | C95: PAN BAGUETTE LA PARRA | D95: Unidad | E95: {=+XLOOKUP(B95,'Base de datos'!A:A,'Base de datos'!H:H,0)} -> 0.28181818 | F95: 1 | G95: 1 | H95: =IFERROR(1-G95/F95,"") -> 0 | I95: =IFERROR(E95*F95,"") -> 0.28181818 | K95: IVA | L95: 0.1 | O95: IVA | P95: 0.1
B96: {=+XLOOKUP(C96,'Base de datos'!C:C,'Base de datos'!A:A,"",FALSE)} -> 96 | C96: TOMATE DANIELA | D96: Kg | E96: {=+XLOOKUP(B96,'Base de datos'!A:A,'Base de datos'!H:H,0)} -> 1.8 | F96: 0.01 | G96: 0.01 | H96: =IFERROR(1-G96/F96,"") -> 0 | I96: =IFERROR(E96*F96,"") -> 0.018 | K96: Coste de Producto | L96: =L92/L94*100 -> 23.565429 | M96: % | O96: Coste de Producto | P96: =P92/P94*100 -> 17.930217 | Q96: %
B97: {=+XLOOKUP(C97,'Base de datos'!C:C,'Base de datos'!A:A,"",FALSE)} -> 72 | C97: PIMIENTO | D97: Kg | E97: {=+XLOOKUP(B97,'Base de datos'!A:A,'Base de datos'!H:H,0)} -> 2 | F97: 0.01 | G97: 0.01 | H97: =IFERROR(1-G97/F97,"") -> 0 | I97: =IFERROR(E97*F97,"") -> 0.02 | K97: Margen Bruto | L97: =100-L96 -> 76.434571 | M97: % | O97: Margen Bruto | P97: =P94-P92 -> 6.8640182 | Q97: €
B98: {=+XLOOKUP(C98,'Base de datos'!C:C,'Base de datos'!A:A,"",FALSE)} -> 37 | C98: JAMON LONCHEADO CUMBRE IB. | D98: Kg | E98: {=+XLOOKUP(B98,'Base de datos'!A:A,'Base de datos'!H:H,0)} -> 7 | F98: 0.02 | G98: 0.02 | H98: =IFERROR(1-G98/F98,"") -> 0 | I98: =IFERROR(E98*F98,"") -> 0.14 | O98: Margen Bruto post Uber | P98: =P94-P92-(P93*0.2) -> 5.0240182 | Q98: €
B99: {=+XLOOKUP(C99,'Base de datos'!C:C,'Base de datos'!A:A,"",FALSE)} -> 34 | C99: HUEVO LÍQUIDO GRANJA | D99: Litro | E99: {=+XLOOKUP(B99,'Base de datos'!A:A,'Base de datos'!H:H,0)} -> 3.75 | F99: 0.02 | G99: 0.02 | H99: =IFERROR(1-G99/F99,"") -> 0 | I99: =IFERROR(E99*F99,"") -> 0.075 | O99: Margen Bruto post Uber | P99: =P98/P94 -> 0.60069783 | Q99: %
B100: {=+XLOOKUP(C100,'Base de datos'!C:C,'Base de datos'!A:A,"",FALSE)} | D100: Kg | E100: {=+XLOOKUP(B100,'Base de datos'!A:A,'Base de datos'!H:H,0)} -> 0 | I100: =IFERROR(E100*F100,"") -> 0
B101: {=+XLOOKUP(C101,'Base de datos'!C:C,'Base de datos'!A:A,"",FALSE)} -> 93 | C101: SERVILLETA 40X40 100UD | D101: Unidad | E101: {=+XLOOKUP(B101,'Base de datos'!A:A,'Base de datos'!H:H,0)} -> 0.0277 | F101: 1 | G101: 1 | H101: =IFERROR(1-G101/F101,"") -> 0 | I101: =IFERROR(E101*F101,"") -> 0.0277
B102: {=+XLOOKUP(C102,'Base de datos'!C:C,'Base de datos'!A:A,"",FALSE)} -> 29 | C102: ENVASE SERRANO IP10 .25 | D102: Unidad | E102: {=+XLOOKUP(B102,'Base de datos'!A:A,'Base de datos'!H:H,0)} -> 0.1946 | F102: 1 | G102: 1 | H102: =IFERROR(1-G102/F102,"") -> 0 | I102: =IFERROR(E102*F102,"") -> 0.1946
B103: {=+XLOOKUP(C103,'Base de datos'!C:C,'Base de datos'!A:A,"",FALSE)} -> 58 | C103: PATATAS FRY & DIP 25 | D103: Kg | E103: {=+XLOOKUP(B103,'Base de datos'!A:A,'Base de datos'!H:H,0)} -> 2.15 | F103: 0.09 | H103: =IFERROR(1-G103/F103,"") -> 1 | I103: =IFERROR(E103*F103,"") -> 0.1935
C105: Notas de elaboración
C117: PRODUCTO | D117: SERRANO PULLED PORK
B120: ID | C120: Nombre del Plato | D120: Unidad de medida | E120: Precio Unidad | F120: Cantidad Bruta | G120: Cantidad Cocinada/limpia | H120: Merma % | I120: Coste | K120: INDICE | O120: INDICE UBER
B121: {=+XLOOKUP(C121,'Base de datos'!C:C,'Base de datos'!A:A,"",FALSE)} | D121: Kg | E121: {=+XLOOKUP(B121,'Base de datos'!A:A,'Base de datos'!H:H,0)} -> 0 | H121: =IFERROR(1-G121/F121,"") | I121: =IFERROR(E121*F121,"") -> 0 | K121: Coste Total | L121: =SUM(I121:I132) -> 1.7827765 | O121: Coste Total | P121: =L121 -> 1.7827765
B122: ='SERRANO SOLOMILLO'!K58 -> #REF! | C122: ='SERRANO SOLOMILLO'!C58 -> #REF! | D122: Kg | E122: ='SERRANO SOLOMILLO'!K64 -> #REF! | H122: =IFERROR(1-G122/F122,"") | I122: =IFERROR(E122*F122,"") | K122: PVP | L122: 8 | O122: PVP | P122: 9.2
B123: {=+XLOOKUP(C123,'Base de datos'!C:C,'Base de datos'!A:A,"",FALSE)} -> 78 | C123: PULLED PORK | D123: Kg | E123: {=+XLOOKUP(B123,'Base de datos'!A:A,'Base de datos'!H:H,0)} -> 8.3215833 | F123: 0.1 | G123: 0.1 | H123: =IFERROR(1-G123/F123,"") -> 0 | I123: =IFERROR(E123*F123,"") -> 0.83215833 | K123: Precio venta (s/IVA) | L123: =L122/1.1 -> 7.2727273 | O123: Precio venta (s/IVA) | P123: =P122/1.1 -> 8.3636364
B124: {=+XLOOKUP(C124,'Base de datos'!C:C,'Base de datos'!A:A,"",FALSE)} -> 110 | C124: PAN BAGUETTE LA PARRA | D124: Unidad | E124: {=+XLOOKUP(B124,'Base de datos'!A:A,'Base de datos'!H:H,0)} -> 0.28181818 | F124: 1 | G124: 1 | H124: =IFERROR(1-G124/F124,"") -> 0 | I124: =IFERROR(E124*F124,"") -> 0.28181818 | K124: IVA | L124: 0.1 | O124: IVA | P124: 0.1
B125: {=+XLOOKUP(C125,'Base de datos'!C:C,'Base de datos'!A:A,"",FALSE)} -> 96 | C125: TOMATE DANIELA | D125: Kg | E125: {=+XLOOKUP(B125,'Base de datos'!A:A,'Base de datos'!H:H,0)} -> 1.8 | F125: 0.01 | G125: 0.01 | H125: =IFERROR(1-G125/F125,"") -> 0 | I125: =IFERROR(E125*F125,"") -> 0.018 | K125: Coste de Producto | L125: =L121/L123*100 -> 24.513177 | M125: % | O125: Coste de Producto | P125: =P121/P123*100 -> 21.315806 | Q125: %
B126: {=+XLOOKUP(C126,'Base de datos'!C:C,'Base de datos'!A:A,"",FALSE)} -> 72 | C126: PIMIENTO | D126: Kg | E126: {=+XLOOKUP(B126,'Base de datos'!A:A,'Base de datos'!H:H,0)} -> 2 | F126: 0.01 | G126: 0.01 | H126: =IFERROR(1-G126/F126,"") -> 0 | I126: =IFERROR(E126*F126,"") -> 0.02 | K126: Margen Bruto | L126: =100-L125 -> 75.486823 | M126: % | O126: Margen Bruto | P126: =P123-P121 -> 6.5808598 | Q126: €
B127: {=+XLOOKUP(C127,'Base de datos'!C:C,'Base de datos'!A:A,"",FALSE)} -> 37 | C127: JAMON LONCHEADO CUMBRE IB. | D127: Kg | E127: {=+XLOOKUP(B127,'Base de datos'!A:A,'Base de datos'!H:H,0)} -> 7 | F127: 0.02 | G127: 0.02 | H127: =IFERROR(1-G127/F127,"") -> 0 | I127: =IFERROR(E127*F127,"") -> 0.14 | O127: Margen Bruto post Uber | P127: =P123-P121-(P122*0.2) -> 4.7408598 | Q127: €
B128: {=+XLOOKUP(C128,'Base de datos'!C:C,'Base de datos'!A:A,"",FALSE)} -> 34 | C128: HUEVO LÍQUIDO GRANJA | D128: Litro | E128: {=+XLOOKUP(B128,'Base de datos'!A:A,'Base de datos'!H:H,0)} -> 3.75 | F128: 0.02 | G128: 0.02 | H128: =IFERROR(1-G128/F128,"") -> 0 | I128: =IFERROR(E128*F128,"") -> 0.075 | O128: Margen Bruto post Uber | P128: =P127/P123 -> 0.56684194 | Q128: %
B129: {=+XLOOKUP(C129,'Base de datos'!C:C,'Base de datos'!A:A,"",FALSE)} | D129: Kg | E129: {=+XLOOKUP(B129,'Base de datos'!A:A,'Base de datos'!H:H,0)} -> 0 | I129: =IFERROR(E129*F129,"") -> 0
B130: {=+XLOOKUP(C130,'Base de datos'!C:C,'Base de datos'!A:A,"",FALSE)} -> 93 | C130: SERVILLETA 40X40 100UD | D130: Unidad | E130: {=+XLOOKUP(B130,'Base de datos'!A:A,'Base de datos'!H:H,0)} -> 0.0277 | F130: 1 | G130: 1 | H130: =IFERROR(1-G130/F130,"") -> 0 | I130: =IFERROR(E130*F130,"") -> 0.0277
B131: {=+XLOOKUP(C131,'Base de datos'!C:C,'Base de datos'!A:A,"",FALSE)} -> 29 | C131: ENVASE SERRANO IP10 .25 | D131: Unidad | E131: {=+XLOOKUP(B131,'Base de datos'!A:A,'Base de datos'!H:H,0)} -> 0.1946 | F131: 1 | G131: 1 | H131: =IFERROR(1-G131/F131,"") -> 0 | I131: =IFERROR(E131*F131,"") -> 0.1946
B132: {=+XLOOKUP(C132,'Base de datos'!C:C,'Base de datos'!A:A,"",FALSE)} -> 58 | C132: PATATAS FRY & DIP 25 | D132: Kg | E132: {=+XLOOKUP(B132,'Base de datos'!A:A,'Base de datos'!H:H,0)} -> 2.15 | F132: 0.09 | H132: =IFERROR(1-G132/F132,"") -> 1 | I132: =IFERROR(E132*F132,"") -> 0.1935
C134: Notas de elaboración
C146: PRODUCTO | D146: SERRANO MECHADA
B149: ID | C149: Nombre del Plato | D149: Unidad de medida | E149: Precio Unidad | F149: Cantidad Bruta | G149: Cantidad Cocinada/limpia | H149: Merma % | I149: Coste | K149: INDICE | O149: INDICE UBER
B150: {=+XLOOKUP(C150,'Base de datos'!C:C,'Base de datos'!A:A,"",FALSE)} | D150: Kg | E150: {=+XLOOKUP(B150,'Base de datos'!A:A,'Base de datos'!H:H,0)} -> 0 | H150: =IFERROR(1-G150/F150,"") | I150: =IFERROR(E150*F150,"") -> 0 | K150: Coste Total | L150: =SUM(I150:I161) -> 1.3391303 | O150: Coste Total | P150: =L150 -> 1.3391303
B151: ='SERRANO SOLOMILLO'!K87 -> #REF! | C151: ='SERRANO SOLOMILLO'!C87 -> #REF! | D151: Kg | E151: ='SERRANO SOLOMILLO'!K93 -> #REF! | H151: =IFERROR(1-G151/F151,"") | I151: =IFERROR(E151*F151,"") | K151: PVP | L151: 8 | O151: PVP | P151: 9.2
B152: {=+XLOOKUP(C152,'Base de datos'!C:C,'Base de datos'!A:A,"",FALSE)} -> 161 | C152: CARNE MECHADA DE CABEZA DE CERO | D152: Kg | E152: {=+XLOOKUP(B152,'Base de datos'!A:A,'Base de datos'!H:H,0)} -> 3.8851216 | F152: 0.1 | G152: 0.1 | H152: =IFERROR(1-G152/F152,"") -> 0 | I152: =IFERROR(E152*F152,"") -> 0.38851216 | K152: Precio venta (s/IVA) | L152: =L151/1.1 -> 7.2727273 | O152: Precio venta (s/IVA) | P152: =P151/1.1 -> 8.3636364
B153: {=+XLOOKUP(C153,'Base de datos'!C:C,'Base de datos'!A:A,"",FALSE)} -> 110 | C153: PAN BAGUETTE LA PARRA | D153: Unidad | E153: {=+XLOOKUP(B153,'Base de datos'!A:A,'Base de datos'!H:H,0)} -> 0.28181818 | F153: 1 | G153: 1 | H153: =IFERROR(1-G153/F153,"") -> 0 | I153: =IFERROR(E153*F153,"") -> 0.28181818 | K153: IVA | L153: 0.1 | O153: IVA | P153: 0.1
B154: {=+XLOOKUP(C154,'Base de datos'!C:C,'Base de datos'!A:A,"",FALSE)} -> 96 | C154: TOMATE DANIELA | D154: Kg | E154: {=+XLOOKUP(B154,'Base de datos'!A:A,'Base de datos'!H:H,0)} -> 1.8 | F154: 0.01 | G154: 0.01 | H154: =IFERROR(1-G154/F154,"") -> 0 | I154: =IFERROR(E154*F154,"") -> 0.018 | K154: Coste de Producto | L154: =L150/L152*100 -> 18.413042 | M154: % | O154: Coste de Producto | P154: =P150/P152*100 -> 16.011341 | Q154: %
B155: {=+XLOOKUP(C155,'Base de datos'!C:C,'Base de datos'!A:A,"",FALSE)} -> 72 | C155: PIMIENTO | D155: Kg | E155: {=+XLOOKUP(B155,'Base de datos'!A:A,'Base de datos'!H:H,0)} -> 2 | F155: 0.01 | G155: 0.01 | H155: =IFERROR(1-G155/F155,"") -> 0 | I155: =IFERROR(E155*F155,"") -> 0.02 | K155: Margen Bruto | L155: =100-L154 -> 81.586958 | M155: % | O155: Margen Bruto | P155: =P152-P150 -> 7.024506 | Q155: €
B156: {=+XLOOKUP(C156,'Base de datos'!C:C,'Base de datos'!A:A,"",FALSE)} -> 37 | C156: JAMON LONCHEADO CUMBRE IB. | D156: Kg | E156: {=+XLOOKUP(B156,'Base de datos'!A:A,'Base de datos'!H:H,0)} -> 7 | F156: 0.02 | G156: 0.02 | H156: =IFERROR(1-G156/F156,"") -> 0 | I156: =IFERROR(E156*F156,"") -> 0.14 | O156: Margen Bruto post Uber | P156: =P152-P150-(P151*0.2) -> 5.184506 | Q156: €
B157: {=+XLOOKUP(C157,'Base de datos'!C:C,'Base de datos'!A:A,"",FALSE)} -> 34 | C157: HUEVO LÍQUIDO GRANJA | D157: Litro | E157: {=+XLOOKUP(B157,'Base de datos'!A:A,'Base de datos'!H:H,0)} -> 3.75 | F157: 0.02 | G157: 0.02 | H157: =IFERROR(1-G157/F157,"") -> 0 | I157: =IFERROR(E157*F157,"") -> 0.075 | O157: Margen Bruto post Uber | P157: =P156/P152 -> 0.61988659 | Q157: %
B158: {=+XLOOKUP(C158,'Base de datos'!C:C,'Base de datos'!A:A,"",FALSE)} | D158: Kg | E158: {=+XLOOKUP(B158,'Base de datos'!A:A,'Base de datos'!H:H,0)} -> 0 | I158: =IFERROR(E158*F158,"") -> 0
B159: {=+XLOOKUP(C159,'Base de datos'!C:C,'Base de datos'!A:A,"",FALSE)} -> 93 | C159: SERVILLETA 40X40 100UD | D159: Unidad | E159: {=+XLOOKUP(B159,'Base de datos'!A:A,'Base de datos'!H:H,0)} -> 0.0277 | F159: 1 | G159: 1 | H159: =IFERROR(1-G159/F159,"") -> 0 | I159: =IFERROR(E159*F159,"") -> 0.0277
B160: {=+XLOOKUP(C160,'Base de datos'!C:C,'Base de datos'!A:A,"",FALSE)} -> 29 | C160: ENVASE SERRANO IP10 .25 | D160: Unidad | E160: {=+XLOOKUP(B160,'Base de datos'!A:A,'Base de datos'!H:H,0)} -> 0.1946 | F160: 1 | G160: 1 | H160: =IFERROR(1-G160/F160,"") -> 0 | I160: =IFERROR(E160*F160,"") -> 0.1946
B161: {=+XLOOKUP(C161,'Base de datos'!C:C,'Base de datos'!A:A,"",FALSE)} -> 58 | C161: PATATAS FRY & DIP 25 | D161: Kg | E161: {=+XLOOKUP(B161,'Base de datos'!A:A,'Base de datos'!H:H,0)} -> 2.15 | F161: 0.09 | H161: =IFERROR(1-G161/F161,"") -> 1 | I161: =IFERROR(E161*F161,"") -> 0.1935
C163: Notas de elaboración

Sheet BOCATAS
C2: PRODUCTO | D2: SIMPLE DE POLLO
B5: ID | C5: Nombre del Plato | D5: Unidad de medida | E5: Precio Unidad | F5: Cantidad Bruta | G5: Cantidad Cocinada/limpia | H5: Merma % | I5: Coste | K5: INDICE
B6: {=+XLOOKUP(C6,'Base de datos'!C:C,'Base de datos'!A:A,"",FALSE)} | D6: Kg | E6: {=+XLOOKUP(B6,'Base de datos'!A:A,'Base de datos'!H:H,0)} -> 0 | H6: =IFERROR(1-G6/F6,"") | I6: =IFERROR(E6*F6,"") -> 0 | K6: Coste Total | L6: =SUM(I6:I13) -> 1.4018182
B7: =K25 -> Margen Bruto | C7: =C25 -> ENVASE SERRANO IP10 .25 | D7: Kg | E7: =#REF! -> #REF! | H7: =IFERROR(1-G7/F7,"") | I7: =IFERROR(E7*F7,"") | K7: PVP | L7: 4
B8: {=+XLOOKUP(C8,'Base de datos'!C:C,'Base de datos'!A:A,"",FALSE)} -> 63 | C8: PECHUGA POLLO FILETEADA 25 SADA | D8: Kg | E8: {=+XLOOKUP(B8,'Base de datos'!A:A,'Base de datos'!H:H,0)} -> 6.15 | F8: 0.11 | G8: 0.1 | H8: =IFERROR(1-G8/F8,"") -> 0.090909091 | I8: =IFERROR(E8*F8,"") -> 0.6765 | K8: Precio venta (s/IVA) | L8: =L7/1.1 -> 3.6363636
B9: {=+XLOOKUP(C9,'Base de datos'!C:C,'Base de datos'!A:A,"",FALSE)} -> 110 | C9: PAN BAGUETTE LA PARRA | D9: Unidad | E9: {=+XLOOKUP(B9,'Base de datos'!A:A,'Base de datos'!H:H,0)} -> 0.28181818 | F9: 1 | G9: 1 | H9: =IFERROR(1-G9/F9,"") -> 0 | I9: =IFERROR(E9*F9,"") -> 0.28181818 | K9: IVA | L9: 0.1
B10: {=+XLOOKUP(C10,'Base de datos'!C:C,'Base de datos'!A:A,"",FALSE)} -> 58 | C10: PATATAS FRY & DIP 25 | D10: Kg | E10: {=+XLOOKUP(B10,'Base de datos'!A:A,'Base de datos'!H:H,0)} -> 2.15 | F10: 0.09 | G10: 0.09 | H10: =IFERROR(1-G10/F10,"") -> 0 | I10: =IFERROR(E10*F10,"") -> 0.1935 | K10: Coste de Producto | L10: =L6/L8*100 -> 38.55 | M10: %
B11: {=+XLOOKUP(C11,'Base de datos'!C:C,'Base de datos'!A:A,"",FALSE)} -> 29 | C11: ENVASE SERRANO IP10 .25 | D11: Unidad | E11: {=+XLOOKUP(B11,'Base de datos'!A:A,'Base de datos'!H:H,0)} -> 0.1946 | F11: 1 | G11: 1 | H11: =IFERROR(1-G11/F11,"") -> 0 | I11: =IFERROR(E11*F11,"") -> 0.1946 | K11: Margen Bruto | L11: =100-L10 -> 61.45 | M11: %
B12: {=+XLOOKUP(C12,'Base de datos'!C:C,'Base de datos'!A:A,"",FALSE)} -> 93 | C12: SERVILLETA 40X40 100UD | D12: Unidad | E12: {=+XLOOKUP(B12,'Base de datos'!A:A,'Base de datos'!H:H,0)} -> 0.0277 | F12: 2 | G12: 2 | H12: =IFERROR(1-G12/F12,"") -> 0 | I12: =IFERROR(E12*F12,"") -> 0.0554
B13: {=+XLOOKUP(C13,'Base de datos'!C:C,'Base de datos'!A:A,"",FALSE)} | D13: Kg | E13: {=+XLOOKUP(B13,'Base de datos'!A:A,'Base de datos'!H:H,0)} -> 0 | I13: =IFERROR(E13*F13,"") -> 0
C16: PRODUCTO | D16: SIMPLE EMPANADO
B19: ID | C19: Nombre del Plato | D19: Unidad de medida | E19: Precio Unidad | F19: Cantidad Bruta | G19: Cantidad Cocinada/limpia | H19: Merma % | I19: Coste | K19: INDICE | N19: RESUMEN
B20: {=+XLOOKUP(C20,'Base de datos'!C:C,'Base de datos'!A:A,"",FALSE)} | D20: Kg | E20: {=+XLOOKUP(B20,'Base de datos'!A:A,'Base de datos'!H:H,0)} -> 0 | H20: =IFERROR(1-G20/F20,"") | I20: =IFERROR(E20*F20,"") -> 0 | K20: Coste Total | L20: =SUM(I20:I27) -> 1.3413182
B21: ='SIMPLE EMPANADO. '!K25 -> #REF! | C21: ='SIMPLE EMPANADO. '!C25 -> #REF! | D21: Kg | E21: ='SIMPLE EMPANADO. '!K31 -> #REF! | H21: =IFERROR(1-G21/F21,"") | I21: =IFERROR(E21*F21,"") | K21: PVP | L21: 5
B22: {=+XLOOKUP(C22,'Base de datos'!C:C,'Base de datos'!A:A,"",FALSE)} -> 62 | C22: PECHUGA EMPANADA 25 | D22: Kg | E22: {=+XLOOKUP(B22,'Base de datos'!A:A,'Base de datos'!H:H,0)} -> 5.6 | F22: 0.11 | G22: 0.1 | H22: =IFERROR(1-G22/F22,"") -> 0.090909091 | I22: =IFERROR(E22*F22,"") -> 0.616 | K22: Precio venta (s/IVA) | L22: =L21/1.1 -> 4.5454545
B23: {=+XLOOKUP(C23,'Base de datos'!C:C,'Base de datos'!A:A,"",FALSE)} -> 110 | C23: PAN BAGUETTE LA PARRA | D23: Unidad | E23: {=+XLOOKUP(B23,'Base de datos'!A:A,'Base de datos'!H:H,0)} -> 0.28181818 | F23: 1 | G23: 1 | H23: =IFERROR(1-G23/F23,"") -> 0 | I23: =IFERROR(E23*F23,"") -> 0.28181818 | K23: IVA | L23: 0.1
B24: {=+XLOOKUP(C24,'Base de datos'!C:C,'Base de datos'!A:A,"",FALSE)} -> 58 | C24: PATATAS FRY & DIP 25 | D24: Kg | E24: {=+XLOOKUP(B24,'Base de datos'!A:A,'Base de datos'!H:H,0)} -> 2.15 | F24: 0.09 | G24: 0.09 | H24: =IFERROR(1-G24/F24,"") -> 0 | I24: =IFERROR(E24*F24,"") -> 0.1935 | K24: Coste de Producto | L24: =L20/L22*100 -> 29.509 | M24: %
B25: {=+XLOOKUP(C25,'Base de datos'!C:C,'Base de datos'!A:A,"",FALSE)} -> 29 | C25: ENVASE SERRANO IP10 .25 | D25: Unidad | E25: {=+XLOOKUP(B25,'Base de datos'!A:A,'Base de datos'!H:H,0)} -> 0.1946 | F25: 1 | G25: 1 | H25: =IFERROR(1-G25/F25,"") -> 0 | I25: =IFERROR(E25*F25,"") -> 0.1946 | K25: Margen Bruto | L25: =100-L24 -> 70.491 | M25: %
B26: {=+XLOOKUP(C26,'Base de datos'!C:C,'Base de datos'!A:A,"",FALSE)} -> 93 | C26: SERVILLETA 40X40 100UD | D26: Unidad | E26: {=+XLOOKUP(B26,'Base de datos'!A:A,'Base de datos'!H:H,0)} -> 0.0277 | F26: 2 | G26: 2 | H26: =IFERROR(1-G26/F26,"") -> 0 | I26: =IFERROR(E26*F26,"") -> 0.0554
B27: {=+XLOOKUP(C27,'Base de datos'!C:C,'Base de datos'!A:A,"",FALSE)} | D27: Kg | E27: {=+XLOOKUP(B27,'Base de datos'!A:A,'Base de datos'!H:H,0)} -> 0 | I27: =IFERROR(E27*F27,"") -> 0
C30: PRODUCTO | D30: SIMPLE ASADO
B33: ID | C33: Nombre del Plato | D33: Unidad de medida | E33: Precio Unidad | F33: Cantidad Bruta | G33: Cantidad Cocinada/limpia | H33: Merma % | I33: Coste | K33: INDICE | N33: RESUMEN
B34: {=+XLOOKUP(C34,'Base de datos'!C:C,'Base de datos'!A:A,"",FALSE)} | D34: Kg | E34: {=+XLOOKUP(B34,'Base de datos'!A:A,'Base de datos'!H:H,0)} -> 0 | H34: =IFERROR(1-G34/F34,"") | I34: =IFERROR(E34*F34,"") -> 0 | K34: Coste Total | L34: =SUM(I34:I41) -> 1.3407028
B35: ='SIMPLE ASADO'!K25 -> #REF! | C35: ='SIMPLE ASADO'!C25 -> #REF! | D35: Kg | E35: ='SIMPLE ASADO'!K31 -> #REF! | H35: =IFERROR(1-G35/F35,"") | I35: =IFERROR(E35*F35,"") | K35: PVP | L35: 5.5
B36: {=+XLOOKUP(C36,'Base de datos'!C:C,'Base de datos'!A:A,"",FALSE)} -> 74 | C36: POLLO ASADO | D36: Kg | E36: {=+XLOOKUP(B36,'Base de datos'!A:A,'Base de datos'!H:H,0)} -> 6.1538462 | F36: 0.1 | G36: 0.1 | H36: =IFERROR(1-G36/F36,"") -> 0 | I36: =IFERROR(E36*F36,"") -> 0.61538462 | K36: Precio venta (s/IVA) | L36: =L35/1.1 -> 5
B37: {=+XLOOKUP(C37,'Base de datos'!C:C,'Base de datos'!A:A,"",FALSE)} -> 110 | C37: PAN BAGUETTE LA PARRA | D37: Unidad | E37: {=+XLOOKUP(B37,'Base de datos'!A:A,'Base de datos'!H:H,0)} -> 0.28181818 | F37: 1 | G37: 1 | H37: =IFERROR(1-G37/F37,"") -> 0 | I37: =IFERROR(E37*F37,"") -> 0.28181818 | K37: IVA | L37: 0.1
B38: {=+XLOOKUP(C38,'Base de datos'!C:C,'Base de datos'!A:A,"",FALSE)} -> 58 | C38: PATATAS FRY & DIP 25 | D38: Kg | E38: {=+XLOOKUP(B38,'Base de datos'!A:A,'Base de datos'!H:H,0)} -> 2.15 | F38: 0.09 | G38: 0.09 | H38: =IFERROR(1-G38/F38,"") -> 0 | I38: =IFERROR(E38*F38,"") -> 0.1935 | K38: Coste de Producto | L38: =L34/L36*100 -> 26.814056 | M38: %
B39: {=+XLOOKUP(C39,'Base de datos'!C:C,'Base de datos'!A:A,"",FALSE)} -> 29 | C39: ENVASE SERRANO IP10 .25 | D39: Unidad | E39: {=+XLOOKUP(B39,'Base de datos'!A:A,'Base de datos'!H:H,0)} -> 0.1946 | F39: 1 | G39: 1 | H39: =IFERROR(1-G39/F39,"") -> 0 | I39: =IFERROR(E39*F39,"") -> 0.1946 | K39: Margen Bruto | L39: =100-L38 -> 73.185944 | M39: %
B40: {=+XLOOKUP(C40,'Base de datos'!C:C,'Base de datos'!A:A,"",FALSE)} -> 93 | C40: SERVILLETA 40X40 100UD | D40: Unidad | E40: {=+XLOOKUP(B40,'Base de datos'!A:A,'Base de datos'!H:H,0)} -> 0.0277 | F40: 2 | G40: 2 | H40: =IFERROR(1-G40/F40,"") -> 0 | I40: =IFERROR(E40*F40,"") -> 0.0554
B41: {=+XLOOKUP(C41,'Base de datos'!C:C,'Base de datos'!A:A,"",FALSE)} | D41: Kg | E41: {=+XLOOKUP(B41,'Base de datos'!A:A,'Base de datos'!H:H,0)} -> 0 | I41: =IFERROR(E41*F41,"") -> 0
C44: PRODUCTO | D44: SIMPLE SOLOMILLO
B47: ID | C47: Nombre del Plato | D47: Unidad de medida | E47: Precio Unidad | F47: Cantidad Bruta | G47: Cantidad Cocinada/limpia | H47: Merma % | I47: Coste | K47: INDICE | N47: RESUMEN
B48: {=+XLOOKUP(C48,'Base de datos'!C:C,'Base de datos'!A:A,"",FALSE)} | D48: Kg | E48: {=+XLOOKUP(B48,'Base de datos'!A:A,'Base de datos'!H:H,0)} -> 0 | H48: =IFERROR(1-G48/F48,"") | I48: =IFERROR(E48*F48,"") -> 0 | K48: Coste Total | L48: =SUM(I48:I56) -> 1.2743182
B49: ='SIMPLE DE SOLOMILLO '!K25 -> #REF! | C49: ='SIMPLE DE SOLOMILLO '!C25 -> #REF! | D49: Kg | E49: ='SIMPLE DE SOLOMILLO '!K31 -> #REF! | H49: =IFERROR(1-G49/F49,"") | I49: =IFERROR(E49*F49,"") | K49: PVP | L49: 5
B50: {=+XLOOKUP(C50,'Base de datos'!C:C,'Base de datos'!A:A,"",FALSE)} -> 116 | C50: SOLOMILLO CERDO | D50: Kg | E50: {=+XLOOKUP(B50,'Base de datos'!A:A,'Base de datos'!H:H,0)} -> 5.49 | F50: 0.1 | H50: =IFERROR(1-G50/F50,"") -> 1 | I50: =IFERROR(E50*F50,"") -> 0.549 | K50: Precio venta (s/IVA) | L50: =L49/1.1 -> 4.5454545
B51: {=+XLOOKUP(C51,'Base de datos'!C:C,'Base de datos'!A:A,"",FALSE)} -> 110 | C51: PAN BAGUETTE LA PARRA | D51: Unidad | E51: {=+XLOOKUP(B51,'Base de datos'!A:A,'Base de datos'!H:H,0)} -> 0.28181818 | F51: 1 | H51: =IFERROR(1-G51/F51,"") -> 1 | I51: =IFERROR(E51*F51,"") -> 0.28181818 | K51: IVA | L51: 0.1
B52: {=+XLOOKUP(C52,'Base de datos'!C:C,'Base de datos'!A:A,"",FALSE)} -> 58 | C52: PATATAS FRY & DIP 25 | D52: Kg | E52: {=+XLOOKUP(B52,'Base de datos'!A:A,'Base de datos'!H:H,0)} -> 2.15 | F52: 0.09 | H52: =IFERROR(1-G52/F52,"") -> 1 | I52: =IFERROR(E52*F52,"") -> 0.1935 | K52: Coste de Producto | L52: =L48/L50*100 -> 28.035 | M52: %
B53: {=+XLOOKUP(C53,'Base de datos'!C:C,'Base de datos'!A:A,"",FALSE)} -> 29 | C53: ENVASE SERRANO IP10 .25 | D53: Unidad | E53: {=+XLOOKUP(B53,'Base de datos'!A:A,'Base de datos'!H:H,0)} -> 0.1946 | F53: 1 | H53: =IFERROR(1-G53/F53,"") -> 1 | I53: =IFERROR(E53*F53,"") -> 0.1946 | K53: Margen Bruto | L53: =100-L52 -> 71.965 | M53: %
B54: {=+XLOOKUP(C54,'Base de datos'!C:C,'Base de datos'!A:A,"",FALSE)} -> 93 | C54: SERVILLETA 40X40 100UD | D54: Unidad | E54: {=+XLOOKUP(B54,'Base de datos'!A:A,'Base de datos'!H:H,0)} -> 0.0277 | F54: 2 | H54: =IFERROR(1-G54/F54,"") -> 1 | I54: =IFERROR(E54*F54,"") -> 0.0554
B55: {=+XLOOKUP(C55,'Base de datos'!C:C,'Base de datos'!A:A,"",FALSE)} | D55: Kg | E55: {=+XLOOKUP(B55,'Base de datos'!A:A,'Base de datos'!H:H,0)} -> 0 | I55: =IFERROR(E55*F55,"") -> 0
B56: {=+XLOOKUP(C56,'Base de datos'!C:C,'Base de datos'!A:A,"",FALSE)} | D56: Kg | E56: {=+XLOOKUP(B56,'Base de datos'!A:A,'Base de datos'!H:H,0)} -> 0 | I56: =IFERROR(E56*F56,"") -> 0
C59: PRODUCTO | D59: VEGETAL POLLO
B62: ID | C62: Nombre del Plato | D62: Unidad de medida | E62: Precio Unidad | F62: Cantidad Bruta | G62: Cantidad Cocinada/limpia | H62: Merma % | I62: Coste | K62: INDICE | N62: RESUMEN
B63: {=+XLOOKUP(C63,'Base de datos'!C:C,'Base de datos'!A:A,"",FALSE)} | D63: Kg | E63: {=+XLOOKUP(B63,'Base de datos'!A:A,'Base de datos'!H:H,0)} -> 0 | H63: =IFERROR(1-G63/F63,"") | I63: =IFERROR(E63*F63,"") -> 0 | K63: Coste Total | L63: =SUM(I63:I72) -> 1.3687182
B64: ='VEGENTAL POLLO '!K29 -> #REF! | C64: ='VEGENTAL POLLO '!C29 -> #REF! | D64: Kg | E64: ='VEGENTAL POLLO '!K35 -> #REF! | H64: =IFERROR(1-G64/F64,"") | I64: =IFERROR(E64*F64,"") | K64: PVP | L64: 5
B65: {=+XLOOKUP(C65,'Base de datos'!C:C,'Base de datos'!A:A,"",FALSE)} -> 63 | C65: PECHUGA POLLO FILETEADA 25 SADA | D65: Kg | E65: {=+XLOOKUP(B65,'Base de datos'!A:A,'Base de datos'!H:H,0)} -> 6.15 | F65: 0.1 | H65: =IFERROR(1-G65/F65,"") -> 1 | I65: =IFERROR(E65*F65,"") -> 0.615 | K65: Precio venta (s/IVA) | L65: =L64/1.1 -> 4.5454545
B66: {=+XLOOKUP(C66,'Base de datos'!C:C,'Base de datos'!A:A,"",FALSE)} -> 110 | C66: PAN BAGUETTE LA PARRA | D66: Unidad | E66: {=+XLOOKUP(B66,'Base de datos'!A:A,'Base de datos'!H:H,0)} -> 0.28181818 | F66: 1 | H66: =IFERROR(1-G66/F66,"") -> 1 | I66: =IFERROR(E66*F66,"") -> 0.28181818 | K66: IVA | L66: 0.1
B67: {=+XLOOKUP(C67,'Base de datos'!C:C,'Base de datos'!A:A,"",FALSE)} -> 58 | C67: PATATAS FRY & DIP 25 | D67: Kg | E67: {=+XLOOKUP(B67,'Base de datos'!A:A,'Base de datos'!H:H,0)} -> 2.15 | F67: 0.09 | H67: =IFERROR(1-G67/F67,"") -> 1 | I67: =IFERROR(E67*F67,"") -> 0.1935 | K67: Coste de Producto | L67: =L63/L65*100 -> 30.1118 | M67: %
B68: {=+XLOOKUP(C68,'Base de datos'!C:C,'Base de datos'!A:A,"",FALSE)} -> 29 | C68: ENVASE SERRANO IP10 .25 | D68: Unidad | E68: {=+XLOOKUP(B68,'Base de datos'!A:A,'Base de datos'!H:H,0)} -> 0.1946 | F68: 1 | H68: =IFERROR(1-G68/F68,"") -> 1 | I68: =IFERROR(E68*F68,"") -> 0.1946 | K68: Margen Bruto | L68: =100-L67 -> 69.8882 | M68: %
B69: {=+XLOOKUP(C69,'Base de datos'!C:C,'Base de datos'!A:A,"",FALSE)} -> 93 | C69: SERVILLETA 40X40 100UD | D69: Unidad | E69: {=+XLOOKUP(B69,'Base de datos'!A:A,'Base de datos'!H:H,0)} -> 0.0277 | F69: 2 | H69: =IFERROR(1-G69/F69,"") -> 1 | I69: =IFERROR(E69*F69,"") -> 0.0554
B70: {=+XLOOKUP(C70,'Base de datos'!C:C,'Base de datos'!A:A,"",FALSE)} -> 96 | C70: TOMATE DANIELA | D70: Kg | E70: {=+XLOOKUP(B70,'Base de datos'!A:A,'Base de datos'!H:H,0)} -> 1.8 | F70: 0.01 | I70: =IFERROR(E70*F70,"") -> 0.018
B71: {=+XLOOKUP(C71,'Base de datos'!C:C,'Base de datos'!A:A,"",FALSE)} -> 39 | C71: LECHUGA LOLLO CUEVAS | D71: Kg | E71: {=+XLOOKUP(B71,'Base de datos'!A:A,'Base de datos'!H:H,0)} -> 1.04 | F71: 0.01 | I71: =IFERROR(E71*F71,"") -> 0.0104
B72: {=+XLOOKUP(C72,'Base de datos'!C:C,'Base de datos'!A:A,"",FALSE)} | D72: Kg | E72: {=+XLOOKUP(B72,'Base de datos'!A:A,'Base de datos'!H:H,0)} -> 0 | I72: =IFERROR(E72*F72,"") -> 0
C75: PRODUCTO | D75: VEGETAL ATUN
B78: ID | C78: Nombre del Plato | D78: Unidad de medida | E78: Precio Unidad | F78: Cantidad Bruta | G78: Cantidad Cocinada/limpia | H78: Merma % | I78: Coste | K78: INDICE | N78: RESUMEN
B79: {=+XLOOKUP(C79,'Base de datos'!C:C,'Base de datos'!A:A,"",FALSE)} | D79: Kg | E79: {=+XLOOKUP(B79,'Base de datos'!A:A,'Base de datos'!H:H,0)} -> 0 | H79: =IFERROR(1-G79/F79,"") | I79: =IFERROR(E79*F79,"") -> 0 | K79: Coste Total | L79: =SUM(I79:I88) -> 1.3287182
B80: ='VEGENTAL ATUN'!K29 -> #REF! | C80: ='VEGENTAL ATUN'!C29 -> #REF! | D80: Kg | E80: ='VEGENTAL ATUN'!K35 -> #REF! | H80: =IFERROR(1-G80/F80,"") | I80: =IFERROR(E80*F80,"") | K80: PVP | L80: 5
B81: {=+XLOOKUP(C81,'Base de datos'!C:C,'Base de datos'!A:A,"",FALSE)} -> 3 | C81: ATUN EN ACEITE VEGETAL | D81: Kg | E81: {=+XLOOKUP(B81,'Base de datos'!A:A,'Base de datos'!H:H,0)} -> 5.75 | F81: 0.1 | H81: =IFERROR(1-G81/F81,"") -> 1 | I81: =IFERROR(E81*F81,"") -> 0.575 | K81: Precio venta (s/IVA) | L81: =L80/1.1 -> 4.5454545
B82: {=+XLOOKUP(C82,'Base de datos'!C:C,'Base de datos'!A:A,"",FALSE)} -> 110 | C82: PAN BAGUETTE LA PARRA | D82: Unidad | E82: {=+XLOOKUP(B82,'Base de datos'!A:A,'Base de datos'!H:H,0)} -> 0.28181818 | F82: 1 | H82: =IFERROR(1-G82/F82,"") -> 1 | I82: =IFERROR(E82*F82,"") -> 0.28181818 | K82: IVA | L82: 0.1
B83: {=+XLOOKUP(C83,'Base de datos'!C:C,'Base de datos'!A:A,"",FALSE)} -> 58 | C83: PATATAS FRY & DIP 25 | D83: Kg | E83: {=+XLOOKUP(B83,'Base de datos'!A:A,'Base de datos'!H:H,0)} -> 2.15 | F83: 0.09 | H83: =IFERROR(1-G83/F83,"") -> 1 | I83: =IFERROR(E83*F83,"") -> 0.1935 | K83: Coste de Producto | L83: =L79/L81*100 -> 29.2318 | M83: %
B84: {=+XLOOKUP(C84,'Base de datos'!C:C,'Base de datos'!A:A,"",FALSE)} -> 29 | C84: ENVASE SERRANO IP10 .25 | D84: Unidad | E84: {=+XLOOKUP(B84,'Base de datos'!A:A,'Base de datos'!H:H,0)} -> 0.1946 | F84: 1 | H84: =IFERROR(1-G84/F84,"") -> 1 | I84: =IFERROR(E84*F84,"") -> 0.1946 | K84: Margen Bruto | L84: =100-L83 -> 70.7682 | M84: %
B85: {=+XLOOKUP(C85,'Base de datos'!C:C,'Base de datos'!A:A,"",FALSE)} -> 93 | C85: SERVILLETA 40X40 100UD | D85: Unidad | E85: {=+XLOOKUP(B85,'Base de datos'!A:A,'Base de datos'!H:H,0)} -> 0.0277 | F85: 2 | H85: =IFERROR(1-G85/F85,"") -> 1 | I85: =IFERROR(E85*F85,"") -> 0.0554
B86: {=+XLOOKUP(C86,'Base de datos'!C:C,'Base de datos'!A:A,"",FALSE)} -> 96 | C86: TOMATE DANIELA | D86: Kg | E86: {=+XLOOKUP(B86,'Base de datos'!A:A,'Base de datos'!H:H,0)} -> 1.8 | F86: 0.01 | I86: =IFERROR(E86*F86,"") -> 0.018
B87: {=+XLOOKUP(C87,'Base de datos'!C:C,'Base de datos'!A:A,"",FALSE)} -> 39 | C87: LECHUGA LOLLO CUEVAS | D87: Kg | E87: {=+XLOOKUP(B87,'Base de datos'!A:A,'Base de datos'!H:H,0)} -> 1.04 | F87: 0.01 | I87: =IFERROR(E87*F87,"") -> 0.0104
B88: {=+XLOOKUP(C88,'Base de datos'!C:C,'Base de datos'!A:A,"",FALSE)} | D88: Kg | E88: {=+XLOOKUP(B88,'Base de datos'!A:A,'Base de datos'!H:H,0)} -> 0 | I88: =IFERROR(E88*F88,"") -> 0
C91: PRODUCTO | D91: VEGETAL POLLO ASADO
B94: ID | C94: Nombre del Plato | D94: Unidad de medida | E94: Precio Unidad | F94: Cantidad Bruta | G94: Cantidad Cocinada/limpia | H94: Merma % | I94: Coste | K94: INDICE | L94: RESUMEN | O94: INDICE UBER
B95: {=+XLOOKUP(C95,'Base de datos'!C:C,'Base de datos'!A:A,"",FALSE)} | D95: Kg | E95: {=+XLOOKUP(B95,'Base de datos'!A:A,'Base de datos'!H:H,0)} -> 0 | H95: =IFERROR(1-G95/F95,"") | I95: =IFERROR(E95*F95,"") -> 0 | K95: Coste Total | L95: =SUM(I95:I106) -> 1.3691028 | O95: Coste Total | P95: =L95 -> 1.3691028
B96: ='VEGETAL ASADO'!K29 -> #REF! | C96: ='VEGETAL ASADO'!C29 -> #REF! | D96: Kg | E96: ='VEGETAL ASADO'!K35 -> #REF! | H96: =IFERROR(1-G96/F96,"") | I96: =IFERROR(E96*F96,"") | K96: PVP | L96: 6.5 | O96: PVP | P96: 6.9
B97: {=+XLOOKUP(C97,'Base de datos'!C:C,'Base de datos'!A:A,"",FALSE)} -> 74 | C97: POLLO ASADO | D97: Kg | E97: {=+XLOOKUP(B97,'Base de datos'!A:A,'Base de datos'!H:H,0)} -> 6.1538462 | F97: 0.1 | H97: =IFERROR(1-G97/F97,"") -> 1 | I97: =IFERROR(E97*F97,"") -> 0.61538462 | K97: Precio venta (s/IVA) | L97: =L96/1.1 -> 5.9090909 | O97: Precio venta (s/IVA) | P97: =P96/1.1 -> 6.2727273
B98: {=+XLOOKUP(C98,'Base de datos'!C:C,'Base de datos'!A:A,"",FALSE)} -> 110 | C98: PAN BAGUETTE LA PARRA | D98: Unidad | E98: {=+XLOOKUP(B98,'Base de datos'!A:A,'Base de datos'!H:H,0)} -> 0.28181818 | F98: 1 | H98: =IFERROR(1-G98/F98,"") -> 1 | I98: =IFERROR(E98*F98,"") -> 0.28181818 | K98: IVA | L98: 0.1 | O98: IVA | P98: 0.1
B99: {=+XLOOKUP(C99,'Base de datos'!C:C,'Base de datos'!A:A,"",FALSE)} -> 58 | C99: PATATAS FRY & DIP 25 | D99: Kg | E99: {=+XLOOKUP(B99,'Base de datos'!A:A,'Base de datos'!H:H,0)} -> 2.15 | F99: 0.09 | H99: =IFERROR(1-G99/F99,"") -> 1 | I99: =IFERROR(E99*F99,"") -> 0.1935 | K99: Coste de Producto | L99: =L95/L97*100 -> 23.169432 | M99: % | O99: Coste de Producto | P99: =P95/P97*100 -> 21.826276 | Q99: %
B100: {=+XLOOKUP(C100,'Base de datos'!C:C,'Base de datos'!A:A,"",FALSE)} -> 29 | C100: ENVASE SERRANO IP10 .25 | D100: Unidad | E100: {=+XLOOKUP(B100,'Base de datos'!A:A,'Base de datos'!H:H,0)} -> 0.1946 | F100: 1 | H100: =IFERROR(1-G100/F100,"") -> 1 | I100: =IFERROR(E100*F100,"") -> 0.1946 | K100: Margen Bruto | L100: =100-L99 -> 76.830568 | M100: % | O100: Margen Bruto | P100: =P97-P95 -> 4.9036245 | Q100: €
B101: {=+XLOOKUP(C101,'Base de datos'!C:C,'Base de datos'!A:A,"",FALSE)} -> 93 | C101: SERVILLETA 40X40 100UD | D101: Unidad | E101: {=+XLOOKUP(B101,'Base de datos'!A:A,'Base de datos'!H:H,0)} -> 0.0277 | F101: 2 | H101: =IFERROR(1-G101/F101,"") -> 1 | I101: =IFERROR(E101*F101,"") -> 0.0554 | O101: Margen Bruto post Uber | P101: =P97-P95-(P96*0.2) -> 3.5236245 | Q101: €
B102: {=+XLOOKUP(C102,'Base de datos'!C:C,'Base de datos'!A:A,"",FALSE)} -> 96 | C102: TOMATE DANIELA | D102: Kg | E102: {=+XLOOKUP(B102,'Base de datos'!A:A,'Base de datos'!H:H,0)} -> 1.8 | F102: 0.01 | I102: =IFERROR(E102*F102,"") -> 0.018 | O102: Margen Bruto post Uber | P102: =P101/P97 -> 0.56173724 | Q102: %
B103: {=+XLOOKUP(C103,'Base de datos'!C:C,'Base de datos'!A:A,"",FALSE)} -> 39 | C103: LECHUGA LOLLO CUEVAS | D103: Kg | E103: {=+XLOOKUP(B103,'Base de datos'!A:A,'Base de datos'!H:H,0)} -> 1.04 | F103: 0.01 | I103: =IFERROR(E103*F103,"") -> 0.0104
B104: {=+XLOOKUP(C104,'Base de datos'!C:C,'Base de datos'!A:A,"",FALSE)} | D104: Kg | E104: {=+XLOOKUP(B104,'Base de datos'!A:A,'Base de datos'!H:H,0)} -> 0 | I104: =IFERROR(E104*F104,"") -> 0
B105: {=+XLOOKUP(C105,'Base de datos'!C:C,'Base de datos'!A:A,"",FALSE)} | D105: Kg | E105: {=+XLOOKUP(B105,'Base de datos'!A:A,'Base de datos'!H:H,0)} -> 0 | I105: =IFERROR(E105*F105,"") -> 0
B106: {=+XLOOKUP(C106,'Base de datos'!C:C,'Base de datos'!A:A,"",FALSE)} | D106: Kg | E106: {=+XLOOKUP(B106,'Base de datos'!A:A,'Base de datos'!H:H,0)} -> 0 | H106: =IFERROR(1-G106/F106,"") | I106: =IFERROR(E106*F106,"") -> 0
C109: PRODUCTO | D109: VEGETAL EMPANADO
B112: ID | C112: Nombre del Plato | D112: Unidad de medida | E112: Precio Unidad | F112: Cantidad Bruta | G112: Cantidad Cocinada/limpia | H112: Merma % | I112: Coste | K112: INDICE | O112: INDICE UBER
B113: {=+XLOOKUP(C113,'Base de datos'!C:C,'Base de datos'!A:A,"",FALSE)} | D113: Kg | E113: {=+XLOOKUP(B113,'Base de datos'!A:A,'Base de datos'!H:H,0)} -> 0 | H113: =IFERROR(1-G113/F113,"") | I113: =IFERROR(E113*F113,"") -> 0 | K113: Coste Total | L113: =SUM(I113:I124) -> 1.3137182 | O113: Coste Total | P113: =L113 -> 1.3137182
B114: ='VEGETAL EMPANADO'!K29 -> #REF! | C114: ='VEGETAL EMPANADO'!C29 -> #REF! | D114: Kg | E114: ='VEGETAL EMPANADO'!K35 -> #REF! | H114: =IFERROR(1-G114/F114,"") | I114: =IFERROR(E114*F114,"") | K114: PVP | L114: 5 | O114: PVP | P114: 7
B115: {=+XLOOKUP(C115,'Base de datos'!C:C,'Base de datos'!A:A,"",FALSE)} -> 62 | C115: PECHUGA EMPANADA 25 | D115: Kg | E115: {=+XLOOKUP(B115,'Base de datos'!A:A,'Base de datos'!H:H,0)} -> 5.6 | F115: 0.1 | H115: =IFERROR(1-G115/F115,"") -> 1 | I115: =IFERROR(E115*F115,"") -> 0.56 | K115: Precio venta (s/IVA) | L115: =L114/1.1 -> 4.5454545 | O115: Precio venta (s/IVA) | P115: =P114/1.1 -> 6.3636364
B116: {=+XLOOKUP(C116,'Base de datos'!C:C,'Base de datos'!A:A,"",FALSE)} -> 110 | C116: PAN BAGUETTE LA PARRA | D116: Unidad | E116: {=+XLOOKUP(B116,'Base de datos'!A:A,'Base de datos'!H:H,0)} -> 0.28181818 | F116: 1 | H116: =IFERROR(1-G116/F116,"") -> 1 | I116: =IFERROR(E116*F116,"") -> 0.28181818 | K116: IVA | L116: 0.1 | O116: IVA | P116: 0.1
B117: {=+XLOOKUP(C117,'Base de datos'!C:C,'Base de datos'!A:A,"",FALSE)} -> 58 | C117: PATATAS FRY & DIP 25 | D117: Kg | E117: {=+XLOOKUP(B117,'Base de datos'!A:A,'Base de datos'!H:H,0)} -> 2.15 | F117: 0.09 | H117: =IFERROR(1-G117/F117,"") -> 1 | I117: =IFERROR(E117*F117,"") -> 0.1935 | K117: Coste de Producto | L117: =L113/L115*100 -> 28.9018 | M117: % | O117: Coste de Producto | P117: =P113/P115*100 -> 20.644143 | Q117: %
B118: {=+XLOOKUP(C118,'Base de datos'!C:C,'Base de datos'!A:A,"",FALSE)} -> 29 | C118: ENVASE SERRANO IP10 .25 | D118: Unidad | E118: {=+XLOOKUP(B118,'Base de datos'!A:A,'Base de datos'!H:H,0)} -> 0.1946 | F118: 1 | H118: =IFERROR(1-G118/F118,"") -> 1 | I118: =IFERROR(E118*F118,"") -> 0.1946 | K118: Margen Bruto | L118: =100-L117 -> 71.0982 | M118: % | O118: Margen Bruto | P118: =P115-P113 -> 5.0499182 | Q118: €
B119: {=+XLOOKUP(C119,'Base de datos'!C:C,'Base de datos'!A:A,"",FALSE)} -> 93 | C119: SERVILLETA 40X40 100UD | D119: Unidad | E119: {=+XLOOKUP(B119,'Base de datos'!A:A,'Base de datos'!H:H,0)} -> 0.0277 | F119: 2 | H119: =IFERROR(1-G119/F119,"") -> 1 | I119: =IFERROR(E119*F119,"") -> 0.0554 | O119: Margen Bruto post Uber | P119: =P115-P113-(P114*0.2) -> 3.6499182 | Q119: €
B120: {=+XLOOKUP(C120,'Base de datos'!C:C,'Base de datos'!A:A,"",FALSE)} -> 96 | C120: TOMATE DANIELA | D120: Kg | E120: {=+XLOOKUP(B120,'Base de datos'!A:A,'Base de datos'!H:H,0)} -> 1.8 | F120: 0.01 | I120: =IFERROR(E120*F120,"") -> 0.018 | O120: Margen Bruto post Uber | P120: =P119/P115 -> 0.57355857 | Q120: %
B121: {=+XLOOKUP(C121,'Base de datos'!C:C,'Base de datos'!A:A,"",FALSE)} -> 39 | C121: LECHUGA LOLLO CUEVAS | D121: Kg | E121: {=+XLOOKUP(B121,'Base de datos'!A:A,'Base de datos'!H:H,0)} -> 1.04 | F121: 0.01 | I121: =IFERROR(E121*F121,"") -> 0.0104
B122: {=+XLOOKUP(C122,'Base de datos'!C:C,'Base de datos'!A:A,"",FALSE)} | D122: Kg | E122: {=+XLOOKUP(B122,'Base de datos'!A:A,'Base de datos'!H:H,0)} -> 0 | I122: =IFERROR(E122*F122,"") -> 0
B123: {=+XLOOKUP(C123,'Base de datos'!C:C,'Base de datos'!A:A,"",FALSE)} | D123: Kg | E123: {=+XLOOKUP(B123,'Base de datos'!A:A,'Base de datos'!H:H,0)} -> 0 | I123: =IFERROR(E123*F123,"") -> 0
B124: {=+XLOOKUP(C124,'Base de datos'!C:C,'Base de datos'!A:A,"",FALSE)} | D124: Kg | E124: {=+XLOOKUP(B124,'Base de datos'!A:A,'Base de datos'!H:H,0)} -> 0 | H124: =IFERROR(1-G124/F124,"") | I124: =IFERROR(E124*F124,"") -> 0
C127: PRODUCTO | D127: BARBARA
B130: ID | C130: Nombre del Plato | D130: Unidad de medida | E130: Precio Unidad | F130: Cantidad Bruta | G130: Cantidad Cocinada/limpia | H130: Merma % | I130: Coste | K130: INDICE
B131: {=+XLOOKUP(C131,'Base de datos'!C:C,'Base de datos'!A:A,"",FALSE)} | D131: Kg | E131: {=+XLOOKUP(B131,'Base de datos'!A:A,'Base de datos'!H:H,0)} -> 0 | H131: =IFERROR(1-G131/F131,"") | I131: =IFERROR(E131*F131,"") -> 0 | K131: Coste Total | L131: =SUM(I131:I139) -> 1.7153182
B132: =BARBARA!K29 -> #REF! | C132: =BARBARA!C29 -> #REF! | D132: Kg | E132: =BARBARA!K35 -> #REF! | H132: =IFERROR(1-G132/F132,"") | I132: =IFERROR(E132*F132,"") | K132: PVP | L132: 5
B133: {=+XLOOKUP(C133,'Base de datos'!C:C,'Base de datos'!A:A,"",FALSE)} -> 63 | C133: PECHUGA POLLO FILETEADA 25 SADA | D133: Kg | E133: {=+XLOOKUP(B133,'Base de datos'!A:A,'Base de datos'!H:H,0)} -> 6.15 | F133: 0.1 | H133: =IFERROR(1-G133/F133,"") -> 1 | I133: =IFERROR(E133*F133,"") -> 0.615 | K133: Precio venta (s/IVA) | L133: =L132/1.1 -> 4.5454545
B134: {=+XLOOKUP(C134,'Base de datos'!C:C,'Base de datos'!A:A,"",FALSE)} -> 110 | C134: PAN BAGUETTE LA PARRA | D134: Unidad | E134: {=+XLOOKUP(B134,'Base de datos'!A:A,'Base de datos'!H:H,0)} -> 0.28181818 | F134: 1 | H134: =IFERROR(1-G134/F134,"") -> 1 | I134: =IFERROR(E134*F134,"") -> 0.28181818 | K134: IVA | L134: 0.1
B135: {=+XLOOKUP(C135,'Base de datos'!C:C,'Base de datos'!A:A,"",FALSE)} -> 58 | C135: PATATAS FRY & DIP 25 | D135: Kg | E135: {=+XLOOKUP(B135,'Base de datos'!A:A,'Base de datos'!H:H,0)} -> 2.15 | F135: 0.09 | H135: =IFERROR(1-G135/F135,"") -> 1 | I135: =IFERROR(E135*F135,"") -> 0.1935 | K135: Coste de Producto | L135: =L131/L133*100 -> 37.737 | M135: %
...

Sheet BRIOCH-SUBS
C2: PRODUCTO | D2: CHICKEN FRIED
B5: ID | C5: Nombre del Plato | D5: Unidad de medida | E5: Precio Unidad | F5: Cantidad Bruta | G5: Cantidad Cocinada/limpia | H5: Merma % | I5: Coste | K5: INDICE
B6: {=+XLOOKUP(C6,'Base de datos'!C:C,'Base de datos'!A:A,"",FALSE)} | D6: Kg | E6: {=+XLOOKUP(B6,'Base de datos'!A:A,'Base de datos'!H:H,0)} -> 0 | H6: =IFERROR(1-G6/F6,"") | I6: =IFERROR(E6*F6,"") -> 0 | K6: Coste Total | L6: =SUM(I6:I17) -> 1.9732002
B7: =K30 | C7: =C30 | D7: Kg | E7: =K36 -> PVP | H7: =IFERROR(1-G7/F7,"") | I7: =IFERROR(E7*F7,"") | K7: PVP | L7: 8
B8: {=+XLOOKUP(C8,'Base de datos'!C:C,'Base de datos'!A:A,"",FALSE)} -> 77 | C8: POLLO CRISPY SIMON(CRUJIPOLLO) | D8: Kg | E8: {=+XLOOKUP(B8,'Base de datos'!A:A,'Base de datos'!H:H,0)} -> 6 | F8: 0.125 | G8: 0.12 | H8: =IFERROR(1-G8/F8,"") -> 0.04 | I8: =IFERROR(E8*F8,"") -> 0.75 | K8: Precio venta (s/IVA) | L8: =L7/1.1 -> 7.2727273
B9: {=+XLOOKUP(C9,'Base de datos'!C:C,'Base de datos'!A:A,"",FALSE)} -> 47 | C9: PAN BRIOCHE PERRITO | D9: Unidad | E9: {=+XLOOKUP(B9,'Base de datos'!A:A,'Base de datos'!H:H,0)} -> 0.5605 | F9: 1 | G9: 1 | H9: =IFERROR(1-G9/F9,"") -> 0 | I9: =IFERROR(E9*F9,"") -> 0.5605 | K9: IVA | L9: 0.1
B10: {=+XLOOKUP(C10,'Base de datos'!C:C,'Base de datos'!A:A,"",FALSE)} -> 67 | C10: PEPINILLOS | D10: Kg | E10: {=+XLOOKUP(B10,'Base de datos'!A:A,'Base de datos'!H:H,0)} -> 6.0473684 | F10: 0.005 | G10: 0.005 | H10: =IFERROR(1-G10/F10,"") -> 0 | I10: =IFERROR(E10*F10,"") -> 0.030236842 | K10: Coste de Producto | L10: =L6/L8*100 -> 27.131502 | M10: %
B11: {=+XLOOKUP(C11,'Base de datos'!C:C,'Base de datos'!A:A,"",FALSE)} -> 4 | C11: BACON LONCHEADO 25 | D11: Kg | E11: {=+XLOOKUP(B11,'Base de datos'!A:A,'Base de datos'!H:H,0)} -> 4.8165 | F11: 0.02 | G11: 0.02 | H11: =IFERROR(1-G11/F11,"") -> 0 | I11: =IFERROR(E11*F11,"") -> 0.09633 | K11: Margen Bruto | L11: =100-L10 -> 72.868498 | M11: %
B12: {=+XLOOKUP(C12,'Base de datos'!C:C,'Base de datos'!A:A,"",FALSE)} -> 20 | C12: CHEDDAR LIQUIDO SOLLERO | D12: Kg | E12: {=+XLOOKUP(B12,'Base de datos'!A:A,'Base de datos'!H:H,0)} -> 6.0166667 | F12: 0.02 | G12: 0.01 | H12: =IFERROR(1-G12/F12,"") -> 0.5 | I12: =IFERROR(E12*F12,"") -> 0.12033333
B13: {=+XLOOKUP(C13,'Base de datos'!C:C,'Base de datos'!A:A,"",FALSE)} | D13: Kg | E13: {=+XLOOKUP(B13,'Base de datos'!A:A,'Base de datos'!H:H,0)} -> 0 | F13: 0.01 | G13: 0.01 | H13: =IFERROR(1-G13/F13,"") -> 0 | I13: =IFERROR(E13*F13,"") -> 0 | K13: INDICE UBER
B14: {=+XLOOKUP(C14,'Base de datos'!C:C,'Base de datos'!A:A,"",FALSE)} | D14: Kg | E14: {=+XLOOKUP(B14,'Base de datos'!A:A,'Base de datos'!H:H,0)} -> 0 | F14: 0.012 | G14: 0.012 | H14: =IFERROR(1-G14/F14,"") -> 0 | I14: =IFERROR(E14*F14,"") -> 0 | K14: Coste Total | L14: =L6 -> 1.9732002
B15: {=+XLOOKUP(C15,'Base de datos'!C:C,'Base de datos'!A:A,"",FALSE)} -> 93 | C15: SERVILLETA 40X40 100UD | D15: Unidad | E15: {=+XLOOKUP(B15,'Base de datos'!A:A,'Base de datos'!H:H,0)} -> 0.0277 | F15: 1 | G15: 1 | H15: =IFERROR(1-G15/F15,"") -> 0 | I15: =IFERROR(E15*F15,"") -> 0.0277 | K15: PVP | L15: 8.5
B16: {=+XLOOKUP(C16,'Base de datos'!C:C,'Base de datos'!A:A,"",FALSE)} -> 29 | C16: ENVASE SERRANO IP10 .25 | D16: Unidad | E16: {=+XLOOKUP(B16,'Base de datos'!A:A,'Base de datos'!H:H,0)} -> 0.1946 | F16: 1 | G16: 1 | H16: =IFERROR(1-G16/F16,"") -> 0 | I16: =IFERROR(E16*F16,"") -> 0.1946 | K16: Precio venta (s/IVA) | L16: =L15/1.1 -> 7.7272727
B17: {=+XLOOKUP(C17,'Base de datos'!C:C,'Base de datos'!A:A,"",FALSE)} -> 58 | C17: PATATAS FRY & DIP 25 | D17: Kg | E17: {=+XLOOKUP(B17,'Base de datos'!A:A,'Base de datos'!H:H,0)} -> 2.15 | F17: 0.09 | H17: =IFERROR(1-G17/F17,"") -> 1 | I17: =IFERROR(E17*F17,"") -> 0.1935 | K17: IVA | L17: 0.1
B18: {=+XLOOKUP(C18,'Base de datos'!C:C,'Base de datos'!A:A,"",FALSE)} -> 69 | C18: Petaca patatas | D18: Unidad | E18: {=+XLOOKUP(B18,'Base de datos'!A:A,'Base de datos'!H:H,0)} -> 0.070541667 | F18: 1 | H18: =IFERROR(1-G18/F18,"") -> 1 | I18: =IFERROR(E18*F18,"") -> 0.070541667 | K18: Coste de Producto | L18: =L14/L16*100 -> 25.535532 | M18: %
K19: Margen Bruto | L19: =L16-L14 -> 5.7540726 | M19: €
C20: Notas de elaboración | K20: Margen Bruto post Uber | L20: =L16-L14-(L15*0.2) -> 4.0540726 | M20: €
K21: Margen Bruto post Uber | L21: =L20/L16 -> 0.52464468 | M21: %
C31: PRODUCTO | D31: PULLED BRIOCH / CHEESE STEACK
B34: ID | C34: Nombre del Plato | D34: Unidad de medida | E34: Precio Unidad | F34: Cantidad Bruta | G34: Cantidad Cocinada/limpia | H34: Merma % | I34: Coste | K34: INDICE
B35: {=+XLOOKUP(C35,'Base de datos'!C:C,'Base de datos'!A:A,"",FALSE)} | D35: Kg | E35: {=+XLOOKUP(B35,'Base de datos'!A:A,'Base de datos'!H:H,0)} -> 0 | H35: =IFERROR(1-G35/F35,"") | I35: =IFERROR(E35*F35,"") -> 0 | K35: Coste Total | L35: =SUM(I35:I46) -> 2.3676979
B36: ='CHEESE STEAK'!K30 -> #REF! | C36: ='CHEESE STEAK'!C30 -> #REF! | D36: Kg | E36: ='CHEESE STEAK'!K36 -> #REF! | H36: =IFERROR(1-G36/F36,"") | I36: =IFERROR(E36*F36,"") | K36: PVP | L36: 8
B37: {=+XLOOKUP(C37,'Base de datos'!C:C,'Base de datos'!A:A,"",FALSE)} -> 78 | C37: PULLED PORK | D37: Kg | E37: {=+XLOOKUP(B37,'Base de datos'!A:A,'Base de datos'!H:H,0)} -> 8.3215833 | F37: 0.125 | G37: 0.12 | H37: =IFERROR(1-G37/F37,"") -> 0.04 | I37: =IFERROR(E37*F37,"") -> 1.0401979 | K37: Precio venta (s/IVA) | L37: =L36/1.1 -> 7.2727273
B38: {=+XLOOKUP(C38,'Base de datos'!C:C,'Base de datos'!A:A,"",FALSE)} -> 47 | C38: PAN BRIOCHE PERRITO | D38: Unidad | E38: {=+XLOOKUP(B38,'Base de datos'!A:A,'Base de datos'!H:H,0)} -> 0.5605 | F38: 1 | G38: 1 | H38: =IFERROR(1-G38/F38,"") -> 0 | I38: =IFERROR(E38*F38,"") -> 0.5605 | K38: IVA | L38: 0.1
B39: {=+XLOOKUP(C39,'Base de datos'!C:C,'Base de datos'!A:A,"",FALSE)} | D39: Kg | E39: {=+XLOOKUP(B39,'Base de datos'!A:A,'Base de datos'!H:H,0)} -> 0 | F39: 0.005 | G39: 0.01 | H39: =IFERROR(1-G39/F39,"") -> -1 | I39: =IFERROR(E39*F39,"") -> 0 | K39: Coste de Producto | L39: =L35/L37*100 -> 32.555846 | M39: %
B40: {=+XLOOKUP(C40,'Base de datos'!C:C,'Base de datos'!A:A,"",FALSE)} | D40: Kg | E40: {=+XLOOKUP(B40,'Base de datos'!A:A,'Base de datos'!H:H,0)} -> 0 | F40: 0.02 | G40: 0.02 | H40: =IFERROR(1-G40/F40,"") -> 0 | I40: =IFERROR(E40*F40,"") -> 0 | K40: Margen Bruto | L40: =100-L39 -> 67.444154 | M40: %
B41: {=+XLOOKUP(C41,'Base de datos'!C:C,'Base de datos'!A:A,"",FALSE)} -> 23 | C41: CHEDDAR SALSA LA FUENTE | D41: Kg | E41: {=+XLOOKUP(B41,'Base de datos'!A:A,'Base de datos'!H:H,0)} -> 4.39 | F41: 0.08 | G41: 0.08 | H41: =IFERROR(1-G41/F41,"") -> 0 | I41: =IFERROR(E41*F41,"") -> 0.3512
B42: {=+XLOOKUP(C42,'Base de datos'!C:C,'Base de datos'!A:A,"",FALSE)} | D42: Kg | E42: {=+XLOOKUP(B42,'Base de datos'!A:A,'Base de datos'!H:H,0)} -> 0 | F42: 0.01 | G42: 0.01 | H42: =IFERROR(1-G42/F42,"") -> 0 | I42: =IFERROR(E42*F42,"") -> 0
B43: {=+XLOOKUP(C43,'Base de datos'!C:C,'Base de datos'!A:A,"",FALSE)} | D43: Kg | E43: {=+XLOOKUP(B43,'Base de datos'!A:A,'Base de datos'!H:H,0)} -> 0 | F43: 0.012 | G43: 0.012 | H43: =IFERROR(1-G43/F43,"") -> 0 | I43: =IFERROR(E43*F43,"") -> 0
B44: {=+XLOOKUP(C44,'Base de datos'!C:C,'Base de datos'!A:A,"",FALSE)} -> 93 | C44: SERVILLETA 40X40 100UD | D44: Unidad | E44: {=+XLOOKUP(B44,'Base de datos'!A:A,'Base de datos'!H:H,0)} -> 0.0277 | F44: 1 | G44: 1 | H44: =IFERROR(1-G44/F44,"") -> 0 | I44: =IFERROR(E44*F44,"") -> 0.0277
B45: {=+XLOOKUP(C45,'Base de datos'!C:C,'Base de datos'!A:A,"",FALSE)} -> 29 | C45: ENVASE SERRANO IP10 .25 | D45: Unidad | E45: {=+XLOOKUP(B45,'Base de datos'!A:A,'Base de datos'!H:H,0)} -> 0.1946 | F45: 1 | G45: 1 | H45: =IFERROR(1-G45/F45,"") -> 0 | I45: =IFERROR(E45*F45,"") -> 0.1946
B46: {=+XLOOKUP(C46,'Base de datos'!C:C,'Base de datos'!A:A,"",FALSE)} -> 58 | C46: PATATAS FRY & DIP 25 | D46: Kg | E46: {=+XLOOKUP(B46,'Base de datos'!A:A,'Base de datos'!H:H,0)} -> 2.15 | F46: 0.09 | H46: =IFERROR(1-G46/F46,"") -> 1 | I46: =IFERROR(E46*F46,"") -> 0.1935
B47: {=+XLOOKUP(C47,'Base de datos'!C:C,'Base de datos'!A:A,"",FALSE)} -> 69 | C47: Petaca patatas | D47: Unidad | E47: {=+XLOOKUP(B47,'Base de datos'!A:A,'Base de datos'!H:H,0)} -> 0.070541667 | F47: 1 | H47: =IFERROR(1-G47/F47,"") -> 1 | I47: =IFERROR(E47*F47,"") -> 0.070541667
C49: Notas de elaboración
C60: PRODUCTO | D60: GYPSI BRIOCHE
B63: ID | C63: Nombre del Plato | D63: Unidad de medida | E63: Precio Unidad | F63: Cantidad Bruta | G63: Cantidad Cocinada/limpia | H63: Merma % | I63: Coste | K63: INDICE
B64: {=+XLOOKUP(C64,'Base de datos'!C:C,'Base de datos'!A:A,"",FALSE)} | D64: Kg | E64: {=+XLOOKUP(B64,'Base de datos'!A:A,'Base de datos'!H:H,0)} -> 0 | H64: =IFERROR(1-G64/F64,"") | I64: =IFERROR(E64*F64,"") -> 0 | K64: Coste Total | L64: =SUM(I64:I75) -> 1.9596667
B65: =GYPSI!K30 -> #REF! | C65: =GYPSI!C30 -> #REF! | D65: Kg | E65: =GYPSI!K36 -> #REF! | H65: =IFERROR(1-G65/F65,"") | I65: =IFERROR(E65*F65,"") | K65: PVP | L65: 8
B66: {=+XLOOKUP(C66,'Base de datos'!C:C,'Base de datos'!A:A,"",FALSE)} -> 12 | C66: CARNE B. | D66: Kg | E66: {=+XLOOKUP(B66,'Base de datos'!A:A,'Base de datos'!H:H,0)} -> 8.1818182 | F66: 0.08 | H66: =IFERROR(1-G66/F66,"") -> 1 | I66: =IFERROR(E66*F66,"") -> 0.65454545 | K66: Precio venta (s/IVA) | L66: =L65/1.1 -> 7.2727273
B67: {=+XLOOKUP(C67,'Base de datos'!C:C,'Base de datos'!A:A,"",FALSE)} -> 47 | C67: PAN BRIOCHE PERRITO | D67: Unidad | E67: {=+XLOOKUP(B67,'Base de datos'!A:A,'Base de datos'!H:H,0)} -> 0.5605 | F67: 1 | G67: 1 | H67: =IFERROR(1-G67/F67,"") -> 0 | I67: =IFERROR(E67*F67,"") -> 0.5605 | K67: IVA | L67: 0.1
B68: {=+XLOOKUP(C68,'Base de datos'!C:C,'Base de datos'!A:A,"",FALSE)} -> 78 | C68: PULLED PORK | D68: Kg | E68: {=+XLOOKUP(B68,'Base de datos'!A:A,'Base de datos'!H:H,0)} -> 8.3215833 | F68: 0.005 | G68: 0.01 | H68: =IFERROR(1-G68/F68,"") -> -1 | I68: =IFERROR(E68*F68,"") -> 0.041607917 | K68: Coste de Producto | L68: =L64/L66*100 -> 26.945417 | M68: %
